Workbook
Name Child_Goal: '9'!$T$104:$T$109
Name HOME: #REF!
Name HOME2: #REF!
Name MF_TYPES: '[1]6'!$Q$5:$Q$7
Name MF_TYPES: '[1]6'!$Q$5:$Q$7
Name MF_TYPES: '3'!$S$5:$S$7
Name TaxSlab: '[1]6'!$P$5:$P$11
Name TaxSlab: '[1]6'!$P$5:$P$11
Name TaxSlab: '3'!$R$1:$R$7

Sheet Main Menu
A4: PERSONAL FINANCE CALCULATORS
A8: SIP & Lump Sum All in One | E8: Find out required amount of investment or wealth to be created for variety of scenarios | J8: What amount of investment you need to make to safeguard your retirement years | O8: Retirement Calculator
A12: SWP Calculator | E12: Check how Systematic Withdrawal Plan performs during distribution phase | J12: What if you increase the loan tenure and start SIP of the difference amt | O12: Home Loan Tenure & SIP Calculator
A16: SWP vs FD Interest | E16: How SWP is tax effective compared to Fixed Deposit interest payout - find out here | J16: Take care of your health cover, life cover and wealth creation in simplest manner | O16: 3 - in - 1 Calculator
A20: SIP + SWP | E20: Detailed analysis of wealth creation (SIP) & distribution (SWP) process | J20: Create multiple financial goals, plan retirement, cover health, life - all in one | O20: Quick Financial Plan
A24: Term Insurance Planning | E24: Get to know how much life cover you require based on expense replacement | J24: Find out wealth creation, reqd. investment, return, tenure - for SIP and lump sum | O24: Quick Calcys
A29: Prepared for: | C29: Client Name | J29: Prepared by: | L29: Partner Name
A30: Disclaimer: Result or output of these calculators are for representational purpose only. Assumptions made here, may or may not be appropriate considering your needs, priorities and risk profile. Check with an expert before taking any financial decision.

Sheet 1 (1)
V1: ="FV of SIP wealth after "&G14&" years" -> FV of SIP wealth after 20 years | Y1: =IF(G14+G15>50,0,VLOOKUP(G14,$V$9:$X$58,3,0)) -> 25507446
A2: BACK | B2: SIP & LUMP SUM - ALL IN ONE | V2: ="FV of SIP wealth after "&G14+G15&" years" -> FV of SIP wealth after 30 years | Y2: =FV($G$16,G15,,-Y1) -> 79222255
V3: ="FV of lump sum wealth after "&$G$14+$G$15&" years" -> FV of lump sum wealth after 30 years | Y3: =FV(G18,G14+G15,,-G17) -> 5991984.4
V4: ="FV of fixed SIP wealth after "&G14&" years" -> FV of fixed SIP wealth after 20 years | Y4: =FV((1+$G$16)^(1/12)-1,$G$14*12,-G9,,1) -> 18397147
D5: Future Wealth Creation | J5: Required Investment to Make
B7: How much wealth can be created? | V7: =IF(M17>M7,"SIP tenure cannot be more than goal tenure","") -> SIP tenure cannot be more than goal tenure
V8: YEARS | W8: SIP | X8: WEALTH | Y8: SIP INV AMT
B9: SIP amount (per month) | G9: 20000 | J9: YEAR | K9: MTHLY SIP AMT | M9: WEALTH @ END OF YEAR | V9: 1 | W9: =G9 -> 20000 | X9: =FV((1+$G$16)^(1/12)-1,12,-W9,,1) -> 255329.96 | Y9: =W9*12 -> 240000
B10: SIP top-up % (after every 12 months) | G10: 0.05 | J10: 1 | K10: =G9 -> 20000 | M10: =FV((1+$G$16)^(1/12)-1,12,-K10,IF(ISNUMBER(M9),-M9,0),1) -> 255329.96 | Q10: =J10<=$G$14 -> TRUE | R10: =J10="" -> FALSE | S10: =IF(R10=FALSE,IF(MOD(ROW(),2)=0,"WHITE","ORANGE")) -> WHITE | T10: =K10*12 -> 240000 | U10: =T10 -> 240000 | V10: 2 | W10: =IF(V10>$G$14,0, W9*(1+$G$10)) -> 21000 | X10: =IF(W10=0,0,FV((1+$G$16)^(1/12)-1,12,-W10,-X9,1)) -> 554066.01 | Y10: =W10*12 -> 252000
B11: SIP top-up amount (after every 12 months) | J11: =IF(J10="","",IF(J10+1>$G$14 + $G$15,"",J10+1)) -> 2 | K11: =IF(J11="","",IF(Q11, IF($G$13="Percentage", IF(OR(ISBLANK($G$12),$G$12=0),K10*(1+$G$10),IF(K10*(1+$G$10)>$G$12,K10,K10*(1+$G$10))), IF(OR(ISBLANK($G$12),$G$12=0),K10+$G$11, IF(K10+$G$11>$G$12,K10, K10+$G$11))), 0)) -> 21000 | M11: =IF(J11="","",FV((1+$G$16)^(1/12)-1,12,-K11,IF(ISNUMBER(M10),-M10,0),1)) -> 554066.01 | Q11: =J11<=$G$14 -> TRUE | R11: =J11="" -> FALSE | S11: =IF(R11=FALSE,IF(MOD(ROW(),2)=0,"WHITE","ORANGE")) -> ORANGE | T11: =K11*12 -> 252000 | U11: =U10+T11 -> 492000 | V11: 3 | W11: =IF(V11>$G$14,0, W10*(1+$G$10)) -> 22050 | X11: =IF(W11=0,0,FV((1+$G$16)^(1/12)-1,12,-W11,-X10,1)) -> 902055.21 | Y11: =W11*12 -> 264600
B12: Max SIP amount cap (for both - % or amount top-up) | J12: =IF(J11="","",IF(J11+1>$G$14 + $G$15,"",J11+1)) -> 3 | K12: =IF(J12="","",IF(Q12, IF($G$13="Percentage", IF(OR(ISBLANK($G$12),$G$12=0),K11*(1+$G$10),IF(K11*(1+$G$10)>$G$12,K11,K11*(1+$G$10))), IF(OR(ISBLANK($G$12),$G$12=0),K11+$G$11, IF(K11+$G$11>$G$12,K11, K11+$G$11))), 0)) -> 22050 | M12: =IF(J12="","",FV((1+$G$16)^(1/12)-1,12,-K12,IF(ISNUMBER(M11),-M11,0),1)) -> 902055.21 | Q12: =J12<=$G$14 -> TRUE | R12: =J12="" -> FALSE | S12: =IF(R12=FALSE,IF(MOD(ROW(),2)=0,"WHITE","ORANGE")) -> WHITE | T12: =K12*12 -> 264600 | U12: =U11+T12 -> 756600 | V12: 4 | W12: =IF(V12>$G$14,0, W11*(1+$G$10)) -> 23152.5 | X12: =IF(W12=0,0,FV((1+$G$16)^(1/12)-1,12,-W12,-X11,1)) -> 1305878.2 | Y12: =W12*12 -> 277830
B13: Here future value calculation is to be based on | G13: Percentage | J13: =IF(J12="","",IF(J12+1>$G$14 + $G$15,"",J12+1)) -> 4 | K13: =IF(J13="","",IF(Q13, IF($G$13="Percentage", IF(OR(ISBLANK($G$12),$G$12=0),K12*(1+$G$10),IF(K12*(1+$G$10)>$G$12,K12,K12*(1+$G$10))), IF(OR(ISBLANK($G$12),$G$12=0),K12+$G$11, IF(K12+$G$11>$G$12,K12, K12+$G$11))), 0)) -> 23152.5 | M13: =IF(J13="","",FV((1+$G$16)^(1/12)-1,12,-K13,IF(ISNUMBER(M12),-M12,0),1)) -> 1305878.2 | Q13: =J13<=$G$14 -> TRUE | R13: =J13="" -> FALSE | S13: =IF(R13=FALSE,IF(MOD(ROW(),2)=0,"WHITE","ORANGE")) -> ORANGE | T13: =K13*12 -> 277830 | U13: =U12+T13 -> 1034430 | V13: 5 | W13: =IF(V13>$G$14,0, W12*(1+$G$10)) -> 24310.125 | X13: =IF(W13=0,0,FV((1+$G$16)^(1/12)-1,12,-W13,-X12,1)) -> 1772938.7 | Y13: =W13*12 -> 291721.5
B14: Fresh SIP will continue for (no. of years) | G14: 20 | J14: =IF(J13="","",IF(J13+1>$G$14 + $G$15,"",J13+1)) -> 5 | K14: =IF(J14="","",IF(Q14, IF($G$13="Percentage", IF(OR(ISBLANK($G$12),$G$12=0),K13*(1+$G$10),IF(K13*(1+$G$10)>$G$12,K13,K13*(1+$G$10))), IF(OR(ISBLANK($G$12),$G$12=0),K13+$G$11, IF(K13+$G$11>$G$12,K13, K13+$G$11))), 0)) -> 24310.125 | M14: =IF(J14="","",FV((1+$G$16)^(1/12)-1,12,-K14,IF(ISNUMBER(M13),-M13,0),1)) -> 1772938.7 | Q14: =J14<=$G$14 -> TRUE | R14: =J14="" -> FALSE | S14: =IF(R14=FALSE,IF(MOD(ROW(),2)=0,"WHITE","ORANGE")) -> WHITE | T14: =K14*12 -> 291721.5 | U14: =U13+T14 -> 1326151.5 | V14: 6 | W14: =IF(V14>$G$14,0, W13*(1+$G$10)) -> 25525.631 | X14: =IF(W14=0,0,FV((1+$G$16)^(1/12)-1,12,-W14,-X13,1)) -> 2311564.3 | Y14: =W14*12 -> 306307.58
B15: Thereafter investment will be held for (no. of years) | G15: 10 | J15: =IF(J14="","",IF(J14+1>$G$14 + $G$15,"",J14+1)) -> 6 | K15: =IF(J15="","",IF(Q15, IF($G$13="Percentage", IF(OR(ISBLANK($G$12),$G$12=0),K14*(1+$G$10),IF(K14*(1+$G$10)>$G$12,K14,K14*(1+$G$10))), IF(OR(ISBLANK($G$12),$G$12=0),K14+$G$11, IF(K14+$G$11>$G$12,K14, K14+$G$11))), 0)) -> 25525.631 | M15: =IF(J15="","",FV((1+$G$16)^(1/12)-1,12,-K15,IF(ISNUMBER(M14),-M14,0),1)) -> 2311564.3 | Q15: =J15<=$G$14 -> TRUE | R15: =J15="" -> FALSE | S15: =IF(R15=FALSE,IF(MOD(ROW(),2)=0,"WHITE","ORANGE")) -> ORANGE | T15: =K15*12 -> 306307.58 | U15: =U14+T15 -> 1632459.1 | V15: 7 | W15: =IF(V15>$G$14,0, W14*(1+$G$10)) -> 26801.913 | X15: =IF(W15=0,0,FV((1+$G$16)^(1/12)-1,12,-W15,-X14,1)) -> 2931118.6 | Y15: =W15*12 -> 321622.95
B16: Expected return from SIP (p.a.) | G16: 0.12 | J16: =IF(J15="","",IF(J15+1>$G$14 + $G$15,"",J15+1)) -> 7 | K16: =IF(J16="","",IF(Q16, IF($G$13="Percentage", IF(OR(ISBLANK($G$12),$G$12=0),K15*(1+$G$10),IF(K15*(1+$G$10)>$G$12,K15,K15*(1+$G$10))), IF(OR(ISBLANK($G$12),$G$12=0),K15+$G$11, IF(K15+$G$11>$G$12,K15, K15+$G$11))), 0)) -> 26801.913 | M16: =IF(J16="","",FV((1+$G$16)^(1/12)-1,12,-K16,IF(ISNUMBER(M15),-M15,0),1)) -> 2931118.6 | Q16: =J16<=$G$14 -> TRUE | R16: =J16="" -> FALSE | S16: =IF(R16=FALSE,IF(MOD(ROW(),2)=0,"WHITE","ORANGE")) -> WHITE | T16: =K16*12 -> 321622.95 | U16: =U15+T16 -> 1954082 | V16: 8 | W16: =IF(V16>$G$14,0, W15*(1+$G$10)) -> 28142.008 | X16: =IF(W16=0,0,FV((1+$G$16)^(1/12)-1,12,-W16,-X15,1)) -> 3642127.7 | Y16: =W16*12 -> 337704.1
B17: Lump sum investment amount (if any) | G17: 200000 | J17: =IF(J16="","",IF(J16+1>$G$14 + $G$15,"",J16+1)) -> 8 | K17: =IF(J17="","",IF(Q17, IF($G$13="Percentage", IF(OR(ISBLANK($G$12),$G$12=0),K16*(1+$G$10),IF(K16*(1+$G$10)>$G$12,K16,K16*(1+$G$10))), IF(OR(ISBLANK($G$12),$G$12=0),K16+$G$11, IF(K16+$G$11>$G$12,K16, K16+$G$11))), 0)) -> 28142.008 | M17: =IF(J17="","",FV((1+$G$16)^(1/12)-1,12,-K17,IF(ISNUMBER(M16),-M16,0),1)) -> 3642127.7 | Q17: =J17<=$G$14 -> TRUE | R17: =J17="" -> FALSE | S17: =IF(R17=FALSE,IF(MOD(ROW(),2)=0,"WHITE","ORANGE")) -> ORANGE | T17: =K17*12 -> 337704.1 | U17: =U16+T17 -> 2291786.1 | V17: 9 | W17: =IF(V17>$G$14,0, W16*(1+$G$10)) -> 29549.109 | X17: =IF(W17=0,0,FV((1+$G$16)^(1/12)-1,12,-W17,-X16,1)) -> 4456421.6 | Y17: =W17*12 -> 354589.31
B18: Expected return from lump sum (p.a.) | G18: 0.12 | J18: =IF(J17="","",IF(J17+1>$G$14 + $G$15,"",J17+1)) -> 9 | K18: =IF(J18="","",IF(Q18, IF($G$13="Percentage", IF(OR(ISBLANK($G$12),$G$12=0),K17*(1+$G$10),IF(K17*(1+$G$10)>$G$12,K17,K17*(1+$G$10))), IF(OR(ISBLANK($G$12),$G$12=0),K17+$G$11, IF(K17+$G$11>$G$12,K17, K17+$G$11))), 0)) -> 29549.109 | M18: =IF(J18="","",FV((1+$G$16)^(1/12)-1,12,-K18,IF(ISNUMBER(M17),-M17,0),1)) -> 4456421.6 | Q18: =J18<=$G$14 -> TRUE | R18: =J18="" -> FALSE | S18: =IF(R18=FALSE,IF(MOD(ROW(),2)=0,"WHITE","ORANGE")) -> WHITE | T18: =K18*12 -> 354589.31 | U18: =U17+T18 -> 2646375.4 | V18: 10 | W18: =IF(V18>$G$14,0, W17*(1+$G$10)) -> 31026.564 | X18: =IF(W18=0,0,FV((1+$G$16)^(1/12)-1,12,-W18,-X17,1)) -> 5387292.8 | Y18: =W18*12 -> 372318.77
B19: =IF(G14+G15>50,"Total investment tenure cannot be more than 50 years","") | J19: =IF(J18="","",IF(J18+1>$G$14 + $G$15,"",J18+1)) -> 10 | K19: =IF(J19="","",IF(Q19, IF($G$13="Percentage", IF(OR(ISBLANK($G$12),$G$12=0),K18*(1+$G$10),IF(K18*(1+$G$10)>$G$12,K18,K18*(1+$G$10))), IF(OR(ISBLANK($G$12),$G$12=0),K18+$G$11, IF(K18+$G$11>$G$12,K18, K18+$G$11))), 0)) -> 31026.564 | M19: =IF(J19="","",FV((1+$G$16)^(1/12)-1,12,-K19,IF(ISNUMBER(M18),-M18,0),1)) -> 5387292.8 | Q19: =J19<=$G$14 -> TRUE | R19: =J19="" -> FALSE | S19: =IF(R19=FALSE,IF(MOD(ROW(),2)=0,"WHITE","ORANGE")) -> ORANGE | T19: =K19*12 -> 372318.77 | U19: =U18+T19 -> 3018694.2 | V19: 11 | W19: =IF(V19>$G$14,0, W18*(1+$G$10)) -> 32577.893 | X19: =IF(W19=0,0,FV((1+$G$16)^(1/12)-1,12,-W19,-X18,1)) -> 6449673.5 | Y19: =W19*12 -> 390934.71
D20: TOTAL INVESTMENT | F20: EXPECTED FUTURE VALUE | J20: =IF(J19="","",IF(J19+1>$G$14 + $G$15,"",J19+1)) -> 11 | K20: =IF(J20="","",IF(Q20, IF($G$13="Percentage", IF(OR(ISBLANK($G$12),$G$12=0),K19*(1+$G$10),IF(K19*(1+$G$10)>$G$12,K19,K19*(1+$G$10))), IF(OR(ISBLANK($G$12),$G$12=0),K19+$G$11, IF(K19+$G$11>$G$12,K19, K19+$G$11))), 0)) -> 32577.893 | M20: =IF(J20="","",FV((1+$G$16)^(1/12)-1,12,-K20,IF(ISNUMBER(M19),-M19,0),1)) -> 6449673.5 | Q20: =J20<=$G$14 -> TRUE | R20: =J20="" -> FALSE | S20: =IF(R20=FALSE,IF(MOD(ROW(),2)=0,"WHITE","ORANGE")) -> WHITE | T20: =K20*12 -> 390934.71 | U20: =U19+T20 -> 3409628.9 | V20: 12 | W20: =IF(V20>$G$14,0, W19*(1+$G$10)) -> 34206.787 | X20: =IF(W20=0,0,FV((1+$G$16)^(1/12)-1,12,-W20,-X19,1)) -> 7660335.2 | Y20: =W20*12 -> 410481.45
B21: TOP-UP SIP (A) | D21: =IF(OR(G14+G15>50,AND(OR(ISBLANK(G10),G10=0),OR(ISBLANK(G11),G11=0))),0,VLOOKUP(G14,$J$10:$U$60,12,0)) -> 7935829 | F21: =IF(OR(G14+G15>50,D21=0),0,VLOOKUP(G14+G15,J10:O60,4,0)) -> 79222255 | J21: =IF(J20="","",IF(J20+1>$G$14 + $G$15,"",J20+1)) -> 12 | K21: =IF(J21="","",IF(Q21, IF($G$13="Percentage", IF(OR(ISBLANK($G$12),$G$12=0),K20*(1+$G$10),IF(K20*(1+$G$10)>$G$12,K20,K20*(1+$G$10))), IF(OR(ISBLANK($G$12),$G$12=0),K20+$G$11, IF(K20+$G$11>$G$12,K20, K20+$G$11))), 0)) -> 34206.787 | M21: =IF(J21="","",FV((1+$G$16)^(1/12)-1,12,-K21,IF(ISNUMBER(M20),-M20,0),1)) -> 7660335.2 | Q21: =J21<=$G$14 -> TRUE | R21: =J21="" -> FALSE | S21: =IF(R21=FALSE,IF(MOD(ROW(),2)=0,"WHITE","ORANGE")) -> ORANGE | T21: =K21*12 -> 410481.45 | U21: =U20+T21 -> 3820110.4 | V21: 13 | W21: =IF(V21>$G$14,0, W20*(1+$G$10)) -> 35917.127 | X21: =IF(W21=0,0,FV((1+$G$16)^(1/12)-1,12,-W21,-X20,1)) -> 9038111.4 | Y21: =W21*12 -> 431005.52
B22: FIXED SIP (B) | D22: =G14*12*G9 -> 4800000 | F22: =FV(G16,G15,,-FV((1+G16)^(1/12)-1,G14*12,-G9,,1),1) -> 57138746 | J22: =IF(J21="","",IF(J21+1>$G$14 + $G$15,"",J21+1)) -> 13 | K22: =IF(J22="","",IF(Q22, IF($G$13="Percentage", IF(OR(ISBLANK($G$12),$G$12=0),K21*(1+$G$10),IF(K21*(1+$G$10)>$G$12,K21,K21*(1+$G$10))), IF(OR(ISBLANK($G$12),$G$12=0),K21+$G$11, IF(K21+$G$11>$G$12,K21, K21+$G$11))), 0)) -> 35917.127 | M22: =IF(J22="","",FV((1+$G$16)^(1/12)-1,12,-K22,IF(ISNUMBER(M21),-M21,0),1)) -> 9038111.4 | Q22: =J22<=$G$14 -> TRUE | R22: =J22="" -> FALSE | S22: =IF(R22=FALSE,IF(MOD(ROW(),2)=0,"WHITE","ORANGE")) -> WHITE | T22: =K22*12 -> 431005.52 | U22: =U21+T22 -> 4251115.9 | V22: 14 | W22: =IF(V22>$G$14,0, W21*(1+$G$10)) -> 37712.983 | X22: =IF(W22=0,0,FV((1+$G$16)^(1/12)-1,12,-W22,-X21,1)) -> 10604147 | Y22: =W22*12 -> 452555.79
B23: DIFFERENCE (A - B) | D23: =IF(OR(G14+G15>50,D21=0),0,D21-D22) -> 3135829 | F23: =IF(OR(G14+G15>50,D21=0),0,F21-F22) -> 22083509 | J23: =IF(J22="","",IF(J22+1>$G$14 + $G$15,"",J22+1)) -> 14 | K23: =IF(J23="","",IF(Q23, IF($G$13="Percentage", IF(OR(ISBLANK($G$12),$G$12=0),K22*(1+$G$10),IF(K22*(1+$G$10)>$G$12,K22,K22*(1+$G$10))), IF(OR(ISBLANK($G$12),$G$12=0),K22+$G$11, IF(K22+$G$11>$G$12,K22, K22+$G$11))), 0)) -> 37712.983 | M23: =IF(J23="","",FV((1+$G$16)^(1/12)-1,12,-K23,IF(ISNUMBER(M22),-M22,0),1)) -> 10604147 | Q23: =J23<=$G$14 -> TRUE | R23: =J23="" -> FALSE | S23: =IF(R23=FALSE,IF(MOD(ROW(),2)=0,"WHITE","ORANGE")) -> ORANGE | T23: =K23*12 -> 452555.79 | U23: =U22+T23 -> 4703671.7 | V23: 15 | W23: =IF(V23>$G$14,0, W22*(1+$G$10)) -> 39598.632 | X23: =IF(W23=0,0,FV((1+$G$16)^(1/12)-1,12,-W23,-X22,1)) -> 12382181 | Y23: =W23*12 -> 475183.58
B24: LUMP SUM (C) | D24: =G17 -> 200000 | F24: =FV(G18,G14+G15,,-G17) -> 5991984.4 | J24: =IF(J23="","",IF(J23+1>$G$14 + $G$15,"",J23+1)) -> 15 | K24: =IF(J24="","",IF(Q24, IF($G$13="Percentage", IF(OR(ISBLANK($G$12),$G$12=0),K23*(1+$G$10),IF(K23*(1+$G$10)>$G$12,K23,K23*(1+$G$10))), IF(OR(ISBLANK($G$12),$G$12=0),K23+$G$11, IF(K23+$G$11>$G$12,K23, K23+$G$11))), 0)) -> 39598.632 | M24: =IF(J24="","",FV((1+$G$16)^(1/12)-1,12,-K24,IF(ISNUMBER(M23),-M23,0),1)) -> 12382181 | Q24: =J24<=$G$14 -> TRUE | R24: =J24="" -> FALSE | S24: =IF(R24=FALSE,IF(MOD(ROW(),2)=0,"WHITE","ORANGE")) -> WHITE | T24: =K24*12 -> 475183.58 | U24: =U23+T24 -> 5178855.3 | V24: 16 | W24: =IF(V24>$G$14,0, W23*(1+$G$10)) -> 41578.564 | X24: =IF(W24=0,0,FV((1+$G$16)^(1/12)-1,12,-W24,-X23,1)) -> 14398855 | Y24: =W24*12 -> 498942.76
B25: LUMP SUM + SIP(A) | D25: =D21+D24 -> 8135829 | F25: =F24+F21 -> 85214240 | J25: =IF(J24="","",IF(J24+1>$G$14 + $G$15,"",J24+1)) -> 16 | K25: =IF(J25="","",IF(Q25, IF($G$13="Percentage", IF(OR(ISBLANK($G$12),$G$12=0),K24*(1+$G$10),IF(K24*(1+$G$10)>$G$12,K24,K24*(1+$G$10))), IF(OR(ISBLANK($G$12),$G$12=0),K24+$G$11, IF(K24+$G$11>$G$12,K24, K24+$G$11))), 0)) -> 41578.564 | M25: =IF(J25="","",FV((1+$G$16)^(1/12)-1,12,-K25,IF(ISNUMBER(M24),-M24,0),1)) -> 14398855 | Q25: =J25<=$G$14 -> TRUE | R25: =J25="" -> FALSE | S25: =IF(R25=FALSE,IF(MOD(ROW(),2)=0,"WHITE","ORANGE")) -> ORANGE | T25: =K25*12 -> 498942.76 | U25: =U24+T25 -> 5677798 | V25: 17 | W25: =IF(V25>$G$14,0, W24*(1+$G$10)) -> 43657.492 | X25: =IF(W25=0,0,FV((1+$G$16)^(1/12)-1,12,-W25,-X24,1)) -> 16684071 | Y25: =W25*12 -> 523889.9
B26: LUMP SUM + SIP(B) | D26: =D24+D22 -> 5000000 | F26: =F24+F22 -> 63130731 | J26: =IF(J25="","",IF(J25+1>$G$14 + $G$15,"",J25+1)) -> 17 | K26: =IF(J26="","",IF(Q26, IF($G$13="Percentage", IF(OR(ISBLANK($G$12),$G$12=0),K25*(1+$G$10),IF(K25*(1+$G$10)>$G$12,K25,K25*(1+$G$10))), IF(OR(ISBLANK($G$12),$G$12=0),K25+$G$11, IF(K25+$G$11>$G$12,K25, K25+$G$11))), 0)) -> 43657.492 | M26: =IF(J26="","",FV((1+$G$16)^(1/12)-1,12,-K26,IF(ISNUMBER(M25),-M25,0),1)) -> 16684071 | Q26: =J26<=$G$14 -> TRUE | R26: =J26="" -> FALSE | S26: =IF(R26=FALSE,IF(MOD(ROW(),2)=0,"WHITE","ORANGE")) -> WHITE | T26: =K26*12 -> 523889.9 | U26: =U25+T26 -> 6201687.9 | V26: 18 | W26: =IF(V26>$G$14,0, W25*(1+$G$10)) -> 45840.366 | X26: =IF(W26=0,0,FV((1+$G$16)^(1/12)-1,12,-W26,-X25,1)) -> 19271381 | Y26: =W26*12 -> 550084.4
H27: ="Dated: "& TEXT(TODAY(),"DD-MMM-YYYY") -> Dated: 28-Aug-2025 | J27: =IF(J26="","",IF(J26+1>$G$14 + $G$15,"",J26+1)) -> 18 | K27: =IF(J27="","",IF(Q27, IF($G$13="Percentage", IF(OR(ISBLANK($G$12),$G$12=0),K26*(1+$G$10),IF(K26*(1+$G$10)>$G$12,K26,K26*(1+$G$10))), IF(OR(ISBLANK($G$12),$G$12=0),K26+$G$11, IF(K26+$G$11>$G$12,K26, K26+$G$11))), 0)) -> 45840.366 | M27: =IF(J27="","",FV((1+$G$16)^(1/12)-1,12,-K27,IF(ISNUMBER(M26),-M26,0),1)) -> 19271381 | Q27: =J27<=$G$14 -> TRUE | R27: =J27="" -> FALSE | S27: =IF(R27=FALSE,IF(MOD(ROW(),2)=0,"WHITE","ORANGE")) -> ORANGE | T27: =K27*12 -> 550084.4 | U27: =U26+T27 -> 6751772.3 | V27: 19 | W27: =IF(V27>$G$14,0, W26*(1+$G$10)) -> 48132.385 | X27: =IF(W27=0,0,FV((1+$G$16)^(1/12)-1,12,-W27,-X26,1)) -> 22198428 | Y27: =W27*12 -> 577588.62
B28: Prepared for: | D28: =" "&UPPER('Main Menu'!C29) -> CLIENT NAME | J28: =IF(J27="","",IF(J27+1>$G$14 + $G$15,"",J27+1)) -> 19 | K28: =IF(J28="","",IF(Q28, IF($G$13="Percentage", IF(OR(ISBLANK($G$12),$G$12=0),K27*(1+$G$10),IF(K27*(1+$G$10)>$G$12,K27,K27*(1+$G$10))), IF(OR(ISBLANK($G$12),$G$12=0),K27+$G$11, IF(K27+$G$11>$G$12,K27, K27+$G$11))), 0)) -> 48132.385 | M28: =IF(J28="","",FV((1+$G$16)^(1/12)-1,12,-K28,IF(ISNUMBER(M27),-M27,0),1)) -> 22198428 | Q28: =J28<=$G$14 -> TRUE | R28: =J28="" -> FALSE | S28: =IF(R28=FALSE,IF(MOD(ROW(),2)=0,"WHITE","ORANGE")) -> WHITE | T28: =K28*12 -> 577588.62 | U28: =U27+T28 -> 7329360.9 | V28: 20 | W28: =IF(V28>$G$14,0, W27*(1+$G$10)) -> 50539.004 | X28: =IF(W28=0,0,FV((1+$G$16)^(1/12)-1,12,-W28,-X27,1)) -> 25507446 | Y28: =W28*12 -> 606468.05
B29: Prepared by: | D29: =" "&UPPER('Main Menu'!L29) -> PARTNER NAME | J29: =IF(J28="","",IF(J28+1>$G$14 + $G$15,"",J28+1)) -> 20 | K29: =IF(J29="","",IF(Q29, IF($G$13="Percentage", IF(OR(ISBLANK($G$12),$G$12=0),K28*(1+$G$10),IF(K28*(1+$G$10)>$G$12,K28,K28*(1+$G$10))), IF(OR(ISBLANK($G$12),$G$12=0),K28+$G$11, IF(K28+$G$11>$G$12,K28, K28+$G$11))), 0)) -> 50539.004 | M29: =IF(J29="","",FV((1+$G$16)^(1/12)-1,12,-K29,IF(ISNUMBER(M28),-M28,0),1)) -> 25507446 | Q29: =J29<=$G$14 -> TRUE | R29: =J29="" -> FALSE | S29: =IF(R29=FALSE,IF(MOD(ROW(),2)=0,"WHITE","ORANGE")) -> ORANGE | T29: =K29*12 -> 606468.05 | U29: =U28+T29 -> 7935829 | V29: 21 | W29: =IF(V29>$G$14,0, W28*(1+$G$10)) -> 0 | X29: =IF(W29=0,0,FV((1+$G$16)^(1/12)-1,12,-W29,-X28,1)) -> 0 | Y29: =W29*12 -> 0
J30: =IF(J29="","",IF(J29+1>$G$14 + $G$15,"",J29+1)) -> 21 | K30: =IF(J30="","",IF(Q30, IF($G$13="Percentage", IF(OR(ISBLANK($G$12),$G$12=0),K29*(1+$G$10),IF(K29*(1+$G$10)>$G$12,K29,K29*(1+$G$10))), IF(OR(ISBLANK($G$12),$G$12=0),K29+$G$11, IF(K29+$G$11>$G$12,K29, K29+$G$11))), 0)) -> 0 | M30: =IF(J30="","",FV((1+$G$16)^(1/12)-1,12,-K30,IF(ISNUMBER(M29),-M29,0),1)) -> 28568340 | Q30: =J30<=$G$14 -> FALSE | R30: =J30="" -> FALSE | S30: =IF(R30=FALSE,IF(MOD(ROW(),2)=0,"WHITE","ORANGE")) -> WHITE | T30: =K30*12 -> 0 | U30: =U29+T30 -> 7935829 | V30: 22 | W30: =IF(V30>$G$14,0, W29*(1+$G$10)) -> 0 | X30: =IF(W30=0,0,FV((1+$G$16)^(1/12)-1,12,-W30,-X29,1)) -> 0 | Y30: =W30*12 -> 0
J31: =IF(J30="","",IF(J30+1>$G$14 + $G$15,"",J30+1)) -> 22 | K31: =IF(J31="","",IF(Q31, IF($G$13="Percentage", IF(OR(ISBLANK($G$12),$G$12=0),K30*(1+$G$10),IF(K30*(1+$G$10)>$G$12,K30,K30*(1+$G$10))), IF(OR(ISBLANK($G$12),$G$12=0),K30+$G$11, IF(K30+$G$11>$G$12,K30, K30+$G$11))), 0)) -> 0 | M31: =IF(J31="","",FV((1+$G$16)^(1/12)-1,12,-K31,IF(ISNUMBER(M30),-M30,0),1)) -> 31996540 | Q31: =J31<=$G$14 -> FALSE | R31: =J31="" -> FALSE | S31: =IF(R31=FALSE,IF(MOD(ROW(),2)=0,"WHITE","ORANGE")) -> ORANGE | T31: =K31*12 -> 0 | U31: =U30+T31 -> 7935829 | V31: 23 | W31: =IF(V31>$G$14,0, W30*(1+$G$10)) -> 0 | X31: =IF(W31=0,0,FV((1+$G$16)^(1/12)-1,12,-W31,-X30,1)) -> 0 | Y31: =W31*12 -> 0
J32: =IF(J31="","",IF(J31+1>$G$14 + $G$15,"",J31+1)) -> 23 | K32: =IF(J32="","",IF(Q32, IF($G$13="Percentage", IF(OR(ISBLANK($G$12),$G$12=0),K31*(1+$G$10),IF(K31*(1+$G$10)>$G$12,K31,K31*(1+$G$10))), IF(OR(ISBLANK($G$12),$G$12=0),K31+$G$11, IF(K31+$G$11>$G$12,K31, K31+$G$11))), 0)) -> 0 | M32: =IF(J32="","",FV((1+$G$16)^(1/12)-1,12,-K32,IF(ISNUMBER(M31),-M31,0),1)) -> 35836125 | Q32: =J32<=$G$14 -> FALSE | R32: =J32="" -> FALSE | S32: =IF(R32=FALSE,IF(MOD(ROW(),2)=0,"WHITE","ORANGE")) -> WHITE | T32: =K32*12 -> 0 | U32: =U31+T32 -> 7935829 | V32: 24 | W32: =IF(V32>$G$14,0, W31*(1+$G$10)) -> 0 | X32: =IF(W32=0,0,FV((1+$G$16)^(1/12)-1,12,-W32,-X31,1)) -> 0 | Y32: =W32*12 -> 0
J33: =IF(J32="","",IF(J32+1>$G$14 + $G$15,"",J32+1)) -> 24 | K33: =IF(J33="","",IF(Q33, IF($G$13="Percentage", IF(OR(ISBLANK($G$12),$G$12=0),K32*(1+$G$10),IF(K32*(1+$G$10)>$G$12,K32,K32*(1+$G$10))), IF(OR(ISBLANK($G$12),$G$12=0),K32+$G$11, IF(K32+$G$11>$G$12,K32, K32+$G$11))), 0)) -> 0 | M33: =IF(J33="","",FV((1+$G$16)^(1/12)-1,12,-K33,IF(ISNUMBER(M32),-M32,0),1)) -> 40136460 | Q33: =J33<=$G$14 -> FALSE | R33: =J33="" -> FALSE | S33: =IF(R33=FALSE,IF(MOD(ROW(),2)=0,"WHITE","ORANGE")) -> ORANGE | T33: =K33*12 -> 0 | U33: =U32+T33 -> 7935829 | V33: 25 | W33: =IF(V33>$G$14,0, W32*(1+$G$10)) -> 0 | X33: =IF(W33=0,0,FV((1+$G$16)^(1/12)-1,12,-W33,-X32,1)) -> 0 | Y33: =W33*12 -> 0
J34: =IF(J33="","",IF(J33+1>$G$14 + $G$15,"",J33+1)) -> 25 | K34: =IF(J34="","",IF(Q34, IF($G$13="Percentage", IF(OR(ISBLANK($G$12),$G$12=0),K33*(1+$G$10),IF(K33*(1+$G$10)>$G$12,K33,K33*(1+$G$10))), IF(OR(ISBLANK($G$12),$G$12=0),K33+$G$11, IF(K33+$G$11>$G$12,K33, K33+$G$11))), 0)) -> 0 | M34: =IF(J34="","",FV((1+$G$16)^(1/12)-1,12,-K34,IF(ISNUMBER(M33),-M33,0),1)) -> 44952835 | Q34: =J34<=$G$14 -> FALSE | R34: =J34="" -> FALSE | S34: =IF(R34=FALSE,IF(MOD(ROW(),2)=0,"WHITE","ORANGE")) -> WHITE | T34: =K34*12 -> 0 | U34: =U33+T34 -> 7935829 | V34: 26 | W34: =IF(V34>$G$14,0, W33*(1+$G$10)) -> 0 | X34: =IF(W34=0,0,FV((1+$G$16)^(1/12)-1,12,-W34,-X33,1)) -> 0 | Y34: =W34*12 -> 0
J35: =IF(J34="","",IF(J34+1>$G$14 + $G$15,"",J34+1)) -> 26 | K35: =IF(J35="","",IF(Q35, IF($G$13="Percentage", IF(OR(ISBLANK($G$12),$G$12=0),K34*(1+$G$10),IF(K34*(1+$G$10)>$G$12,K34,K34*(1+$G$10))), IF(OR(ISBLANK($G$12),$G$12=0),K34+$G$11, IF(K34+$G$11>$G$12,K34, K34+$G$11))), 0)) -> 0 | M35: =IF(J35="","",FV((1+$G$16)^(1/12)-1,12,-K35,IF(ISNUMBER(M34),-M34,0),1)) -> 50347176 | Q35: =J35<=$G$14 -> FALSE | R35: =J35="" -> FALSE | S35: =IF(R35=FALSE,IF(MOD(ROW(),2)=0,"WHITE","ORANGE")) -> ORANGE | T35: =K35*12 -> 0 | U35: =U34+T35 -> 7935829 | V35: 27 | W35: =IF(V35>$G$14,0, W34*(1+$G$10)) -> 0 | X35: =IF(W35=0,0,FV((1+$G$16)^(1/12)-1,12,-W35,-X34,1)) -> 0 | Y35: =W35*12 -> 0
J36: =IF(J35="","",IF(J35+1>$G$14 + $G$15,"",J35+1)) -> 27 | K36: =IF(J36="","",IF(Q36, IF($G$13="Percentage", IF(OR(ISBLANK($G$12),$G$12=0),K35*(1+$G$10),IF(K35*(1+$G$10)>$G$12,K35,K35*(1+$G$10))), IF(OR(ISBLANK($G$12),$G$12=0),K35+$G$11, IF(K35+$G$11>$G$12,K35, K35+$G$11))), 0)) -> 0 | M36: =IF(J36="","",FV((1+$G$16)^(1/12)-1,12,-K36,IF(ISNUMBER(M35),-M35,0),1)) -> 56388837 | Q36: =J36<=$G$14 -> FALSE | R36: =J36="" -> FALSE | S36: =IF(R36=FALSE,IF(MOD(ROW(),2)=0,"WHITE","ORANGE")) -> WHITE | T36: =K36*12 -> 0 | U36: =U35+T36 -> 7935829 | V36: 28 | W36: =IF(V36>$G$14,0, W35*(1+$G$10)) -> 0 | X36: =IF(W36=0,0,FV((1+$G$16)^(1/12)-1,12,-W36,-X35,1)) -> 0 | Y36: =W36*12 -> 0
J37: =IF(J36="","",IF(J36+1>$G$14 + $G$15,"",J36+1)) -> 28 | K37: =IF(J37="","",IF(Q37, IF($G$13="Percentage", IF(OR(ISBLANK($G$12),$G$12=0),K36*(1+$G$10),IF(K36*(1+$G$10)>$G$12,K36,K36*(1+$G$10))), IF(OR(ISBLANK($G$12),$G$12=0),K36+$G$11, IF(K36+$G$11>$G$12,K36, K36+$G$11))), 0)) -> 0 | M37: =IF(J37="","",FV((1+$G$16)^(1/12)-1,12,-K37,IF(ISNUMBER(M36),-M36,0),1)) -> 63155497 | Q37: =J37<=$G$14 -> FALSE | R37: =J37="" -> FALSE | S37: =IF(R37=FALSE,IF(MOD(ROW(),2)=0,"WHITE","ORANGE")) -> ORANGE | T37: =K37*12 -> 0 | U37: =U36+T37 -> 7935829 | V37: 29 | W37: =IF(V37>$G$14,0, W36*(1+$G$10)) -> 0 | X37: =IF(W37=0,0,FV((1+$G$16)^(1/12)-1,12,-W37,-X36,1)) -> 0 | Y37: =W37*12 -> 0
J38: =IF(J37="","",IF(J37+1>$G$14 + $G$15,"",J37+1)) -> 29 | K38: =IF(J38="","",IF(Q38, IF($G$13="Percentage", IF(OR(ISBLANK($G$12),$G$12=0),K37*(1+$G$10),IF(K37*(1+$G$10)>$G$12,K37,K37*(1+$G$10))), IF(OR(ISBLANK($G$12),$G$12=0),K37+$G$11, IF(K37+$G$11>$G$12,K37, K37+$G$11))), 0)) -> 0 | M38: =IF(J38="","",FV((1+$G$16)^(1/12)-1,12,-K38,IF(ISNUMBER(M37),-M37,0),1)) -> 70734157 | Q38: =J38<=$G$14 -> FALSE | R38: =J38="" -> FALSE | S38: =IF(R38=FALSE,IF(MOD(ROW(),2)=0,"WHITE","ORANGE")) -> WHITE | T38: =K38*12 -> 0 | U38: =U37+T38 -> 7935829 | V38: 30 | W38: =IF(V38>$G$14,0, W37*(1+$G$10)) -> 0 | X38: =IF(W38=0,0,FV((1+$G$16)^(1/12)-1,12,-W38,-X37,1)) -> 0 | Y38: =W38*12 -> 0
J39: =IF(J38="","",IF(J38+1>$G$14 + $G$15,"",J38+1)) -> 30 | K39: =IF(J39="","",IF(Q39, IF($G$13="Percentage", IF(OR(ISBLANK($G$12),$G$12=0),K38*(1+$G$10),IF(K38*(1+$G$10)>$G$12,K38,K38*(1+$G$10))), IF(OR(ISBLANK($G$12),$G$12=0),K38+$G$11, IF(K38+$G$11>$G$12,K38, K38+$G$11))), 0)) -> 0 | M39: =IF(J39="","",FV((1+$G$16)^(1/12)-1,12,-K39,IF(ISNUMBER(M38),-M38,0),1)) -> 79222255 | Q39: =J39<=$G$14 -> FALSE | R39: =J39="" -> FALSE | S39: =IF(R39=FALSE,IF(MOD(ROW(),2)=0,"WHITE","ORANGE")) -> ORANGE | T39: =K39*12 -> 0 | U39: =U38+T39 -> 7935829 | V39: 31 | W39: =IF(V39>$G$14,0, W38*(1+$G$10)) -> 0 | X39: =IF(W39=0,0,FV((1+$G$16)^(1/12)-1,12,-W39,-X38,1)) -> 0 | Y39: =W39*12 -> 0
J40: =IF(J39="","",IF(J39+1>$G$14 + $G$15,"",J39+1)) | K40: =IF(J40="","",IF(Q40, IF($G$13="Percentage", IF(OR(ISBLANK($G$12),$G$12=0),K39*(1+$G$10),IF(K39*(1+$G$10)>$G$12,K39,K39*(1+$G$10))), IF(OR(ISBLANK($G$12),$G$12=0),K39+$G$11, IF(K39+$G$11>$G$12,K39, K39+$G$11))), 0)) | M40: =IF(J40="","",FV((1+$G$16)^(1/12)-1,12,-K40,IF(ISNUMBER(M39),-M39,0),1)) | Q40: =J40<=$G$14 -> FALSE | R40: =J40="" -> TRUE | S40: =IF(R40=FALSE,IF(MOD(ROW(),2)=0,"WHITE","ORANGE")) -> FALSE | T40: =K40*12 -> #VALUE! | U40: =U39+T40 -> #VALUE! | V40: 32 | W40: =IF(V40>$G$14,0, W39*(1+$G$10)) -> 0 | X40: =IF(W40=0,0,FV((1+$G$16)^(1/12)-1,12,-W40,-X39,1)) -> 0 | Y40: =W40*12 -> 0
J41: =IF(J40="","",IF(J40+1>$G$14 + $G$15,"",J40+1)) | K41: =IF(J41="","",IF(Q41, IF($G$13="Percentage", IF(OR(ISBLANK($G$12),$G$12=0),K40*(1+$G$10),IF(K40*(1+$G$10)>$G$12,K40,K40*(1+$G$10))), IF(OR(ISBLANK($G$12),$G$12=0),K40+$G$11, IF(K40+$G$11>$G$12,K40, K40+$G$11))), 0)) | M41: =IF(J41="","",FV((1+$G$16)^(1/12)-1,12,-K41,IF(ISNUMBER(M40),-M40,0),1)) | Q41: =J41<=$G$14 -> FALSE | R41: =J41="" -> TRUE | S41: =IF(R41=FALSE,IF(MOD(ROW(),2)=0,"WHITE","ORANGE")) -> FALSE | T41: =K41*12 -> #VALUE! | U41: =U40+T41 -> #VALUE! | V41: 33 | W41: =IF(V41>$G$14,0, W40*(1+$G$10)) -> 0 | X41: =IF(W41=0,0,FV((1+$G$16)^(1/12)-1,12,-W41,-X40,1)) -> 0 | Y41: =W41*12 -> 0
... J58: =IF(J57="","",IF(J57+1>$G$14 + $G$15,"",J57+1)) | K58: =IF(J58="","",IF(Q58, IF($G$13="Percentage", IF(OR(ISBLANK($G$12),$G$12=0),K57*(1+$G$10),IF(K57*(1+$G$10)>$G$12,K57,K57*(1+$G$10))), IF(OR(ISBLANK($G$12),$G$12=0),K57+$G$11, IF(K57+$G$11>$G$12,K57, K57+$G$11))), 0)) | M58: =IF(J58="","",FV((1+$G$16)^(1/12)-1,12,-K58,IF(ISNUMBER(M57),-M57,0),1)) | Q58: =J58<=$G$14 -> FALSE | R58: =J58="" -> TRUE | S58: =IF(R58=FALSE,IF(MOD(ROW(),2)=0,"WHITE","ORANGE")) -> FALSE | T58: =K58*12 -> #VALUE! | U58: =U57+T58 -> #VALUE! | V58: 50 | W58: =IF(V58>$G$14,0, W57*(1+$G$10)) -> 0 | X58: =IF(W58=0,0,FV((1+$G$16)^(1/12)-1,12,-W58,-X57,1)) -> 0 | Y58: =W58*12 -> 0
J59: =IF(J58="","",IF(J58+1>$G$14 + $G$15,"",J58+1)) | K59: =IF(J59="","",IF(Q59, IF($G$13="Percentage", IF(OR(ISBLANK($G$12),$G$12=0),K58*(1+$G$10),IF(K58*(1+$G$10)>$G$12,K58,K58*(1+$G$10))), IF(OR(ISBLANK($G$12),$G$12=0),K58+$G$11, IF(K58+$G$11>$G$12,K58, K58+$G$11))), 0)) | M59: =IF(J59="","",FV((1+$G$16)^(1/12)-1,12,-K59,IF(ISNUMBER(M58),-M58,0),1)) | Q59: =J59<=$G$14 -> FALSE | R59: =J59="" -> TRUE | S59: =IF(R59=FALSE,IF(MOD(ROW(),2)=0,"WHITE","ORANGE")) -> FALSE | T59: =K59*12 -> #VALUE! | U59: =U58+T59 -> #VALUE!
J60: =IF(J59="","",IF(J59+1>$G$14 + $G$15,"",J59+1)) | K60: =IF(J60="","",IF(Q60, IF($G$13="Percentage", IF(OR(ISBLANK($G$12),$G$12=0),K59*(1+$G$10),IF(K59*(1+$G$10)>$G$12,K59,K59*(1+$G$10))), IF(OR(ISBLANK($G$12),$G$12=0),K59+$G$11, IF(K59+$G$11>$G$12,K59, K59+$G$11))), 0)) | M60: =IF(J60="","",FV((1+$G$16)^(1/12)-1,12,-K60,IF(ISNUMBER(M59),-M59,0),1)) | Q60: =J60<=$G$14 -> FALSE | R60: =J60="" -> TRUE | S60: =IF(R60=FALSE,IF(MOD(ROW(),2)=0,"WHITE","ORANGE")) -> FALSE | T60: =K60*12 -> #VALUE! | U60: =U59+T60 -> #VALUE!

Sheet 1 (2)
A2: BACK | B2: SIP & LUMP SUM - ALL IN ONE
D5: Future Wealth Creation | J5: Required Investment to Make
B7: How much investment is required?
T8: YEARS | U8: SIP INVESTMENT | V8: WEALTH
B9: Goal is due after (no. of years) | G9: 20 | J9: YEAR | K9: MTHLY SIP AMT | M9: WEALTH @ END OF YEAR | T9: 1 | U9: 100 | V9: =FV((1+$G$12)^(1/12)-1,12,-U9,,1) -> 1276.6498
B10: Cost of goal as of today | G10: 1000000 | J10: 1 | K10: =G20 -> 3811.4822 | M10: =FV((1+$G$12)^(1/12)-1,12,-K10,IF(ISNUMBER(M9),-M9,0),1) -> 48659.279 | Q10: =J10<=$G$19 -> TRUE | R10: =J10="" -> FALSE | S10: =IF(R10=FALSE,IF(MOD(ROW(),2)=0,"WHITE","ORANGE")) -> WHITE | T10: 2 | U10: =U9*(1+$G$18) -> 110 | V10: =FV((1+$G$12)^(1/12)-1,12,-U10,-V9,1) -> 2834.1625
B11: Assumed inflation for the goal | G11: 0.07 | J11: =IF(J10="","",IF(J10+1>$G$9,"",J10+1)) -> 2 | K11: =IF(J11="","",IF(Q11,K10*(1+$G$18),0)) -> 4192.6304 | M11: =IF(J11="","",FV((1+$G$12)^(1/12)-1,12,-K11,IF(ISNUMBER(M10),-M10,0),1)) -> 108023.6 | Q11: =J11<=$G$19 -> TRUE | R11: =J11="" -> FALSE | S11: =IF(R11=FALSE,IF(MOD(ROW(),2)=0,"WHITE","ORANGE")) -> ORANGE | T11: 3 | U11: =U10*(1+$G$18) -> 121 | V11: =FV((1+$G$12)^(1/12)-1,12,-U11,-V10,1) -> 4719.0083
B12: Expected return from new investment | G12: 0.12 | J12: =IF(J11="","",IF(J11+1>$G$9,"",J11+1)) -> 3 | K12: =IF(J12="","",IF(Q12,K11*(1+$G$18),0)) -> 4611.8934 | M12: =IF(J12="","",FV((1+$G$12)^(1/12)-1,12,-K12,IF(ISNUMBER(M11),-M11,0),1)) -> 179864.16 | Q12: =J12<=$G$19 -> TRUE | R12: =J12="" -> FALSE | S12: =IF(R12=FALSE,IF(MOD(ROW(),2)=0,"WHITE","ORANGE")) -> WHITE | T12: 4 | U12: =U11*(1+$G$18) -> 133.1 | V12: =FV((1+$G$12)^(1/12)-1,12,-U12,-V11,1) -> 6984.5102
B13: Value of assets linked to this goal | G13: 0 | J13: =IF(J12="","",IF(J12+1>$G$9,"",J12+1)) -> 4 | K13: =IF(J13="","",IF(Q13,K12*(1+$G$18),0)) -> 5073.0828 | M13: =IF(J13="","",FV((1+$G$12)^(1/12)-1,12,-K13,IF(ISNUMBER(M12),-M12,0),1)) -> 266213.36 | Q13: =J13<=$G$19 -> TRUE | R13: =J13="" -> FALSE | S13: =IF(R13=FALSE,IF(MOD(ROW(),2)=0,"WHITE","ORANGE")) -> ORANGE | T13: 5 | U13: =U12*(1+$G$18) -> 146.41 | V13: =FV((1+$G$12)^(1/12)-1,12,-U13,-V12,1) -> 9691.7943
B14: Assumed return from linked assets | G14: 0.1 | J14: =IF(J13="","",IF(J13+1>$G$9,"",J13+1)) -> 5 | K14: =IF(J14="","",IF(Q14,K13*(1+$G$18),0)) -> 5580.3911 | M14: =IF(J14="","",FV((1+$G$12)^(1/12)-1,12,-K14,IF(ISNUMBER(M13),-M13,0),1)) -> 369401.01 | Q14: =J14<=$G$19 -> TRUE | R14: =J14="" -> FALSE | S14: =IF(R14=FALSE,IF(MOD(ROW(),2)=0,"WHITE","ORANGE")) -> WHITE | T14: 6 | U14: =U13*(1+$G$18) -> 161.051 | V14: =FV((1+$G$12)^(1/12)-1,12,-U14,-V13,1) -> 12910.867
B15: FUTURE VALUE OF THE GOAL | G15: =FV(G11,G9,,-G10) -> 3869684.5 | J15: =IF(J14="","",IF(J14+1>$G$9,"",J14+1)) -> 6 | K15: =IF(J15="","",IF(Q15,K14*(1+$G$18),0)) -> 6138.4302 | M15: =IF(J15="","",FV((1+$G$12)^(1/12)-1,12,-K15,IF(ISNUMBER(M14),-M14,0),1)) -> 492095.39 | Q15: =J15<=$G$19 -> TRUE | R15: =J15="" -> FALSE | S15: =IF(R15=FALSE,IF(MOD(ROW(),2)=0,"WHITE","ORANGE")) -> ORANGE | T15: 7 | U15: =U14*(1+$G$18) -> 177.1561 | V15: =FV((1+$G$12)^(1/12)-1,12,-U15,-V14,1) -> 16721.834
J16: =IF(J15="","",IF(J15+1>$G$9,"",J15+1)) -> 7 | K16: =IF(J16="","",IF(Q16,K15*(1+$G$18),0)) -> 6752.2732 | M16: =IF(J16="","",FV((1+$G$12)^(1/12)-1,12,-K16,IF(ISNUMBER(M15),-M15,0),1)) -> 637349.72 | Q16: =J16<=$G$19 -> TRUE | R16: =J16="" -> FALSE | S16: =IF(R16=FALSE,IF(MOD(ROW(),2)=0,"WHITE","ORANGE")) -> WHITE | T16: 8 | U16: =U15*(1+$G$18) -> 194.87171 | V16: =FV((1+$G$12)^(1/12)-1,12,-U16,-V15,1) -> 21216.283
B17: REQUIRED LUMP SUM INVESTMENT | G17: =-PV(G12,G9,,G15-FV(G14,G9,,-G13),) -> 401157.67 | J17: =IF(J16="","",IF(J16+1>$G$9,"",J16+1)) -> 8 | K17: =IF(J17="","",IF(Q17,K16*(1+$G$18),0)) -> 7427.5005 | M17: =IF(J17="","",FV((1+$G$12)^(1/12)-1,12,-K17,IF(ISNUMBER(M16),-M16,0),1)) -> 808654.86 | Q17: =J17<=$G$19 -> TRUE | R17: =J17="" -> FALSE | S17: =IF(R17=FALSE,IF(MOD(ROW(),2)=0,"WHITE","ORANGE")) -> ORANGE | T17: 9 | U17: =U16*(1+$G$18) -> 214.35888 | V17: =FV((1+$G$12)^(1/12)-1,12,-U17,-V16,1) -> 26498.849
B18: SIP top-up % (after every 12 months) | G18: 0.1 | J18: =IF(J17="","",IF(J17+1>$G$9,"",J17+1)) -> 9 | K18: =IF(J18="","",IF(Q18,K17*(1+$G$18),0)) -> 8170.2505 | M18: =IF(J18="","",FV((1+$G$12)^(1/12)-1,12,-K18,IF(ISNUMBER(M17),-M17,0),1)) -> 1009998.9 | Q18: =J18<=$G$19 -> TRUE | R18: =J18="" -> FALSE | S18: =IF(R18=FALSE,IF(MOD(ROW(),2)=0,"WHITE","ORANGE")) -> WHITE | T18: 10 | U18: =U17*(1+$G$18) -> 235.79477 | V18: =FV((1+$G$12)^(1/12)-1,12,-U18,-V17,1) -> 32688.985
B19: Fresh SIP investment will continue for | G19: 10 | J19: =IF(J18="","",IF(J18+1>$G$9,"",J18+1)) -> 10 | K19: =IF(J19="","",IF(Q19,K18*(1+$G$18),0)) -> 8987.2756 | M19: =IF(J19="","",FV((1+$G$12)^(1/12)-1,12,-K19,IF(ISNUMBER(M18),-M18,0),1)) -> 1245934.8 | Q19: =J19<=$G$19 -> TRUE | R19: =J19="" -> FALSE | S19: =IF(R19=FALSE,IF(MOD(ROW(),2)=0,"WHITE","ORANGE")) -> ORANGE | T19: 11 | U19: =U18*(1+$G$18) -> 259.37425 | V19: =FV((1+$G$12)^(1/12)-1,12,-U19,-V18,1) -> 39922.964
B20: REQUIRED SIP INVESTMENT | G20: =IF(G19>G9, 0, IF(OR(ISBLANK(G19),G19=0),(100/VLOOKUP(G9,T9:V58,3,0))*(G15-FV(G14,G9,,-G13)), (100/VLOOKUP(G19,T9:V58,3,0))*-PV(G12,G9-G19,,(G15-FV(G14,G9,,-G13)),))) -> 3811.4822 | J20: =IF(J19="","",IF(J19+1>$G$9,"",J19+1)) -> 11 | K20: =IF(J20="","",IF(Q20,K19*(1+$G$18),0)) -> 0 | M20: =IF(J20="","",FV((1+$G$12)^(1/12)-1,12,-K20,IF(ISNUMBER(M19),-M19,0),1)) -> 1395447 | Q20: =J20<=$G$19 -> FALSE | R20: =J20="" -> FALSE | S20: =IF(R20=FALSE,IF(MOD(ROW(),2)=0,"WHITE","ORANGE")) -> WHITE | T20: 12 | U20: =U19*(1+$G$18) -> 285.31167 | V20: =FV((1+$G$12)^(1/12)-1,12,-U20,-V19,1) -> 48356.15
B21: =IF(G19>G9,"SIP tenure cannot be more than the goal tenure","") | J21: =IF(J20="","",IF(J20+1>$G$9,"",J20+1)) -> 12 | K21: =IF(J21="","",IF(Q21,K20*(1+$G$18),0)) -> 0 | M21: =IF(J21="","",FV((1+$G$12)^(1/12)-1,12,-K21,IF(ISNUMBER(M20),-M20,0),1)) -> 1562900.7 | Q21: =J21<=$G$19 -> FALSE | R21: =J21="" -> FALSE | S21: =IF(R21=FALSE,IF(MOD(ROW(),2)=0,"WHITE","ORANGE")) -> ORANGE | T21: 13 | U21: =U20*(1+$G$18) -> 313.84284 | V21: =FV((1+$G$12)^(1/12)-1,12,-U21,-V20,1) -> 58165.562
J22: =IF(J21="","",IF(J21+1>$G$9,"",J21+1)) -> 13 | K22: =IF(J22="","",IF(Q22,K21*(1+$G$18),0)) -> 0 | M22: =IF(J22="","",FV((1+$G$12)^(1/12)-1,12,-K22,IF(ISNUMBER(M21),-M21,0),1)) -> 1750448.7 | Q22: =J22<=$G$19 -> FALSE | R22: =J22="" -> FALSE | S22: =IF(R22=FALSE,IF(MOD(ROW(),2)=0,"WHITE","ORANGE")) -> WHITE | T22: 14 | U22: =U21*(1+$G$18) -> 345.22712 | V22: =FV((1+$G$12)^(1/12)-1,12,-U22,-V21,1) -> 69552.771
B23: Prepared for: | D23: =" "&UPPER('Main Menu'!C29) -> CLIENT NAME | J23: =IF(J22="","",IF(J22+1>$G$9,"",J22+1)) -> 14 | K23: =IF(J23="","",IF(Q23,K22*(1+$G$18),0)) -> 0 | M23: =IF(J23="","",FV((1+$G$12)^(1/12)-1,12,-K23,IF(ISNUMBER(M22),-M22,0),1)) -> 1960502.6 | Q23: =J23<=$G$19 -> FALSE | R23: =J23="" -> FALSE | S23: =IF(R23=FALSE,IF(MOD(ROW(),2)=0,"WHITE","ORANGE")) -> ORANGE | T23: 15 | U23: =U22*(1+$G$18) -> 379.74983 | V23: =FV((1+$G$12)^(1/12)-1,12,-U23,-V22,1) -> 82747.179
B24: Prepared by: | D24: =" "&UPPER('Main Menu'!L29) -> PARTNER NAME | J24: =IF(J23="","",IF(J23+1>$G$9,"",J23+1)) -> 15 | K24: =IF(J24="","",IF(Q24,K23*(1+$G$18),0)) -> 0 | M24: =IF(J24="","",FV((1+$G$12)^(1/12)-1,12,-K24,IF(ISNUMBER(M23),-M23,0),1)) -> 2195762.9 | Q24: =J24<=$G$19 -> FALSE | R24: =J24="" -> FALSE | S24: =IF(R24=FALSE,IF(MOD(ROW(),2)=0,"WHITE","ORANGE")) -> WHITE | T24: 16 | U24: =U23*(1+$G$18) -> 417.72482 | V24: =FV((1+$G$12)^(1/12)-1,12,-U24,-V23,1) -> 98009.723
G25: ="Dated: "& TEXT(TODAY(),"DD-MMM-YYYY") -> Dated: 28-Aug-2025 | J25: =IF(J24="","",IF(J24+1>$G$9,"",J24+1)) -> 16 | K25: =IF(J25="","",IF(Q25,K24*(1+$G$18),0)) -> 0 | M25: =IF(J25="","",FV((1+$G$12)^(1/12)-1,12,-K25,IF(ISNUMBER(M24),-M24,0),1)) -> 2459254.4 | Q25: =J25<=$G$19 -> FALSE | R25: =J25="" -> FALSE | S25: =IF(R25=FALSE,IF(MOD(ROW(),2)=0,"WHITE","ORANGE")) -> ORANGE | T25: 17 | U25: =U24*(1+$G$18) -> 459.4973 | V25: =FV((1+$G$12)^(1/12)-1,12,-U25,-V24,1) -> 115637.06
J26: =IF(J25="","",IF(J25+1>$G$9,"",J25+1)) -> 17 | K26: =IF(J26="","",IF(Q26,K25*(1+$G$18),0)) -> 0 | M26: =IF(J26="","",FV((1+$G$12)^(1/12)-1,12,-K26,IF(ISNUMBER(M25),-M25,0),1)) -> 2754365 | Q26: =J26<=$G$19 -> FALSE | R26: =J26="" -> FALSE | S26: =IF(R26=FALSE,IF(MOD(ROW(),2)=0,"WHITE","ORANGE")) -> WHITE | T26: 18 | U26: =U25*(1+$G$18) -> 505.44703 | V26: =FV((1+$G$12)^(1/12)-1,12,-U26,-V25,1) -> 135966.3
J27: =IF(J26="","",IF(J26+1>$G$9,"",J26+1)) -> 18 | K27: =IF(J27="","",IF(Q27,K26*(1+$G$18),0)) -> 0 | M27: =IF(J27="","",FV((1+$G$12)^(1/12)-1,12,-K27,IF(ISNUMBER(M26),-M26,0),1)) -> 3084888.8 | Q27: =J27<=$G$19 -> FALSE | R27: =J27="" -> FALSE | S27: =IF(R27=FALSE,IF(MOD(ROW(),2)=0,"WHITE","ORANGE")) -> ORANGE | T27: 19 | U27: =U26*(1+$G$18) -> 555.99173 | V27: =FV((1+$G$12)^(1/12)-1,12,-U27,-V26,1) -> 159380.32
J28: =IF(J27="","",IF(J27+1>$G$9,"",J27+1)) -> 19 | K28: =IF(J28="","",IF(Q28,K27*(1+$G$18),0)) -> 0 | M28: =IF(J28="","",FV((1+$G$12)^(1/12)-1,12,-K28,IF(ISNUMBER(M27),-M27,0),1)) -> 3455075.4 | Q28: =J28<=$G$19 -> FALSE | R28: =J28="" -> FALSE | S28: =IF(R28=FALSE,IF(MOD(ROW(),2)=0,"WHITE","ORANGE")) -> WHITE | T28: 20 | U28: =U27*(1+$G$18) -> 611.5909 | V28: =FV((1+$G$12)^(1/12)-1,12,-U28,-V27,1) -> 186313.83
J29: =IF(J28="","",IF(J28+1>$G$9,"",J28+1)) -> 20 | K29: =IF(J29="","",IF(Q29,K28*(1+$G$18),0)) -> 0 | M29: =IF(J29="","",FV((1+$G$12)^(1/12)-1,12,-K29,IF(ISNUMBER(M28),-M28,0),1)) -> 3869684.5 | Q29: =J29<=$G$19 -> FALSE | R29: =J29="" -> FALSE | S29: =IF(R29=FALSE,IF(MOD(ROW(),2)=0,"WHITE","ORANGE")) -> ORANGE | T29: 21 | U29: =U28*(1+$G$18) -> 672.74999 | V29: =FV((1+$G$12)^(1/12)-1,12,-U29,-V28,1) -> 217260.15
J30: =IF(J29="","",IF(J29+1>$G$9,"",J29+1)) | K30: =IF(J30="","",IF(Q30,K29*(1+$G$18),0)) | M30: =IF(J30="","",FV((1+$G$12)^(1/12)-1,12,-K30,IF(ISNUMBER(M29),-M29,0),1)) | Q30: =J30<=$G$19 -> FALSE | R30: =J30="" -> TRUE | S30: =IF(R30=FALSE,IF(MOD(ROW(),2)=0,"WHITE","ORANGE")) -> FALSE | T30: 22 | U30: =U29*(1+$G$18) -> 740.02499 | V30: =FV((1+$G$12)^(1/12)-1,12,-U30,-V29,1) -> 252778.9
J31: =IF(J30="","",IF(J30+1>$G$9,"",J30+1)) | K31: =IF(J31="","",IF(Q31,K30*(1+$G$18),0)) | M31: =IF(J31="","",FV((1+$G$12)^(1/12)-1,12,-K31,IF(ISNUMBER(M30),-M30,0),1)) | Q31: =J31<=$G$19 -> FALSE | R31: =J31="" -> TRUE | S31: =IF(R31=FALSE,IF(MOD(ROW(),2)=0,"WHITE","ORANGE")) -> FALSE | T31: 23 | U31: =U30*(1+$G$18) -> 814.02749 | V31: =FV((1+$G$12)^(1/12)-1,12,-U31,-V30,1) -> 293504.65
J32: =IF(J31="","",IF(J31+1>$G$9,"",J31+1)) | K32: =IF(J32="","",IF(Q32,K31*(1+$G$18),0)) | M32: =IF(J32="","",FV((1+$G$12)^(1/12)-1,12,-K32,IF(ISNUMBER(M31),-M31,0),1)) | Q32: =J32<=$G$19 -> FALSE | R32: =J32="" -> TRUE | S32: =IF(R32=FALSE,IF(MOD(ROW(),2)=0,"WHITE","ORANGE")) -> FALSE | T32: 24 | U32: =U31*(1+$G$18) -> 895.43024 | V32: =FV((1+$G$12)^(1/12)-1,12,-U32,-V31,1) -> 340156.71
J33: =IF(J32="","",IF(J32+1>$G$9,"",J32+1)) | K33: =IF(J33="","",IF(Q33,K32*(1+$G$18),0)) | M33: =IF(J33="","",FV((1+$G$12)^(1/12)-1,12,-K33,IF(ISNUMBER(M32),-M32,0),1)) | Q33: =J33<=$G$19 -> FALSE | R33: =J33="" -> TRUE | S33: =IF(R33=FALSE,IF(MOD(ROW(),2)=0,"WHITE","ORANGE")) -> FALSE | T33: 25 | U33: =U32*(1+$G$18) -> 984.97327 | V33: =FV((1+$G$12)^(1/12)-1,12,-U33,-V32,1) -> 393550.18
J34: =IF(J33="","",IF(J33+1>$G$9,"",J33+1)) | K34: =IF(J34="","",IF(Q34,K33*(1+$G$18),0)) | M34: =IF(J34="","",FV((1+$G$12)^(1/12)-1,12,-K34,IF(ISNUMBER(M33),-M33,0),1)) | Q34: =J34<=$G$19 -> FALSE | R34: =J34="" -> TRUE | S34: =IF(R34=FALSE,IF(MOD(ROW(),2)=0,"WHITE","ORANGE")) -> FALSE | T34: 26 | U34: =U33*(1+$G$18) -> 1083.4706 | V34: =FV((1+$G$12)^(1/12)-1,12,-U34,-V33,1) -> 454608.33
J35: =IF(J34="","",IF(J34+1>$G$9,"",J34+1)) | K35: =IF(J35="","",IF(Q35,K34*(1+$G$18),0)) | M35: =IF(J35="","",FV((1+$G$12)^(1/12)-1,12,-K35,IF(ISNUMBER(M34),-M34,0),1)) | Q35: =J35<=$G$19 -> FALSE | R35: =J35="" -> TRUE | S35: =IF(R35=FALSE,IF(MOD(ROW(),2)=0,"WHITE","ORANGE")) -> FALSE | T35: 27 | U35: =U34*(1+$G$18) -> 1191.8177 | V35: =FV((1+$G$12)^(1/12)-1,12,-U35,-V34,1) -> 524376.66
J36: =IF(J35="","",IF(J35+1>$G$9,"",J35+1)) | K36: =IF(J36="","",IF(Q36,K35*(1+$G$18),0)) | M36: =IF(J36="","",FV((1+$G$12)^(1/12)-1,12,-K36,IF(ISNUMBER(M35),-M35,0),1)) | Q36: =J36<=$G$19 -> FALSE | R36: =J36="" -> TRUE | S36: =IF(R36=FALSE,IF(MOD(ROW(),2)=0,"WHITE","ORANGE")) -> FALSE | T36: 28 | U36: =U35*(1+$G$18) -> 1310.9994 | V36: =FV((1+$G$12)^(1/12)-1,12,-U36,-V35,1) -> 604038.73
J37: =IF(J36="","",IF(J36+1>$G$9,"",J36+1)) | K37: =IF(J37="","",IF(Q37,K36*(1+$G$18),0)) | M37: =IF(J37="","",FV((1+$G$12)^(1/12)-1,12,-K37,IF(ISNUMBER(M36),-M36,0),1)) | Q37: =J37<=$G$19 -> FALSE | R37: =J37="" -> TRUE | S37: =IF(R37=FALSE,IF(MOD(ROW(),2)=0,"WHITE","ORANGE")) -> FALSE | T37: 29 | U37: =U36*(1+$G$18) -> 1442.0994 | V37: =FV((1+$G$12)^(1/12)-1,12,-U37,-V36,1) -> 694933.94
... J58: =IF(J57="","",IF(J57+1>$G$9,"",J57+1)) | K58: =IF(J58="","",IF(Q58,K57*(1+$G$18),0)) | M58: =IF(J58="","",FV((1+$G$12)^(1/12)-1,12,-K58,IF(ISNUMBER(M57),-M57,0),1)) | Q58: =J58<=$G$19 -> FALSE | R58: =J58="" -> TRUE | S58: =IF(R58=FALSE,IF(MOD(ROW(),2)=0,"WHITE","ORANGE")) -> FALSE | T58: 50 | U58: =U57*(1+$G$18) -> 10671.896 | V58: =FV((1+$G$12)^(1/12)-1,12,-U58,-V57,1) -> 10954379
J59: =IF(J58="","",IF(J58+1>$G$9,"",J58+1)) | K59: =IF(J59="","",IF(Q59,K58*(1+$G$18),0)) | M59: =IF(J59="","",FV((1+$G$12)^(1/12)-1,12,-K59,IF(ISNUMBER(M58),-M58,0),1)) | Q59: =J59<=$G$19 -> FALSE | R59: =J59="" -> TRUE | S59: =IF(R59=FALSE,IF(MOD(ROW(),2)=0,"WHITE","ORANGE")) -> FALSE
J60: =IF(J59="","",IF(J59+1>$G$9,"",J59+1)) | K60: =IF(J60="","",IF(Q60,K59*(1+$G$18),0)) | M60: =IF(J60="","",FV((1+$G$12)^(1/12)-1,12,-K60,IF(ISNUMBER(M59),-M59,0),1)) | Q60: =J60<=$G$19 -> FALSE | R60: =J60="" -> TRUE | S60: =IF(R60=FALSE,IF(MOD(ROW(),2)=0,"WHITE","ORANGE")) -> FALSE

Sheet 2
A2: BACK | B2: SWP REGULAR INCOME GENERATION
I4: ASSET ALLOCATION FOR WITHDRAWAL PHASE:
B5: Current corpus | F5: 30000000 | I5: PORTFOLIO ALLOCATION | L5: AMOUNT | N5: EXP. RETURN
B6: Current monthly requirement | F6: 150000 | I6: Liquidity | K6: 0.1 | L6: =$F$5*K6 -> 3000000 | N6: 0.06
B7: Assumed inflation | F7: 0.06 | I7: Safety | K7: 0.3 | L7: =$F$5*K7 -> 9000000 | N7: 0.08
B8: Current age | F8: 45 | I8: Growth | K8: 0.6 | L8: =$F$5*K8 -> 18000000 | N8: 0.15
B9: Withdrawal start age | F9: 50 | I9: Portfolio weighted average return | N9: =SUMPRODUCT(L6:L8,N6:N8)/SUM(L6:L8) -> 0.12
B10: Assumed return till withdrawal starts | F10: 0.08 | I10: Portfolio would continue till the age of | N10: {=IFERROR(INDEX(B17:B66,MATCH(1,Q17:Q66,0)-2),">"&B17+49)} -> >99
B12: Prepared for: | D12: =" "&UPPER('Main Menu'!C29) -> CLIENT NAME
B13: Prepared by: | D13: =" "&UPPER('Main Menu'!L29) -> PARTNER NAME | I13: ="Dated: "& TEXT(TODAY(),"DD-MMM-YYYY") -> Dated: 28-Aug-2025
B14: The chart on the right hand side shows the end-of-year corpus for first 25 years à
B15: AGE | C15: START OF THE YEAR CORPUS | E15: WITHDRAWAL | I15: END OF THE YEAR CORPUS
E16: YEARLY | G16: MONTHLY
B17: =F9 -> 50 | C17: =IF(F9>F8,FV(F10,F9-F8,,-F5),F5) -> 44079842 | E17: =IF(F9>F8,FV(F7,F9-F8,,-F6)*12,12*F6) -> 2408806 | G17: =E17/12 -> 200733.84 | I17: =FV($N$9,1,,-(C17-E17)) -> 46671561 | P17: =B17="" -> FALSE | Q17: =P17*1 -> 0 | T17: =IF(ISBLANK(I17),0,IF(I17>=$F$5,0,1)) -> 0
B18: =IF(OR(I17<=0,B17=""),"",B17+1) -> 51 | C18: =IF(I17<=0,"",I17) -> 46671561 | E18: =IF(C18="","",E17*(1+$F$7)) -> 2553334.4 | G18: =IF(E18="","",E18/12) -> 212777.87 | I18: =IF(G18="","",FV($N$9,1,,-(C18-E18))) -> 49412413 | P18: =B18="" -> FALSE | Q18: =P18*1 -> 0 | T18: =IF(ISBLANK(I18),0,IF(I18>=$F$5,0,1)) -> 0
B19: =IF(OR(I18<=0,B18=""),"",B18+1) -> 52 | C19: =IF(I18<=0,"",I18) -> 49412413 | E19: =IF(C19="","",E18*(1+$F$7)) -> 2706534.5 | G19: =IF(E19="","",E19/12) -> 225544.54 | I19: =IF(G19="","",FV($N$9,1,,-(C19-E19))) -> 52310584 | P19: =B19="" -> FALSE | Q19: =P19*1 -> 0 | T19: =IF(ISBLANK(I19),0,IF(I19>=$F$5,0,1)) -> 0
B20: =IF(OR(I19<=0,B19=""),"",B19+1) -> 53 | C20: =IF(I19<=0,"",I19) -> 52310584 | E20: =IF(C20="","",E19*(1+$F$7)) -> 2868926.5 | G20: =IF(E20="","",E20/12) -> 239077.21 | I20: =IF(G20="","",FV($N$9,1,,-(C20-E20))) -> 55374657 | P20: =B20="" -> FALSE | Q20: =P20*1 -> 0 | T20: =IF(ISBLANK(I20),0,IF(I20>=$F$5,0,1)) -> 0
B21: =IF(OR(I20<=0,B20=""),"",B20+1) -> 54 | C21: =IF(I20<=0,"",I20) -> 55374657 | E21: =IF(C21="","",E20*(1+$F$7)) -> 3041062.1 | G21: =IF(E21="","",E21/12) -> 253421.84 | I21: =IF(G21="","",FV($N$9,1,,-(C21-E21))) -> 58613626 | P21: =B21="" -> FALSE | Q21: =P21*1 -> 0 | T21: =IF(ISBLANK(I21),0,IF(I21>=$F$5,0,1)) -> 0
B22: =IF(OR(I21<=0,B21=""),"",B21+1) -> 55 | C22: =IF(I21<=0,"",I21) -> 58613626 | E22: =IF(C22="","",E21*(1+$F$7)) -> 3223525.9 | G22: =IF(E22="","",E22/12) -> 268627.15 | I22: =IF(G22="","",FV($N$9,1,,-(C22-E22))) -> 62036912 | P22: =B22="" -> FALSE | Q22: =P22*1 -> 0 | T22: =IF(ISBLANK(I22),0,IF(I22>=$F$5,0,1)) -> 0
B23: =IF(OR(I22<=0,B22=""),"",B22+1) -> 56 | C23: =IF(I22<=0,"",I22) -> 62036912 | E23: =IF(C23="","",E22*(1+$F$7)) -> 3416937.4 | G23: =IF(E23="","",E23/12) -> 284744.78 | I23: =IF(G23="","",FV($N$9,1,,-(C23-E23))) -> 65654372 | P23: =B23="" -> FALSE | Q23: =P23*1 -> 0 | T23: =IF(ISBLANK(I23),0,IF(I23>=$F$5,0,1)) -> 0
B24: =IF(OR(I23<=0,B23=""),"",B23+1) -> 57 | C24: =IF(I23<=0,"",I23) -> 65654372 | E24: =IF(C24="","",E23*(1+$F$7)) -> 3621953.6 | G24: =IF(E24="","",E24/12) -> 301829.47 | I24: =IF(G24="","",FV($N$9,1,,-(C24-E24))) -> 69476308 | P24: =B24="" -> FALSE | Q24: =P24*1 -> 0 | T24: =IF(ISBLANK(I24),0,IF(I24>=$F$5,0,1)) -> 0
B25: =IF(OR(I24<=0,B24=""),"",B24+1) -> 58 | C25: =IF(I24<=0,"",I24) -> 69476308 | E25: =IF(C25="","",E24*(1+$F$7)) -> 3839270.9 | G25: =IF(E25="","",E25/12) -> 319939.24 | I25: =IF(G25="","",FV($N$9,1,,-(C25-E25))) -> 73513482 | P25: =B25="" -> FALSE | Q25: =P25*1 -> 0 | T25: =IF(ISBLANK(I25),0,IF(I25>=$F$5,0,1)) -> 0
B26: =IF(OR(I25<=0,B25=""),"",B25+1) -> 59 | C26: =IF(I25<=0,"",I25) -> 73513482 | E26: =IF(C26="","",E25*(1+$F$7)) -> 4069627.1 | G26: =IF(E26="","",E26/12) -> 339135.59 | I26: =IF(G26="","",FV($N$9,1,,-(C26-E26))) -> 77777117 | P26: =B26="" -> FALSE | Q26: =P26*1 -> 0 | T26: =IF(ISBLANK(I26),0,IF(I26>=$F$5,0,1)) -> 0
B27: =IF(OR(I26<=0,B26=""),"",B26+1) -> 60 | C27: =IF(I26<=0,"",I26) -> 77777117 | E27: =IF(C27="","",E26*(1+$F$7)) -> 4313804.7 | G27: =IF(E27="","",E27/12) -> 359483.73 | I27: =IF(G27="","",FV($N$9,1,,-(C27-E27))) -> 82278910 | P27: =B27="" -> FALSE | Q27: =P27*1 -> 0 | T27: =IF(ISBLANK(I27),0,IF(I27>=$F$5,0,1)) -> 0
B28: =IF(OR(I27<=0,B27=""),"",B27+1) -> 61 | C28: =IF(I27<=0,"",I27) -> 82278910 | E28: =IF(C28="","",E27*(1+$F$7)) -> 4572633 | G28: =IF(E28="","",E28/12) -> 381052.75 | I28: =IF(G28="","",FV($N$9,1,,-(C28-E28))) -> 87031030 | P28: =B28="" -> FALSE | Q28: =P28*1 -> 0 | T28: =IF(ISBLANK(I28),0,IF(I28>=$F$5,0,1)) -> 0
B29: =IF(OR(I28<=0,B28=""),"",B28+1) -> 62 | C29: =IF(I28<=0,"",I28) -> 87031030 | E29: =IF(C29="","",E28*(1+$F$7)) -> 4846991 | G29: =IF(E29="","",E29/12) -> 403915.92 | I29: =IF(G29="","",FV($N$9,1,,-(C29-E29))) -> 92046124 | P29: =B29="" -> FALSE | Q29: =P29*1 -> 0 | T29: =IF(ISBLANK(I29),0,IF(I29>=$F$5,0,1)) -> 0
... B66: =IF(OR(I65<=0,B65=""),"",B65+1) -> 99 | C66: =IF(I65<=0,"",I65) -> 5.5312479e+08 | E66: =IF(C66="","",E65*(1+$F$7)) -> 41859037 | G66: =IF(E66="","",E66/12) -> 3488253.1 | I66: =IF(G66="","",FV($N$9,1,,-(C66-E66))) -> 5.7261765e+08 | P66: =B66="" -> FALSE | Q66: =P66*1 -> 0 | T66: =IF(ISBLANK(I66),0,IF(I66>=$F$5,0,1)) -> 0

Sheet 3
R1: 0
A2: BACK | B2: SWP VS INTEREST PAYOUT | R2: 0.052
R3: 0.104 | T3: 8.43
R4: 0.156 | T4: 8.43
B5: Investment amount | H5: 10000000 | J5: Mutual Fund type | N5: Equity | R5: 0.208 | S5: Equity | T5: =SUM(T3:T4) -> 16.86
B6: Assumed MF return | H6: 0.08 | R6: 0.26 | S6: Debt
B7: Assumed FD return | H7: 0.08 | J7: Withdrawal % from MF | N7: Similar to FD | R7: 0.312 | S7: Other
B8: Tax slab | H8: 0.312 | J8: Withdrawal % from Mutual Fund | N8: 0.1
B9: Mutual Fund Types: Equity (equity exposure >= 65%), Other (equity exposure >35% and <65%) and Debt (equity exposure <= 35%)
B10: Prepared for: | D10: =" "&UPPER('Main Menu'!C29) -> CLIENT NAME | I10: Prepared by: | K10: =" "&UPPER('Main Menu'!L29) -> PARTNER NAME | M10: r
N11: ="Dated: "& TEXT(TODAY(),"DD-MMM-YYYY") -> Dated: 28-Aug-2025
B12: Comparison is to be done for how many years? | H12: 10 | K12: ="i.e."&H12&" financial years including purchase and sale year" -> i.e.10 financial years including purchase and sale year | R12: Assumed inflation | V12: 0.07
B14: MUTUAL FUND SWP TAXATION (YEARLY) | J14: FIXED DEPOSIT INTEREST TAXATION (YEARLY) | R14: =SUM(R18:S22) -> 3860418.1 | T14: =SUM(T17:U21) -> 3088406.5
B15: YEAR | C15: WITHDRAWAL FROM MF | E15: TAX TYPE | F15: TOTAL TAX PAID | H15: EFFECTIVE TAX RATE | J15: WITHDRAWAL FROM FD | L15: TOTAL TAX PAID | N15: EFFECTIVE TAX RATE | R15: FD WITHDRAWAL | T15: MF WITHDRAWAL | U15: MF WITHDRAWAL% | X15: =IF(N7="Diff. than FD",N8,H7) -> 0.08
U16: Amount Withdrawn (MF) | X16: =$H$5*((1+$X$15)^(1/12)-1) -> 64340.301
B17: TOTAL | C17: =SUM(C18:D42) -> 7720836.1 | F17: =SUM(F18:F42) -> 296089.65 | H17: =F17/C17 -> 0.038349428 | J17: =SUM(J18:K42) -> 7720836.1 | L17: =SUM(L18:M42) -> 2408900.9 | N17: =L17/J17 -> 0.312
B18: 1 | C18: =IF(B18="","",T18) -> 772083.61 | E18: =IF(B18="","",IF(AND($N$5="Equity", B18=1), "STCG", IF($N$5="Debt", "NA", IF(AND($N$5="Other", B18<3), "STCG", "LTCG")))) -> STCG | F18: =IF(B18="","",SUMIFS($G$49:$G$348,$Y$49:$Y$348,"="&B18)) -> 5911.1284 | H18: =IF(B18="","",IF(T18=0,"",F18/T18)) -> 0.0076560728 | J18: =IF(B18="","",R18) -> 772083.61 | L18: =IF(B18="","",R18*$H$8) -> 240890.09 | N18: =IF(B18="","",L18/R18) -> 0.312 | R18: =12*$J$49 -> 772083.61 | T18: =SUMIFS($T$49:$T$108,$B$49:$B$108,"<="&12) -> 772083.61 | U18: 0
B19: =IF(B18="","",IF(B18+1<=$H$12,B18+1,"")) -> 2 | C19: =IF(B19="","",T19) -> 772083.61 | E19: =IF(B19="","",IF(AND($N$5="Equity", B19=1), "STCG", IF($N$5="Debt", "NA", IF(AND($N$5="Other", B19<3), "STCG", "LTCG")))) -> LTCG | F19: =IF(B19="","",SUMIFS($G$49:$G$348,$Y$49:$Y$348,"="&B19)) -> 10776.57 | H19: =IF(B19="","",IF(T19=0,"",F19/T19)) -> 0.013957775 | J19: =IF(B19="","",R19) -> 772083.61 | L19: =IF(B19="","",R19*$H$8) -> 240890.09 | N19: =IF(B19="","",L19/R19) -> 0.312 | R19: =12*$J$49 -> 772083.61 | T19: =SUMIFS($T$49:$T$348,$B$49:$B$348,">"&U19, $B$49:$B$348, "<="&(U19+12)) -> 772083.61 | U19: 12
B20: =IF(B19="","",IF(B19+1<=$H$12,B19+1,"")) -> 3 | C20: =IF(B20="","",T20) -> 772083.61 | E20: =IF(B20="","",IF(AND($N$5="Equity", B20=1), "STCG", IF($N$5="Debt", "NA", IF(AND($N$5="Other", B20<3), "STCG", "LTCG")))) -> LTCG | F20: =IF(B20="","",SUMIFS($G$49:$G$348,$Y$49:$Y$348,"="&B20)) -> 17127.228 | H20: =IF(B20="","",IF(T20=0,"",F20/T20)) -> 0.022183125 | J20: =IF(B20="","",R20) -> 772083.61 | L20: =IF(B20="","",R20*$H$8) -> 240890.09 | N20: =IF(B20="","",L20/R20) -> 0.312 | R20: =12*$J$49 -> 772083.61 | T20: =SUMIFS($T$49:$T$348,$B$49:$B$348,">"&U20, $B$49:$B$348, "<="&(U20+12)) -> 772083.61 | U20: 24
B21: =IF(B20="","",IF(B20+1<=$H$12,B20+1,"")) -> 4 | C21: =IF(B21="","",T21) -> 772083.61 | E21: =IF(B21="","",IF(AND($N$5="Equity", B21=1), "STCG", IF($N$5="Debt", "NA", IF(AND($N$5="Other", B21<3), "STCG", "LTCG")))) -> LTCG | F21: =IF(B21="","",SUMIFS($G$49:$G$348,$Y$49:$Y$348,"="&B21)) -> 23007.466 | H21: =IF(B21="","",IF(T21=0,"",F21/T21)) -> 0.02979919 | J21: =IF(B21="","",R21) -> 772083.61 | L21: =IF(B21="","",R21*$H$8) -> 240890.09 | N21: =IF(B21="","",L21/R21) -> 0.312 | R21: =12*$J$49 -> 772083.61 | T21: =SUMIFS($T$49:$T$348,$B$49:$B$348,">"&U21, $B$49:$B$348, "<="&(U21+12)) -> 772083.61 | U21: 36
B22: =IF(B21="","",IF(B21+1<=$H$12,B21+1,"")) -> 5 | C22: =IF(B22="","",T22) -> 772083.61 | E22: =IF(B22="","",IF(AND($N$5="Equity", B22=1), "STCG", IF($N$5="Debt", "NA", IF(AND($N$5="Other", B22<3), "STCG", "LTCG")))) -> LTCG | F22: =IF(B22="","",SUMIFS($G$49:$G$348,$Y$49:$Y$348,"="&B22)) -> 28452.132 | H22: =IF(B22="","",IF(T22=0,"",F22/T22)) -> 0.036851102 | J22: =IF(B22="","",R22) -> 772083.61 | L22: =IF(B22="","",R22*$H$8) -> 240890.09 | N22: =IF(B22="","",L22/R22) -> 0.312 | R22: =12*$J$49 -> 772083.61 | T22: =SUMIFS($T$49:$T$348,$B$49:$B$348,">"&U22, $B$49:$B$348, "<="&(U22+12)) -> 772083.61 | U22: 48
B23: =IF(B22="","",IF(B22+1<=$H$12,B22+1,"")) -> 6 | C23: =IF(B23="","",T23) -> 772083.61 | E23: =IF(B23="","",IF(AND($N$5="Equity", B23=1), "STCG", IF($N$5="Debt", "NA", IF(AND($N$5="Other", B23<3), "STCG", "LTCG")))) -> LTCG | F23: =IF(B23="","",SUMIFS($G$49:$G$348,$Y$49:$Y$348,"="&B23)) -> 33493.489 | H23: =IF(B23="","",IF(T23=0,"",F23/T23)) -> 0.04338065 | J23: =IF(B23="","",R23) -> 772083.61 | L23: =IF(B23="","",R23*$H$8) -> 240890.09 | N23: =IF(B23="","",L23/R23) -> 0.312 | R23: =12*$J$49 -> 772083.61 | T23: =SUMIFS($T$49:$T$348,$B$49:$B$348,">"&U23, $B$49:$B$348, "<="&(U23+12)) -> 772083.61 | U23: 60
B24: =IF(B23="","",IF(B23+1<=$H$12,B23+1,"")) -> 7 | C24: =IF(B24="","",T24) -> 772083.61 | E24: =IF(B24="","",IF(AND($N$5="Equity", B24=1), "STCG", IF($N$5="Debt", "NA", IF(AND($N$5="Other", B24<3), "STCG", "LTCG")))) -> LTCG | F24: =IF(B24="","",SUMIFS($G$49:$G$348,$Y$49:$Y$348,"="&B24)) -> 38161.412 | H24: =IF(B24="","",IF(T24=0,"",F24/T24)) -> 0.049426528 | J24: =IF(B24="","",R24) -> 772083.61 | L24: =IF(B24="","",R24*$H$8) -> 240890.09 | N24: =IF(B24="","",L24/R24) -> 0.312 | R24: =12*$J$49 -> 772083.61 | T24: =SUMIFS($T$49:$T$348,$B$49:$B$348,">"&U24, $B$49:$B$348, "<="&(U24+12)) -> 772083.61 | U24: 72
B25: =IF(B24="","",IF(B24+1<=$H$12,B24+1,"")) -> 8 | C25: =IF(B25="","",T25) -> 772083.61 | E25: =IF(B25="","",IF(AND($N$5="Equity", B25=1), "STCG", IF($N$5="Debt", "NA", IF(AND($N$5="Other", B25<3), "STCG", "LTCG")))) -> LTCG | F25: =IF(B25="","",SUMIFS($G$49:$G$348,$Y$49:$Y$348,"="&B25)) -> 42483.563 | H25: =IF(B25="","",IF(T25=0,"",F25/T25)) -> 0.055024563 | J25: =IF(B25="","",R25) -> 772083.61 | L25: =IF(B25="","",R25*$H$8) -> 240890.09 | N25: =IF(B25="","",L25/R25) -> 0.312 | R25: =12*$J$49 -> 772083.61 | T25: =SUMIFS($T$49:$T$348,$B$49:$B$348,">"&U25, $B$49:$B$348, "<="&(U25+12)) -> 772083.61 | U25: 84
B26: =IF(B25="","",IF(B25+1<=$H$12,B25+1,"")) -> 9 | C26: =IF(B26="","",T26) -> 772083.61 | E26: =IF(B26="","",IF(AND($N$5="Equity", B26=1), "STCG", IF($N$5="Debt", "NA", IF(AND($N$5="Other", B26<3), "STCG", "LTCG")))) -> LTCG | F26: =IF(B26="","",SUMIFS($G$49:$G$348,$Y$49:$Y$348,"="&B26)) -> 46485.555 | H26: =IF(B26="","",IF(T26=0,"",F26/T26)) -> 0.060207928 | J26: =IF(B26="","",R26) -> 772083.61 | L26: =IF(B26="","",R26*$H$8) -> 240890.09 | N26: =IF(B26="","",L26/R26) -> 0.312 | R26: =12*$J$49 -> 772083.61 | T26: =SUMIFS($T$49:$T$348,$B$49:$B$348,">"&U26, $B$49:$B$348, "<="&(U26+12)) -> 772083.61 | U26: 96
B27: =IF(B26="","",IF(B26+1<=$H$12,B26+1,"")) -> 10 | C27: =IF(B27="","",T27) -> 772083.61 | E27: =IF(B27="","",IF(AND($N$5="Equity", B27=1), "STCG", IF($N$5="Debt", "NA", IF(AND($N$5="Other", B27<3), "STCG", "LTCG")))) -> LTCG | F27: =IF(B27="","",SUMIFS($G$49:$G$348,$Y$49:$Y$348,"="&B27)) -> 50191.103 | H27: =IF(B27="","",IF(T27=0,"",F27/T27)) -> 0.065007341 | J27: =IF(B27="","",R27) -> 772083.61 | L27: =IF(B27="","",R27*$H$8) -> 240890.09 | N27: =IF(B27="","",L27/R27) -> 0.312 | R27: =12*$J$49 -> 772083.61 | T27: =SUMIFS($T$49:$T$348,$B$49:$B$348,">"&U27, $B$49:$B$348, "<="&(U27+12)) -> 772083.61 | U27: 108
B28: =IF(B27="","",IF(B27+1<=$H$12,B27+1,"")) | C28: =IF(B28="","",T28) | E28: =IF(B28="","",IF(AND($N$5="Equity", B28=1), "STCG", IF($N$5="Debt", "NA", IF(AND($N$5="Other", B28<3), "STCG", "LTCG")))) | F28: =IF(B28="","",SUMIFS($G$49:$G$348,$Y$49:$Y$348,"="&B28)) | H28: =IF(B28="","",IF(T28=0,"",F28/T28)) | J28: =IF(B28="","",R28) | L28: =IF(B28="","",R28*$H$8) | N28: =IF(B28="","",L28/R28) | R28: =12*$J$49 -> 772083.61 | T28: =SUMIFS($T$49:$T$348,$B$49:$B$348,">"&U28, $B$49:$B$348, "<="&(U28+12)) -> 772083.61 | U28: 120
B29: =IF(B28="","",IF(B28+1<=$H$12,B28+1,"")) | C29: =IF(B29="","",T29) | E29: =IF(B29="","",IF(AND($N$5="Equity", B29=1), "STCG", IF($N$5="Debt", "NA", IF(AND($N$5="Other", B29<3), "STCG", "LTCG")))) | F29: =IF(B29="","",SUMIFS($G$49:$G$348,$Y$49:$Y$348,"="&B29)) | H29: =IF(B29="","",IF(T29=0,"",F29/T29)) | J29: =IF(B29="","",R29) | L29: =IF(B29="","",R29*$H$8) | N29: =IF(B29="","",L29/R29) | R29: =12*$J$49 -> 772083.61 | T29: =SUMIFS($T$49:$T$348,$B$49:$B$348,">"&U29, $B$49:$B$348, "<="&(U29+12)) -> 772083.61 | U29: 132
B30: =IF(B29="","",IF(B29+1<=$H$12,B29+1,"")) | C30: =IF(B30="","",T30) | E30: =IF(B30="","",IF(AND($N$5="Equity", B30=1), "STCG", IF($N$5="Debt", "NA", IF(AND($N$5="Other", B30<3), "STCG", "LTCG")))) | F30: =IF(B30="","",SUMIFS($G$49:$G$348,$Y$49:$Y$348,"="&B30)) | H30: =IF(B30="","",IF(T30=0,"",F30/T30)) | J30: =IF(B30="","",R30) | L30: =IF(B30="","",R30*$H$8) | N30: =IF(B30="","",L30/R30) | R30: =12*$J$49 -> 772083.61 | T30: =SUMIFS($T$49:$T$348,$B$49:$B$348,">"&U30, $B$49:$B$348, "<="&(U30+12)) -> 772083.61 | U30: 144
... B42: =IF(B41="","",IF(B41+1<=$H$12,B41+1,"")) | C42: =IF(B42="","",T42) | E42: =IF(B42="","",IF(AND($N$5="Equity", B42=1), "STCG", IF($N$5="Debt", "NA", IF(AND($N$5="Other", B42<3), "STCG", "LTCG")))) | F42: =IF(B42="","",SUMIFS($G$49:$G$348,$Y$49:$Y$348,"="&B42)) | H42: =IF(B42="","",IF(T42=0,"",F42/T42)) | J42: =IF(B42="","",R42) | L42: =IF(B42="","",R42*$H$8) | N42: =IF(B42="","",L42/R42) | R42: =12*$J$49 -> 772083.61 | T42: =SUMIFS($T$49:$T$348,$B$49:$B$348,">"&U42, $B$49:$B$348, "<="&(U42+12)) -> 772083.61 | U42: 288
B43: ="Fund value at the end of "&$H$12&" years:" -> Fund value at the end of 10 years: | H43: =VLOOKUP($H$12*12,$B$49:$I$348,7,0) -> 10000000 | K43: ="FD value after "&$H$12&" years:" -> FD value after 10 years: | N43: =N348 -> 10000000
B44: *Please note that exemption of Long Term Capital Gain of upto Rs. 1 Lakh for Equity Fund's long-term taxation has not been considered in case of monthly withdrawals
R45: Capital Gain (Non-Equity) | T45: =INDEX($S$49:$S$348,MATCH($H$12*12,$X$49:$X$348,0))*(INDEX($D$49:$D$348,MATCH($H$12*12,$X$49:$X$348,0))-FV(V12,$H$12-1,,-10)) -> 1484376.6 | V45: Capital Gain (Specified) | X45: =INDEX($S$49:$S$348,MATCH($H$12*12,$X$49:$X$348,0))*(INDEX($D$49:$D$348,MATCH($H$12*12,$X$49:$X$348,0))-10) -> 5368065.1 | Z45: Capital Gain (Equity) | AB45: =INDEX($S$49:$S$348,MATCH($H$12*12,$X$49:$X$348,0))*(INDEX($D$49:$D$348,MATCH($H$12*12,$X$49:$X$348,0))-10) -> 5368065.1
B46: MUTUAL FUND SWP TAXATION (MONTHLY) | J46: FIXED DEPOSIT INTEREST TAXATION (MONTHLY)
B47: MONTH | C47: SWP AMT | D47: NAV | E47: STCG | F47: LTCG* | G47: TAX PAID | H47: FUND VALUE | J47: INTEREST PAYOUT | L47: TAX PAID | N47: FD VALUE | R47: UNITS REDEEMED | S47: BALANCE UNITS | T47: Amt Withdrawn
S48: =H5/10 -> 1000000
B49: 1 | C49: =T49 -> 64340.301 | D49: =10*(1+(1+$H$6)^(1/12)-1) -> 10.06434 | E49: =IF(AND(OR($N$5="Other",$N$5="Debt"), B49<24),R49*(D49-10), IF(AND($N$5="Equity", B49<12),R49*(D49-10), 0)) -> 411.32098 | F49: =IF(AND(OR($N$5="Other",$N$5="Debt"), B49>=24),R49*(D49-10), IF(AND($N$5="Equity", B49>=12),R49*(D49-10),0)) -> 0 | G49: =IF(AND($N$5="Equity", B49< 12), E49*20%, IF(AND($N$5="Equity", B49>= 12),F49*12.5%, IF(AND($N$5="Other", B49<24),E49*$H$8, IF(AND($N$5="Other", B49>=24),F49*12.5%,F49*$H$8)))) -> 82.264197 | H49: =S49*D49 -> 10000000 | J49: =$H$5*((1+$H$7)^(1/12)-1) -> 64340.301 | L49: =J49*$H$8 -> 20074.174 | N49: =$H$5 -> 10000000 | P49: =ROUNDUP(B49/12,0) - 1 -> 0 | R49: =IF($X$16/D49>S48,S48,$X$16/D49) -> 6392.898 | S49: =S48-R49 -> 993607.1 | T49: =IF($X$16/D49>S48,S48*D49,$X$16) -> 64340.301 | X49: 1 | Y49: 1
B50: 2 | C50: =T50 -> 64340.301 | D50: =D49*(1+(1+$H$6)^(1/12)-1) -> 10.129095 | E50: =IF(AND(OR($N$5="Other",$N$5="Debt"), B50<24),R50*(D50-10), IF(AND($N$5="Equity", B50<12),R50*(D50-10), 0)) -> 820.01243 | F50: =IF(AND(OR($N$5="Other",$N$5="Debt"), B50>=24),R50*(D50-10), IF(AND($N$5="Equity", B50>=12),R50*(D50-10),0)) -> 0 | G50: =IF(AND($N$5="Equity", B50< 12), E50*20%, IF(AND($N$5="Equity", B50>= 12),F50*12.5%, IF(AND($N$5="Other", B50<24),E50*$H$8, IF(AND($N$5="Other", B50>=24),F50*12.5%,F50*$H$8)))) -> 164.00249 | H50: =S50*D50 -> 10000000 | J50: =$H$5*((1+$H$7)^(1/12)-1) -> 64340.301 | L50: =J50*$H$8 -> 20074.174 | N50: =$H$5 -> 10000000 | P50: =ROUNDUP(B50/12,0) - 1 -> 0 | R50: =IF($X$16/D50>S49,S49,$X$16/D50) -> 6352.0289 | S50: =S49-R50 -> 987255.07 | T50: =IF($X$16/D50>S49,S49*D50,$X$16) -> 64340.301 | X50: 2 | Y50: 1
B51: 3 | C51: =T51 -> 64340.301 | D51: =D50*(1+(1+$H$6)^(1/12)-1) -> 10.194265 | E51: =IF(AND(OR($N$5="Other",$N$5="Debt"), B51<24),R51*(D51-10), IF(AND($N$5="Equity", B51<12),R51*(D51-10), 0)) -> 1226.0912 | F51: =IF(AND(OR($N$5="Other",$N$5="Debt"), B51>=24),R51*(D51-10), IF(AND($N$5="Equity", B51>=12),R51*(D51-10),0)) -> 0 | G51: =IF(AND($N$5="Equity", B51< 12), E51*20%, IF(AND($N$5="Equity", B51>= 12),F51*12.5%, IF(AND($N$5="Other", B51<24),E51*$H$8, IF(AND($N$5="Other", B51>=24),F51*12.5%,F51*$H$8)))) -> 245.21823 | H51: =S51*D51 -> 10000000 | J51: =$H$5*((1+$H$7)^(1/12)-1) -> 64340.301 | L51: =J51*$H$8 -> 20074.174 | N51: =$H$5 -> 10000000 | P51: =ROUNDUP(B51/12,0) - 1 -> 0 | R51: =IF($X$16/D51>S50,S50,$X$16/D51) -> 6311.421 | S51: =S50-R51 -> 980943.65 | T51: =IF($X$16/D51>S50,S50*D51,$X$16) -> 64340.301 | X51: 3 | Y51: 1
B52: 4 | C52: =T52 -> 64340.301 | D52: =D51*(1+(1+$H$6)^(1/12)-1) -> 10.259856 | E52: =IF(AND(OR($N$5="Other",$N$5="Debt"), B52<24),R52*(D52-10), IF(AND($N$5="Equity", B52<12),R52*(D52-10), 0)) -> 1629.5739 | F52: =IF(AND(OR($N$5="Other",$N$5="Debt"), B52>=24),R52*(D52-10), IF(AND($N$5="Equity", B52>=12),R52*(D52-10),0)) -> 0 | G52: =IF(AND($N$5="Equity", B52< 12), E52*20%, IF(AND($N$5="Equity", B52>= 12),F52*12.5%, IF(AND($N$5="Other", B52<24),E52*$H$8, IF(AND($N$5="Other", B52>=24),F52*12.5%,F52*$H$8)))) -> 325.91477 | H52: =S52*D52 -> 10000000 | J52: =$H$5*((1+$H$7)^(1/12)-1) -> 64340.301 | L52: =J52*$H$8 -> 20074.174 | N52: =$H$5 -> 10000000 | P52: =ROUNDUP(B52/12,0) - 1 -> 0 | R52: =IF($X$16/D52>S51,S51,$X$16/D52) -> 6271.0727 | S52: =S51-R52 -> 974672.58 | T52: =IF($X$16/D52>S51,S51*D52,$X$16) -> 64340.301 | X52: 4 | Y52: 1
B53: 5 | C53: =T53 -> 64340.301 | D53: =D52*(1+(1+$H$6)^(1/12)-1) -> 10.325868 | E53: =IF(AND(OR($N$5="Other",$N$5="Debt"), B53<24),R53*(D53-10), IF(AND($N$5="Equity", B53<12),R53*(D53-10), 0)) -> 2030.4772 | F53: =IF(AND(OR($N$5="Other",$N$5="Debt"), B53>=24),R53*(D53-10), IF(AND($N$5="Equity", B53>=12),R53*(D53-10),0)) -> 0 | G53: =IF(AND($N$5="Equity", B53< 12), E53*20%, IF(AND($N$5="Equity", B53>= 12),F53*12.5%, IF(AND($N$5="Other", B53<24),E53*$H$8, IF(AND($N$5="Other", B53>=24),F53*12.5%,F53*$H$8)))) -> 406.09543 | H53: =S53*D53 -> 10000000 | J53: =$H$5*((1+$H$7)^(1/12)-1) -> 64340.301 | L53: =J53*$H$8 -> 20074.174 | N53: =$H$5 -> 10000000 | P53: =ROUNDUP(B53/12,0) - 1 -> 0 | R53: =IF($X$16/D53>S52,S52,$X$16/D53) -> 6230.9824 | S53: =S52-R53 -> 968441.6 | T53: =IF($X$16/D53>S52,S52*D53,$X$16) -> 64340.301 | X53: 5 | Y53: 1
B54: 6 | C54: =T54 -> 64340.301 | D54: =D53*(1+(1+$H$6)^(1/12)-1) -> 10.392305 | E54: =IF(AND(OR($N$5="Other",$N$5="Debt"), B54<24),R54*(D54-10), IF(AND($N$5="Equity", B54<12),R54*(D54-10), 0)) -> 2428.8175 | F54: =IF(AND(OR($N$5="Other",$N$5="Debt"), B54>=24),R54*(D54-10), IF(AND($N$5="Equity", B54>=12),R54*(D54-10),0)) -> 0 | G54: =IF(AND($N$5="Equity", B54< 12), E54*20%, IF(AND($N$5="Equity", B54>= 12),F54*12.5%, IF(AND($N$5="Other", B54<24),E54*$H$8, IF(AND($N$5="Other", B54>=24),F54*12.5%,F54*$H$8)))) -> 485.7635 | H54: =S54*D54 -> 10000000 | J54: =$H$5*((1+$H$7)^(1/12)-1) -> 64340.301 | L54: =J54*$H$8 -> 20074.174 | N54: =$H$5 -> 10000000 | P54: =ROUNDUP(B54/12,0) - 1 -> 0 | R54: =IF($X$16/D54>S53,S53,$X$16/D54) -> 6191.1484 | S54: =S53-R54 -> 962250.45 | T54: =IF($X$16/D54>S53,S53*D54,$X$16) -> 64340.301 | X54: 6 | Y54: 1
B55: 7 | C55: =T55 -> 64340.301 | D55: =D54*(1+(1+$H$6)^(1/12)-1) -> 10.459169 | E55: =IF(AND(OR($N$5="Other",$N$5="Debt"), B55<24),R55*(D55-10), IF(AND($N$5="Equity", B55<12),R55*(D55-10), 0)) -> 2824.6113 | F55: =IF(AND(OR($N$5="Other",$N$5="Debt"), B55>=24),R55*(D55-10), IF(AND($N$5="Equity", B55>=12),R55*(D55-10),0)) -> 0 | G55: =IF(AND($N$5="Equity", B55< 12), E55*20%, IF(AND($N$5="Equity", B55>= 12),F55*12.5%, IF(AND($N$5="Other", B55<24),E55*$H$8, IF(AND($N$5="Other", B55>=24),F55*12.5%,F55*$H$8)))) -> 564.92226 | H55: =S55*D55 -> 10000000 | J55: =$H$5*((1+$H$7)^(1/12)-1) -> 64340.301 | L55: =J55*$H$8 -> 20074.174 | N55: =$H$5 -> 10000000 | P55: =ROUNDUP(B55/12,0) - 1 -> 0 | R55: =IF($X$16/D55>S54,S54,$X$16/D55) -> 6151.569 | S55: =S54-R55 -> 956098.88 | T55: =IF($X$16/D55>S54,S54*D55,$X$16) -> 64340.301 | X55: 7 | Y55: 1
B56: 8 | C56: =T56 -> 64340.301 | D56: =D55*(1+(1+$H$6)^(1/12)-1) -> 10.526464 | E56: =IF(AND(OR($N$5="Other",$N$5="Debt"), B56<24),R56*(D56-10), IF(AND($N$5="Equity", B56<12),R56*(D56-10), 0)) -> 3217.8748 | F56: =IF(AND(OR($N$5="Other",$N$5="Debt"), B56>=24),R56*(D56-10), IF(AND($N$5="Equity", B56>=12),R56*(D56-10),0)) -> 0 | G56: =IF(AND($N$5="Equity", B56< 12), E56*20%, IF(AND($N$5="Equity", B56>= 12),F56*12.5%, IF(AND($N$5="Other", B56<24),E56*$H$8, IF(AND($N$5="Other", B56>=24),F56*12.5%,F56*$H$8)))) -> 643.57497 | H56: =S56*D56 -> 10000000 | J56: =$H$5*((1+$H$7)^(1/12)-1) -> 64340.301 | L56: =J56*$H$8 -> 20074.174 | N56: =$H$5 -> 10000000 | P56: =ROUNDUP(B56/12,0) - 1 -> 0 | R56: =IF($X$16/D56>S55,S55,$X$16/D56) -> 6112.2426 | S56: =S55-R56 -> 949986.64 | T56: =IF($X$16/D56>S55,S55*D56,$X$16) -> 64340.301 | X56: 8 | Y56: 1
B57: 9 | C57: =T57 -> 64340.301 | D57: =D56*(1+(1+$H$6)^(1/12)-1) -> 10.594191 | E57: =IF(AND(OR($N$5="Other",$N$5="Debt"), B57<24),R57*(D57-10), IF(AND($N$5="Equity", B57<12),R57*(D57-10), 0)) -> 3608.6243 | F57: =IF(AND(OR($N$5="Other",$N$5="Debt"), B57>=24),R57*(D57-10), IF(AND($N$5="Equity", B57>=12),R57*(D57-10),0)) -> 0 | G57: =IF(AND($N$5="Equity", B57< 12), E57*20%, IF(AND($N$5="Equity", B57>= 12),F57*12.5%, IF(AND($N$5="Other", B57<24),E57*$H$8, IF(AND($N$5="Other", B57>=24),F57*12.5%,F57*$H$8)))) -> 721.72485 | H57: =S57*D57 -> 10000000 | J57: =$H$5*((1+$H$7)^(1/12)-1) -> 64340.301 | L57: =J57*$H$8 -> 20074.174 | N57: =$H$5 -> 10000000 | P57: =ROUNDUP(B57/12,0) - 1 -> 0 | R57: =IF($X$16/D57>S56,S56,$X$16/D57) -> 6073.1677 | S57: =S56-R57 -> 943913.47 | T57: =IF($X$16/D57>S56,S56*D57,$X$16) -> 64340.301 | X57: 9 | Y57: 1
B58: 10 | C58: =T58 -> 64340.301 | D58: =D57*(1+(1+$H$6)^(1/12)-1) -> 10.662355 | E58: =IF(AND(OR($N$5="Other",$N$5="Debt"), B58<24),R58*(D58-10), IF(AND($N$5="Equity", B58<12),R58*(D58-10), 0)) -> 3996.8757 | F58: =IF(AND(OR($N$5="Other",$N$5="Debt"), B58>=24),R58*(D58-10), IF(AND($N$5="Equity", B58>=12),R58*(D58-10),0)) -> 0 | G58: =IF(AND($N$5="Equity", B58< 12), E58*20%, IF(AND($N$5="Equity", B58>= 12),F58*12.5%, IF(AND($N$5="Other", B58<24),E58*$H$8, IF(AND($N$5="Other", B58>=24),F58*12.5%,F58*$H$8)))) -> 799.37514 | H58: =S58*D58 -> 10000000 | J58: =$H$5*((1+$H$7)^(1/12)-1) -> 64340.301 | L58: =J58*$H$8 -> 20074.174 | N58: =$H$5 -> 10000000 | P58: =ROUNDUP(B58/12,0) - 1 -> 0 | R58: =IF($X$16/D58>S57,S57,$X$16/D58) -> 6034.3425 | S58: =S57-R58 -> 937879.13 | T58: =IF($X$16/D58>S57,S57*D58,$X$16) -> 64340.301 | X58: 10 | Y58: 1
B59: 11 | C59: =T59 -> 64340.301 | D59: =D58*(1+(1+$H$6)^(1/12)-1) -> 10.730957 | E59: =IF(AND(OR($N$5="Other",$N$5="Debt"), B59<24),R59*(D59-10), IF(AND($N$5="Equity", B59<12),R59*(D59-10), 0)) -> 4382.645 | F59: =IF(AND(OR($N$5="Other",$N$5="Debt"), B59>=24),R59*(D59-10), IF(AND($N$5="Equity", B59>=12),R59*(D59-10),0)) -> 0 | G59: =IF(AND($N$5="Equity", B59< 12), E59*20%, IF(AND($N$5="Equity", B59>= 12),F59*12.5%, IF(AND($N$5="Other", B59<24),E59*$H$8, IF(AND($N$5="Other", B59>=24),F59*12.5%,F59*$H$8)))) -> 876.52901 | H59: =S59*D59 -> 10000000 | J59: =$H$5*((1+$H$7)^(1/12)-1) -> 64340.301 | L59: =J59*$H$8 -> 20074.174 | N59: =$H$5 -> 10000000 | P59: =ROUNDUP(B59/12,0) - 1 -> 0 | R59: =IF($X$16/D59>S58,S58,$X$16/D59) -> 5995.7656 | S59: =S58-R59 -> 931883.36 | T59: =IF($X$16/D59>S58,S58*D59,$X$16) -> 64340.301 | X59: 11 | Y59: 1
B60: 12 | C60: =T60 -> 64340.301 | D60: =D59*(1+(1+$H$6)^(1/12)-1) -> 10.8 | E60: =IF(AND(OR($N$5="Other",$N$5="Debt"), B60<24),R60*(D60-10), IF(AND($N$5="Equity", B60<12),R60*(D60-10), 0)) -> 0 | F60: =IF(AND(OR($N$5="Other",$N$5="Debt"), B60>=24),R60*(D60-10), IF(AND($N$5="Equity", B60>=12),R60*(D60-10),0)) -> 4765.9482 | G60: =IF(AND($N$5="Equity", B60< 12), E60*20%, IF(AND($N$5="Equity", B60>= 12),F60*12.5%, IF(AND($N$5="Other", B60<24),E60*$H$8, IF(AND($N$5="Other", B60>=24),F60*12.5%,F60*$H$8)))) -> 595.74353 | H60: =S60*D60 -> 10000000 | J60: =$H$5*((1+$H$7)^(1/12)-1) -> 64340.301 | L60: =J60*$H$8 -> 20074.174 | N60: =$H$5 -> 10000000 | P60: =ROUNDUP(B60/12,0) - 1 -> 0 | R60: =IF($X$16/D60>S59,S59,$X$16/D60) -> 5957.4353 | S60: =S59-R60 -> 925925.93 | T60: =IF($X$16/D60>S59,S59*D60,$X$16) -> 64340.301 | X60: 12 | Y60: 1
B61: 13 | C61: =T61 -> 64340.301 | D61: =D60*(1+(1+$H$6)^(1/12)-1) -> 10.869488 | E61: =IF(AND(OR($N$5="Other",$N$5="Debt"), B61<24),R61*(D61-10), IF(AND($N$5="Equity", B61<12),R61*(D61-10), 0)) -> 0 | F61: =IF(AND(OR($N$5="Other",$N$5="Debt"), B61>=24),R61*(D61-10), IF(AND($N$5="Equity", B61>=12),R61*(D61-10),0)) -> 5146.801 | G61: =IF(AND($N$5="Equity", B61< 12), E61*20%, IF(AND($N$5="Equity", B61>= 12),F61*12.5%, IF(AND($N$5="Other", B61<24),E61*$H$8, IF(AND($N$5="Other", B61>=24),F61*12.5%,F61*$H$8)))) -> 643.35012 | H61: =S61*D61 -> 10000000 | J61: =$H$5*((1+$H$7)^(1/12)-1) -> 64340.301 | L61: =J61*$H$8 -> 20074.174 | N61: =$H$5 -> 10000000 | P61: =ROUNDUP(B61/12,0) - 1 -> 1 | R61: =IF($X$16/D61>S60,S60,$X$16/D61) -> 5919.35 | S61: =S60-R61 -> 920006.58 | T61: =IF($X$16/D61>S60,S60*D61,$X$16) -> 64340.301 | X61: 13 | Y61: 2
... B109: 61 | C109: =T109 -> 64340.301 | D109: =D108*(1+(1+$H$6)^(1/12)-1) -> 14.787818 | E109: =IF(AND(OR($N$5="Other",$N$5="Debt"), B109<24),R109*(D109-10), IF(AND($N$5="Equity", B109<12),R109*(D109-10), 0)) -> 0 | F109: =IF(AND(OR($N$5="Other",$N$5="Debt"), B109>=24),R109*(D109-10), IF(AND($N$5="Equity", B109>=12),R109*(D109-10),0)) -> 20831.311 | G109: =IF(AND($N$5="Equity", B109< 12), E109*20%, IF(AND($N$5="Equity", B109>= 12),F109*12.5%, IF(AND($N$5="Other", B109<24),E109*$H$8, IF(AND($N$5="Other", B109>=24),F109*12.5%,F109*$H$8)))) -> 2603.9139 | H109: =S109*D109 -> 10000000 | J109: =$H$5*((1+$H$7)^(1/12)-1) -> 64340.301 | L109: =J109*$H$8 -> 20074.174 | N109: =$H$5 -> 10000000 | P109: =ROUNDUP(B109/12,0) - 1 -> 5 | R109: =IF($X$16/D109>S108,S108,$X$16/D109) -> 4350.899 | S109: =S108-R109 -> 676232.3 | T109: =IF($X$16/D109>S108,S108*D109,$X$16) -> 64340.301 | X109: 61 | Y109: 6
B110: 62 | C110: =E12 -> 0 | D110: =D109*(1+(1+$H$6)^(1/12)-1) -> 14.882963 | E110: =IF(AND(OR($N$5="Other",$N$5="Debt"), B110<24),R110*(D110-10), IF(AND($N$5="Equity", B110<12),R110*(D110-10), 0)) -> 0 | F110: =IF(AND(OR($N$5="Other",$N$5="Debt"), B110>=24),R110*(D110-10), IF(AND($N$5="Equity", B110>=12),R110*(D110-10),0)) -> 21109.46 | G110: =IF(AND($N$5="Equity", B110< 12), E110*20%, IF(AND($N$5="Equity", B110>= 12),F110*12.5%, IF(AND($N$5="Other", B110<24),E110*$H$8, IF(AND($N$5="Other", B110>=24),F110*12.5%,F110*$H$8)))) -> 2638.6825 | H110: =S110*D110 -> 10000000 | J110: =$H$5*((1+$H$7)^(1/12)-1) -> 64340.301 | L110: =J110*$H$8 -> 20074.174 | N110: =$H$5 -> 10000000 | P110: =ROUNDUP(B110/12,0) - 1 -> 5 | R110: =IF($X$16/D110>S109,S109,$X$16/D110) -> 4323.0841 | S110: =S109-R110 -> 671909.21 | T110: =IF($X$16/D110>S109,S109*D110,$X$16) -> 64340.301 | X110: 62 | Y110: 6
B111: 63 | C111: =E13 -> 0 | D111: =D110*(1+(1+$H$6)^(1/12)-1) -> 14.97872 | E111: =IF(AND(OR($N$5="Other",$N$5="Debt"), B111<24),R111*(D111-10), IF(AND($N$5="Equity", B111<12),R111*(D111-10), 0)) -> 0 | F111: =IF(AND(OR($N$5="Other",$N$5="Debt"), B111>=24),R111*(D111-10), IF(AND($N$5="Equity", B111>=12),R111*(D111-10),0)) -> 21385.83 | G111: =IF(AND($N$5="Equity", B111< 12), E111*20%, IF(AND($N$5="Equity", B111>= 12),F111*12.5%, IF(AND($N$5="Other", B111<24),E111*$H$8, IF(AND($N$5="Other", B111>=24),F111*12.5%,F111*$H$8)))) -> 2673.2288 | H111: =S111*D111 -> 10000000 | J111: =$H$5*((1+$H$7)^(1/12)-1) -> 64340.301 | L111: =J111*$H$8 -> 20074.174 | N111: =$H$5 -> 10000000 | P111: =ROUNDUP(B111/12,0) - 1 -> 5 | R111: =IF($X$16/D111>S110,S110,$X$16/D111) -> 4295.4471 | S111: =S110-R111 -> 667613.77 | T111: =IF($X$16/D111>S110,S110*D111,$X$16) -> 64340.301 | X111: 63 | Y111: 6
B112: 64 | C112: =T112 -> 64340.301 | D112: =D111*(1+(1+$H$6)^(1/12)-1) -> 15.075094 | E112: =IF(AND(OR($N$5="Other",$N$5="Debt"), B112<24),R112*(D112-10), IF(AND($N$5="Equity", B112<12),R112*(D112-10), 0)) -> 0 | F112: =IF(AND(OR($N$5="Other",$N$5="Debt"), B112>=24),R112*(D112-10), IF(AND($N$5="Equity", B112>=12),R112*(D112-10),0)) -> 21660.434 | G112: =IF(AND($N$5="Equity", B112< 12), E112*20%, IF(AND($N$5="Equity", B112>= 12),F112*12.5%, IF(AND($N$5="Other", B112<24),E112*$H$8, IF(AND($N$5="Other", B112>=24),F112*12.5%,F112*$H$8)))) -> 2707.5542 | H112: =S112*D112 -> 10000000 | J112: =$H$5*((1+$H$7)^(1/12)-1) -> 64340.301 | L112: =J112*$H$8 -> 20074.174 | N112: =$H$5 -> 10000000 | P112: =ROUNDUP(B112/12,0) - 1 -> 5 | R112: =IF($X$16/D112>S111,S111,$X$16/D112) -> 4267.9867 | S112: =S111-R112 -> 663345.78 | T112: =IF($X$16/D112>S111,S111*D112,$X$16) -> 64340.301 | X112: 64 | Y112: 6
B113: 65 | C113: =T113 -> 64340.301 | D113: =D112*(1+(1+$H$6)^(1/12)-1) -> 15.172088 | E113: =IF(AND(OR($N$5="Other",$N$5="Debt"), B113<24),R113*(D113-10), IF(AND($N$5="Equity", B113<12),R113*(D113-10), 0)) -> 0 | F113: =IF(AND(OR($N$5="Other",$N$5="Debt"), B113>=24),R113*(D113-10), IF(AND($N$5="Equity", B113>=12),R113*(D113-10),0)) -> 21933.282 | G113: =IF(AND($N$5="Equity", B113< 12), E113*20%, IF(AND($N$5="Equity", B113>= 12),F113*12.5%, IF(AND($N$5="Other", B113<24),E113*$H$8, IF(AND($N$5="Other", B113>=24),F113*12.5%,F113*$H$8)))) -> 2741.6602 | H113: =S113*D113 -> 10000000 | J113: =$H$5*((1+$H$7)^(1/12)-1) -> 64340.301 | L113: =J113*$H$8 -> 20074.174 | N113: =$H$5 -> 10000000 | P113: =ROUNDUP(B113/12,0) - 1 -> 5 | R113: =IF($X$16/D113>S112,S112,$X$16/D113) -> 4240.7019 | S113: =S112-R113 -> 659105.08 | T113: =IF($X$16/D113>S112,S112*D113,$X$16) -> 64340.301 | X113: 65 | Y113: 6
B114: 66 | C114: =T114 -> 64340.301 | D114: =D113*(1+(1+$H$6)^(1/12)-1) -> 15.269705 | E114: =IF(AND(OR($N$5="Other",$N$5="Debt"), B114<24),R114*(D114-10), IF(AND($N$5="Equity", B114<12),R114*(D114-10), 0)) -> 0 | F114: =IF(AND(OR($N$5="Other",$N$5="Debt"), B114>=24),R114*(D114-10), IF(AND($N$5="Equity", B114>=12),R114*(D114-10),0)) -> 22204.386 | G114: =IF(AND($N$5="Equity", B114< 12), E114*20%, IF(AND($N$5="Equity", B114>= 12),F114*12.5%, IF(AND($N$5="Other", B114<24),E114*$H$8, IF(AND($N$5="Other", B114>=24),F114*12.5%,F114*$H$8)))) -> 2775.5482 | H114: =S114*D114 -> 10000000 | J114: =$H$5*((1+$H$7)^(1/12)-1) -> 64340.301 | L114: =J114*$H$8 -> 20074.174 | N114: =$H$5 -> 10000000 | P114: =ROUNDUP(B114/12,0) - 1 -> 5 | R114: =IF($X$16/D114>S113,S113,$X$16/D114) -> 4213.5915 | S114: =S113-R114 -> 654891.49 | T114: =IF($X$16/D114>S113,S113*D114,$X$16) -> 64340.301 | X114: 66 | Y114: 6
B115: 67 | C115: =T115 -> 64340.301 | D115: =D114*(1+(1+$H$6)^(1/12)-1) -> 15.367951 | E115: =IF(AND(OR($N$5="Other",$N$5="Debt"), B115<24),R115*(D115-10), IF(AND($N$5="Equity", B115<12),R115*(D115-10), 0)) -> 0 | F115: =IF(AND(OR($N$5="Other",$N$5="Debt"), B115>=24),R115*(D115-10), IF(AND($N$5="Equity", B115>=12),R115*(D115-10),0)) -> 22473.756 | G115: =IF(AND($N$5="Equity", B115< 12), E115*20%, IF(AND($N$5="Equity", B115>= 12),F115*12.5%, IF(AND($N$5="Other", B115<24),E115*$H$8, IF(AND($N$5="Other", B115>=24),F115*12.5%,F115*$H$8)))) -> 2809.2195 | H115: =S115*D115 -> 10000000 | J115: =$H$5*((1+$H$7)^(1/12)-1) -> 64340.301 | L115: =J115*$H$8 -> 20074.174 | N115: =$H$5 -> 10000000 | P115: =ROUNDUP(B115/12,0) - 1 -> 5 | R115: =IF($X$16/D115>S114,S114,$X$16/D115) -> 4186.6545 | S115: =S114-R115 -> 650704.83 | T115: =IF($X$16/D115>S114,S114*D115,$X$16) -> 64340.301 | X115: 67 | Y115: 6
B116: 68 | C116: =T116 -> 64340.301 | D116: =D115*(1+(1+$H$6)^(1/12)-1) -> 15.466829 | E116: =IF(AND(OR($N$5="Other",$N$5="Debt"), B116<24),R116*(D116-10), IF(AND($N$5="Equity", B116<12),R116*(D116-10), 0)) -> 0 | F116: =IF(AND(OR($N$5="Other",$N$5="Debt"), B116>=24),R116*(D116-10), IF(AND($N$5="Equity", B116>=12),R116*(D116-10),0)) -> 22741.405 | G116: =IF(AND($N$5="Equity", B116< 12), E116*20%, IF(AND($N$5="Equity", B116>= 12),F116*12.5%, IF(AND($N$5="Other", B116<24),E116*$H$8, IF(AND($N$5="Other", B116>=24),F116*12.5%,F116*$H$8)))) -> 2842.6756 | H116: =S116*D116 -> 10000000 | J116: =$H$5*((1+$H$7)^(1/12)-1) -> 64340.301 | L116: =J116*$H$8 -> 20074.174 | N116: =$H$5 -> 10000000 | P116: =ROUNDUP(B116/12,0) - 1 -> 5 | R116: =IF($X$16/D116>S115,S115,$X$16/D116) -> 4159.8896 | S116: =S115-R116 -> 646544.94 | T116: =IF($X$16/D116>S115,S115*D116,$X$16) -> 64340.301 | X116: 68 | Y116: 6
B117: 69 | C117: =T117 -> 64340.301 | D117: =D116*(1+(1+$H$6)^(1/12)-1) -> 15.566343 | E117: =IF(AND(OR($N$5="Other",$N$5="Debt"), B117<24),R117*(D117-10), IF(AND($N$5="Equity", B117<12),R117*(D117-10), 0)) -> 0 | F117: =IF(AND(OR($N$5="Other",$N$5="Debt"), B117>=24),R117*(D117-10), IF(AND($N$5="Equity", B117>=12),R117*(D117-10),0)) -> 23007.342 | G117: =IF(AND($N$5="Equity", B117< 12), E117*20%, IF(AND($N$5="Equity", B117>= 12),F117*12.5%, IF(AND($N$5="Other", B117<24),E117*$H$8, IF(AND($N$5="Other", B117>=24),F117*12.5%,F117*$H$8)))) -> 2875.9178 | H117: =S117*D117 -> 10000000 | J117: =$H$5*((1+$H$7)^(1/12)-1) -> 64340.301 | L117: =J117*$H$8 -> 20074.174 | N117: =$H$5 -> 10000000 | P117: =ROUNDUP(B117/12,0) - 1 -> 5 | R117: =IF($X$16/D117>S116,S116,$X$16/D117) -> 4133.2959 | S117: =S116-R117 -> 642411.65 | T117: =IF($X$16/D117>S116,S116*D117,$X$16) -> 64340.301 | X117: 69 | Y117: 6
B118: 70 | C118: =T118 -> 64340.301 | D118: =D117*(1+(1+$H$6)^(1/12)-1) -> 15.666497 | E118: =IF(AND(OR($N$5="Other",$N$5="Debt"), B118<24),R118*(D118-10), IF(AND($N$5="Equity", B118<12),R118*(D118-10), 0)) -> 0 | F118: =IF(AND(OR($N$5="Other",$N$5="Debt"), B118>=24),R118*(D118-10), IF(AND($N$5="Equity", B118>=12),R118*(D118-10),0)) -> 23271.58 | G118: =IF(AND($N$5="Equity", B118< 12), E118*20%, IF(AND($N$5="Equity", B118>= 12),F118*12.5%, IF(AND($N$5="Other", B118<24),E118*$H$8, IF(AND($N$5="Other", B118>=24),F118*12.5%,F118*$H$8)))) -> 2908.9475 | H118: =S118*D118 -> 10000000 | J118: =$H$5*((1+$H$7)^(1/12)-1) -> 64340.301 | L118: =J118*$H$8 -> 20074.174 | N118: =$H$5 -> 10000000 | P118: =ROUNDUP(B118/12,0) - 1 -> 5 | R118: =IF($X$16/D118>S117,S117,$X$16/D118) -> 4106.8721 | S118: =S117-R118 -> 638304.77 | T118: =IF($X$16/D118>S117,S117*D118,$X$16) -> 64340.301 | X118: 70 | Y118: 6
A119: WHITE | B119: 71 | C119: =T119 -> 64340.301 | D119: =D118*(1+(1+$H$6)^(1/12)-1) -> 15.767296 | E119: =IF(AND(OR($N$5="Other",$N$5="Debt"), B119<24),R119*(D119-10), IF(AND($N$5="Equity", B119<12),R119*(D119-10), 0)) -> 0 | F119: =IF(AND(OR($N$5="Other",$N$5="Debt"), B119>=24),R119*(D119-10), IF(AND($N$5="Equity", B119>=12),R119*(D119-10),0)) -> 23534.128 | G119: =IF(AND($N$5="Equity", B119< 12), E119*20%, IF(AND($N$5="Equity", B119>= 12),F119*12.5%, IF(AND($N$5="Other", B119<24),E119*$H$8, IF(AND($N$5="Other", B119>=24),F119*12.5%,F119*$H$8)))) -> 2941.766 | H119: =S119*D119 -> 10000000 | J119: =$H$5*((1+$H$7)^(1/12)-1) -> 64340.301 | L119: =J119*$H$8 -> 20074.174 | N119: =$H$5 -> 10000000 | P119: =ROUNDUP(B119/12,0) - 1 -> 5 | R119: =IF($X$16/D119>S118,S118,$X$16/D119) -> 4080.6173 | S119: =S118-R119 -> 634224.16 | T119: =IF($X$16/D119>S118,S118*D119,$X$16) -> 64340.301 | X119: 71 | Y119: 6
A120: ORANGE | B120: 72 | C120: =T120 -> 64340.301 | D120: =D119*(1+(1+$H$6)^(1/12)-1) -> 15.868743 | E120: =IF(AND(OR($N$5="Other",$N$5="Debt"), B120<24),R120*(D120-10), IF(AND($N$5="Equity", B120<12),R120*(D120-10), 0)) -> 0 | F120: =IF(AND(OR($N$5="Other",$N$5="Debt"), B120>=24),R120*(D120-10), IF(AND($N$5="Equity", B120>=12),R120*(D120-10),0)) -> 23794.998 | G120: =IF(AND($N$5="Equity", B120< 12), E120*20%, IF(AND($N$5="Equity", B120>= 12),F120*12.5%, IF(AND($N$5="Other", B120<24),E120*$H$8, IF(AND($N$5="Other", B120>=24),F120*12.5%,F120*$H$8)))) -> 2974.3747 | H120: =S120*D120 -> 10000000 | J120: =$H$5*((1+$H$7)^(1/12)-1) -> 64340.301 | L120: =J120*$H$8 -> 20074.174 | N120: =$H$5 -> 10000000 | P120: =ROUNDUP(B120/12,0) - 1 -> 5 | R120: =IF($X$16/D120>S119,S119,$X$16/D120) -> 4054.5304 | S120: =S119-R120 -> 630169.63 | T120: =IF($X$16/D120>S119,S119*D120,$X$16) -> 64340.301 | X120: 72 | Y120: 6
A121: WHITE | B121: 73 | C121: =T121 -> 64340.301 | D121: =D120*(1+(1+$H$6)^(1/12)-1) -> 15.970843 | E121: =IF(AND(OR($N$5="Other",$N$5="Debt"), B121<24),R121*(D121-10), IF(AND($N$5="Equity", B121<12),R121*(D121-10), 0)) -> 0 | F121: =IF(AND(OR($N$5="Other",$N$5="Debt"), B121>=24),R121*(D121-10), IF(AND($N$5="Equity", B121>=12),R121*(D121-10),0)) -> 24054.2 | G121: =IF(AND($N$5="Equity", B121< 12), E121*20%, IF(AND($N$5="Equity", B121>= 12),F121*12.5%, IF(AND($N$5="Other", B121<24),E121*$H$8, IF(AND($N$5="Other", B121>=24),F121*12.5%,F121*$H$8)))) -> 3006.7749 | H121: =S121*D121 -> 10000000 | J121: =$H$5*((1+$H$7)^(1/12)-1) -> 64340.301 | L121: =J121*$H$8 -> 20074.174 | N121: =$H$5 -> 10000000 | P121: =ROUNDUP(B121/12,0) - 1 -> 6 | R121: =IF($X$16/D121>S120,S120,$X$16/D121) -> 4028.6102 | S121: =S120-R121 -> 626141.02 | T121: =IF($X$16/D121>S120,S120*D121,$X$16) -> 64340.301 | X121: 73 | Y121: 7
A122: ORANGE | B122: 74 | C122: =T122 -> 64340.301 | D122: =D121*(1+(1+$H$6)^(1/12)-1) -> 16.0736 | E122: =IF(AND(OR($N$5="Other",$N$5="Debt"), B122<24),R122*(D122-10), IF(AND($N$5="Equity", B122<12),R122*(D122-10), 0)) -> 0 | F122: =IF(AND(OR($N$5="Other",$N$5="Debt"), B122>=24),R122*(D122-10), IF(AND($N$5="Equity", B122>=12),R122*(D122-10),0)) -> 24311.744 | G122: =IF(AND($N$5="Equity", B122< 12), E122*20%, IF(AND($N$5="Equity", B122>= 12),F122*12.5%, IF(AND($N$5="Other", B122<24),E122*$H$8, IF(AND($N$5="Other", B122>=24),F122*12.5%,F122*$H$8)))) -> 3038.9681 | H122: =S122*D122 -> 10000000 | J122: =$H$5*((1+$H$7)^(1/12)-1) -> 64340.301 | L122: =J122*$H$8 -> 20074.174 | N122: =$H$5 -> 10000000 | P122: =ROUNDUP(B122/12,0) - 1 -> 6 | R122: =IF($X$16/D122>S121,S121,$X$16/D122) -> 4002.8557 | S122: =S121-R122 -> 622138.16 | T122: =IF($X$16/D122>S121,S121*D122,$X$16) -> 64340.301 | X122: 74 | Y122: 7
A123: WHITE | B123: 75 | C123: =T123 -> 64340.301 | D123: =D122*(1+(1+$H$6)^(1/12)-1) -> 16.177018 | E123: =IF(AND(OR($N$5="Other",$N$5="Debt"), B123<24),R123*(D123-10), IF(AND($N$5="Equity", B123<12),R123*(D123-10), 0)) -> 0 | F123: =IF(AND(OR($N$5="Other",$N$5="Debt"), B123>=24),R123*(D123-10), IF(AND($N$5="Equity", B123>=12),R123*(D123-10),0)) -> 24567.643 | G123: =IF(AND($N$5="Equity", B123< 12), E123*20%, IF(AND($N$5="Equity", B123>= 12),F123*12.5%, IF(AND($N$5="Other", B123<24),E123*$H$8, IF(AND($N$5="Other", B123>=24),F123*12.5%,F123*$H$8)))) -> 3070.9554 | H123: =S123*D123 -> 10000000 | J123: =$H$5*((1+$H$7)^(1/12)-1) -> 64340.301 | L123: =J123*$H$8 -> 20074.174 | N123: =$H$5 -> 10000000 | P123: =ROUNDUP(B123/12,0) - 1 -> 6 | R123: =IF($X$16/D123>S122,S122,$X$16/D123) -> 3977.2658 | S123: =S122-R123 -> 618160.9 | T123: =IF($X$16/D123>S122,S122*D123,$X$16) -> 64340.301 | X123: 75 | Y123: 7
A124: ORANGE | B124: 76 | C124: =T124 -> 64340.301 | D124: =D123*(1+(1+$H$6)^(1/12)-1) -> 16.281102 | E124: =IF(AND(OR($N$5="Other",$N$5="Debt"), B124<24),R124*(D124-10), IF(AND($N$5="Equity", B124<12),R124*(D124-10), 0)) -> 0 | F124: =IF(AND(OR($N$5="Other",$N$5="Debt"), B124>=24),R124*(D124-10), IF(AND($N$5="Equity", B124>=12),R124*(D124-10),0)) -> 24821.906 | G124: =IF(AND($N$5="Equity", B124< 12), E124*20%, IF(AND($N$5="Equity", B124>= 12),F124*12.5%, IF(AND($N$5="Other", B124<24),E124*$H$8, IF(AND($N$5="Other", B124>=24),F124*12.5%,F124*$H$8)))) -> 3102.7382 | H124: =S124*D124 -> 10000000 | J124: =$H$5*((1+$H$7)^(1/12)-1) -> 64340.301 | L124: =J124*$H$8 -> 20074.174 | N124: =$H$5 -> 10000000 | P124: =ROUNDUP(B124/12,0) - 1 -> 6 | R124: =IF($X$16/D124>S123,S123,$X$16/D124) -> 3951.8396 | S124: =S123-R124 -> 614209.06 | T124: =IF($X$16/D124>S123,S123*D124,$X$16) -> 64340.301 | X124: 76 | Y124: 7
A125: WHITE | B125: 77 | C125: =T125 -> 64340.301 | D125: =D124*(1+(1+$H$6)^(1/12)-1) -> 16.385855 | E125: =IF(AND(OR($N$5="Other",$N$5="Debt"), B125<24),R125*(D125-10), IF(AND($N$5="Equity", B125<12),R125*(D125-10), 0)) -> 0 | F125: =IF(AND(OR($N$5="Other",$N$5="Debt"), B125>=24),R125*(D125-10), IF(AND($N$5="Equity", B125>=12),R125*(D125-10),0)) -> 25074.543 | G125: =IF(AND($N$5="Equity", B125< 12), E125*20%, IF(AND($N$5="Equity", B125>= 12),F125*12.5%, IF(AND($N$5="Other", B125<24),E125*$H$8, IF(AND($N$5="Other", B125>=24),F125*12.5%,F125*$H$8)))) -> 3134.3178 | H125: =S125*D125 -> 10000000 | J125: =$H$5*((1+$H$7)^(1/12)-1) -> 64340.301 | L125: =J125*$H$8 -> 20074.174 | N125: =$H$5 -> 10000000 | P125: =ROUNDUP(B125/12,0) - 1 -> 6 | R125: =IF($X$16/D125>S124,S124,$X$16/D125) -> 3926.5759 | S125: =S124-R125 -> 610282.48 | T125: =IF($X$16/D125>S124,S124*D125,$X$16) -> 64340.301 | X125: 77 | Y125: 7
A126: ORANGE | B126: 78 | C126: =T126 -> 64340.301 | D126: =D125*(1+(1+$H$6)^(1/12)-1) -> 16.491282 | E126: =IF(AND(OR($N$5="Other",$N$5="Debt"), B126<24),R126*(D126-10), IF(AND($N$5="Equity", B126<12),R126*(D126-10), 0)) -> 0 | F126: =IF(AND(OR($N$5="Other",$N$5="Debt"), B126>=24),R126*(D126-10), IF(AND($N$5="Equity", B126>=12),R126*(D126-10),0)) -> 25325.565 | G126: =IF(AND($N$5="Equity", B126< 12), E126*20%, IF(AND($N$5="Equity", B126>= 12),F126*12.5%, IF(AND($N$5="Other", B126<24),E126*$H$8, IF(AND($N$5="Other", B126>=24),F126*12.5%,F126*$H$8)))) -> 3165.6956 | H126: =S126*D126 -> 10000000 | J126: =$H$5*((1+$H$7)^(1/12)-1) -> 64340.301 | L126: =J126*$H$8 -> 20074.174 | N126: =$H$5 -> 10000000 | P126: =ROUNDUP(B126/12,0) - 1 -> 6 | R126: =IF($X$16/D126>S125,S125,$X$16/D126) -> 3901.4737 | S126: =S125-R126 -> 606381.01 | T126: =IF($X$16/D126>S125,S125*D126,$X$16) -> 64340.301 | X126: 78 | Y126: 7
A127: WHITE | B127: 79 | C127: =T127 -> 64340.301 | D127: =D126*(1+(1+$H$6)^(1/12)-1) -> 16.597387 | E127: =IF(AND(OR($N$5="Other",$N$5="Debt"), B127<24),R127*(D127-10), IF(AND($N$5="Equity", B127<12),R127*(D127-10), 0)) -> 0 | F127: =IF(AND(OR($N$5="Other",$N$5="Debt"), B127>=24),R127*(D127-10), IF(AND($N$5="Equity", B127>=12),R127*(D127-10),0)) -> 25574.982 | G127: =IF(AND($N$5="Equity", B127< 12), E127*20%, IF(AND($N$5="Equity", B127>= 12),F127*12.5%, IF(AND($N$5="Other", B127<24),E127*$H$8, IF(AND($N$5="Other", B127>=24),F127*12.5%,F127*$H$8)))) -> 3196.8727 | H127: =S127*D127 -> 10000000 | J127: =$H$5*((1+$H$7)^(1/12)-1) -> 64340.301 | L127: =J127*$H$8 -> 20074.174 | N127: =$H$5 -> 10000000 | P127: =ROUNDUP(B127/12,0) - 1 -> 6 | R127: =IF($X$16/D127>S126,S126,$X$16/D127) -> 3876.5319 | S127: =S126-R127 -> 602504.47 | T127: =IF($X$16/D127>S126,S126*D127,$X$16) -> 64340.301 | X127: 79 | Y127: 7
A128: ORANGE | B128: 80 | C128: =T128 -> 64340.301 | D128: =D127*(1+(1+$H$6)^(1/12)-1) -> 16.704175 | E128: =IF(AND(OR($N$5="Other",$N$5="Debt"), B128<24),R128*(D128-10), IF(AND($N$5="Equity", B128<12),R128*(D128-10), 0)) -> 0 | F128: =IF(AND(OR($N$5="Other",$N$5="Debt"), B128>=24),R128*(D128-10), IF(AND($N$5="Equity", B128>=12),R128*(D128-10),0)) -> 25822.805 | G128: =IF(AND($N$5="Equity", B128< 12), E128*20%, IF(AND($N$5="Equity", B128>= 12),F128*12.5%, IF(AND($N$5="Other", B128<24),E128*$H$8, IF(AND($N$5="Other", B128>=24),F128*12.5%,F128*$H$8)))) -> 3227.8506 | H128: =S128*D128 -> 10000000 | J128: =$H$5*((1+$H$7)^(1/12)-1) -> 64340.301 | L128: =J128*$H$8 -> 20074.174 | N128: =$H$5 -> 10000000 | P128: =ROUNDUP(B128/12,0) - 1 -> 6 | R128: =IF($X$16/D128>S127,S127,$X$16/D128) -> 3851.7497 | S128: =S127-R128 -> 598652.72 | T128: =IF($X$16/D128>S127,S127*D128,$X$16) -> 64340.301 | X128: 80 | Y128: 7
A129: WHITE | B129: 81 | C129: =T129 -> 64340.301 | D129: =D128*(1+(1+$H$6)^(1/12)-1) -> 16.81165 | E129: =IF(AND(OR($N$5="Other",$N$5="Debt"), B129<24),R129*(D129-10), IF(AND($N$5="Equity", B129<12),R129*(D129-10), 0)) -> 0 | F129: =IF(AND(OR($N$5="Other",$N$5="Debt"), B129>=24),R129*(D129-10), IF(AND($N$5="Equity", B129>=12),R129*(D129-10),0)) -> 26069.043 | G129: =IF(AND($N$5="Equity", B129< 12), E129*20%, IF(AND($N$5="Equity", B129>= 12),F129*12.5%, IF(AND($N$5="Other", B129<24),E129*$H$8, IF(AND($N$5="Other", B129>=24),F129*12.5%,F129*$H$8)))) -> 3258.6304 | H129: =S129*D129 -> 10000000 | J129: =$H$5*((1+$H$7)^(1/12)-1) -> 64340.301 | L129: =J129*$H$8 -> 20074.174 | N129: =$H$5 -> 10000000 | P129: =ROUNDUP(B129/12,0) - 1 -> 6 | R129: =IF($X$16/D129>S128,S128,$X$16/D129) -> 3827.1258 | S129: =S128-R129 -> 594825.6 | T129: =IF($X$16/D129>S128,S128*D129,$X$16) -> 64340.301 | X129: 81 | Y129: 7
A130: ORANGE | B130: 82 | C130: =T130 -> 64340.301 | D130: =D129*(1+(1+$H$6)^(1/12)-1) -> 16.919817 | E130: =IF(AND(OR($N$5="Other",$N$5="Debt"), B130<24),R130*(D130-10), IF(AND($N$5="Equity", B130<12),R130*(D130-10), 0)) -> 0 | F130: =IF(AND(OR($N$5="Other",$N$5="Debt"), B130>=24),R130*(D130-10), IF(AND($N$5="Equity", B130>=12),R130*(D130-10),0)) -> 26313.707 | G130: =IF(AND($N$5="Equity", B130< 12), E130*20%, IF(AND($N$5="Equity", B130>= 12),F130*12.5%, IF(AND($N$5="Other", B130<24),E130*$H$8, IF(AND($N$5="Other", B130>=24),F130*12.5%,F130*$H$8)))) -> 3289.2134 | H130: =S130*D130 -> 10000000 | J130: =$H$5*((1+$H$7)^(1/12)-1) -> 64340.301 | L130: =J130*$H$8 -> 20074.174 | N130: =$H$5 -> 10000000 | P130: =ROUNDUP(B130/12,0) - 1 -> 6 | R130: =IF($X$16/D130>S129,S129,$X$16/D130) -> 3802.6594 | S130: =S129-R130 -> 591022.94 | T130: =IF($X$16/D130>S129,S129*D130,$X$16) -> 64340.301 | X130: 82 | Y130: 7
... A348: ORANGE | B348: 300 | C348: =T348 -> 64340.301 | D348: =D347*(1+(1+$H$6)^(1/12)-1) -> 68.484752 | E348: =IF(AND(OR($N$5="Other",$N$5="Debt"), B348<24),R348*(D348-10), IF(AND($N$5="Equity", B348<12),R348*(D348-10), 0)) -> 0 | F348: =IF(AND(OR($N$5="Other",$N$5="Debt"), B348>=24),R348*(D348-10), IF(AND($N$5="Equity", B348>=12),R348*(D348-10),0)) -> 54945.465 | G348: =IF(AND($N$5="Equity", B348< 12), E348*20%, IF(AND($N$5="Equity", B348>= 12),F348*12.5%, IF(AND($N$5="Other", B348<24),E348*$H$8, IF(AND($N$5="Other", B348>=24),F348*12.5%,F348*$H$8)))) -> 6868.1831 | H348: =S348*D348 -> 10000000 | J348: =$H$5*((1+$H$7)^(1/12)-1) -> 64340.301 | L348: =J348*$H$8 -> 20074.174 | N348: =$H$5 -> 10000000 | P348: =ROUNDUP(B348/12,0) - 1 -> 24 | R348: =IF($X$16/D348>S347,S347,$X$16/D348) -> 939.4836 | S348: =S347-R348 -> 146017.9 | T348: =IF($X$16/D348>S347,S347*D348,$X$16) -> 64340.301 | X348: 300 | Y348: 25
R350: =S348*D348 -> 10000000
R351: =S348*58.48*10.4% -> 888069.22

Sheet 4
A2: BACK | B2: NON-EQUITY MF & FD TAXATION
B5: Total investment amount | G5: 1000000 | J5: POST TAX RETURN
B6: Assumed return - MF* (35%< Eq Exposure <65%) | G6: 0.07
B7: Assumed return - Fixed Deposit | G7: 0.07 | J7: NON-EQ MF | L7: FIXED DEPOSIT
B8: Tax slab | G8: 0.312 | J8: =IF(J19<=0,"",RATE(J19,,-J17,J28)) -> 0.064600399 | L8: =IF(L19<=0,"",RATE(L19,,-L17,L28)) -> 0.051028587
B9: Investment done in FY | G9: 2017-18 | J9: * E.g., Balanced Hybrid, Dynamic Asset Allocation, Balanced Advantage Funds (based on avg exposure in domestic equity in a year)
B10: Redemption done in FY | G10: 2024-25
B11: =IF(J19<=0,"*SALE FY cannot be same or earlier than the PURCHASE FY!",IF(J19>=3,"","*You're not entitled for Long term Capital Gain as investment tenure is less than 3 years"))
B12: Prepared for: | D12: =" "&UPPER('Main Menu'!C29) -> CLIENT NAME
B13: prepared by: | D13: =" "&UPPER('Main Menu'!L29) -> PARTNER NAME | L13: ="Dated: "& TEXT(TODAY(),"DD-MMM-YYYY") -> Dated: 28-Aug-2025
B14: Disclaimer: Result or output of these calculators are for representational purpose only. Assumptions made here, may or may not be appropriate considering your needs, priorities and risk profile. Check with an expert before taking any financial decision.
B16: PARTICULARS | J16: NON-EQUITY MF | L16: FIXED DEPOSIT
B17: Purchase Amount | J17: =G5 -> 1000000 | L17: =G5 -> 1000000 | P17: YEAR | Q17: CII | R17: YEARS
B18: Assumed Return | J18: =G6 -> 0.07 | L18: =G7 -> 0.07 | P18: 2001-02 | Q18: 100 | R18: =IF(ISNUMBER(R17),R17+1,0+1) -> 1
B19: Tenure of Investment (in years) | J19: =VLOOKUP(G10,CII[],3,0) - VLOOKUP(G9,CII[],3,0) -> 7 | L19: =VLOOKUP(G10,CII[],3,0) - VLOOKUP(G9,CII[],3,0) -> 7 | P19: 2002-03 | Q19: 105 | R19: =IF(ISNUMBER(R18),R18+1,0+1) -> 2
B20: Pre-Tax Sale Value | J20: =IF(J19<=0,"",FV(J18,J19,,-J17)) -> 1605781.5 | L20: =IF(L19<=0,"",FV(L18,L19,,-L17)) -> 1605781.5 | P20: 2003-04 | Q20: 109 | R20: =IF(ISNUMBER(R19),R19+1,0+1) -> 3
B21: Interest Income | J21: NA | L21: =IF(L19<=0,"",L20-L17) -> 605781.48 | P21: 2004-05 | Q21: 113 | R21: =IF(ISNUMBER(R20),R20+1,0+1) -> 4
B22: =IF(J19>=3,"Long Term Capital Gain Before Indexation","Short Term Capital Gain") -> Long Term Capital Gain Before Indexation | J22: =IF(J19<=0,"",(J20-J17)) -> 605781.48 | L22: NA | P22: 2005-06 | Q22: 117 | R22: =IF(ISNUMBER(R21),R21+1,0+1) -> 5
B23: =IF(J19>=3,"Indexed Cost of Acquisition","Cost of Acquisition") -> Indexed Cost of Acquisition | J23: =IF(J19<=0,"",IF(J19>=3,J17*(VLOOKUP(G10,CII[],2,0)/VLOOKUP(G9,CII[],2,0)),J17)) -> 1334558.8 | L23: NA | P23: 2006-07 | Q23: 122 | R23: =IF(ISNUMBER(R22),R22+1,0+1) -> 6
B24: =IF(J19>=3,"Long Term Capital Gain After Indexation","Short Term Capital Gain") -> Long Term Capital Gain After Indexation | J24: =IF(J19<=0,"",J20-J23) -> 271222.65 | L24: NA | P24: 2007-08 | Q24: 129 | R24: =IF(ISNUMBER(R23),R23+1,0+1) -> 7
B25: Applicable Tax Rate | J25: =IF(J19>=3,20.6%,G8) -> 0.206 | L25: =G8 -> 0.312 | P25: 2008-09 | Q25: 137 | R25: =IF(ISNUMBER(R24),R24+1,0+1) -> 8
B26: Tax Payable | J26: =IF(J19<=0,"",J25*J24) -> 55871.867 | L26: =IF(L19<=0,"",L25*L21) -> 189003.82 | P26: 2009-10 | Q26: 148 | R26: =IF(ISNUMBER(R25),R25+1,0+1) -> 9
B27: Net Gain | J27: =IF(J19<=0,"",J22-J26) -> 549909.61 | L27: =IF(L19<=0,"",L21-L26) -> 416777.66 | P27: 2010-11 | Q27: 167 | R27: =IF(ISNUMBER(R26),R26+1,0+1) -> 10
B28: Post-Tax Sale Value | J28: =IF(J19<=0,"",J17+J27) -> 1549909.6 | L28: =IF(L19<=0,"",L17+L27) -> 1416777.7 | P28: 2011-12 | Q28: 184 | R28: =IF(ISNUMBER(R27),R27+1,0+1) -> 11
P29: 2012-13 | Q29: 200 | R29: =IF(ISNUMBER(R28),R28+1,0+1) -> 12
P30: 2013-14 | Q30: 220 | R30: =IF(ISNUMBER(R29),R29+1,0+1) -> 13
P31: 2014-15 | Q31: 240 | R31: =IF(ISNUMBER(R30),R30+1,0+1) -> 14
P32: 2015-16 | Q32: 254 | R32: =IF(ISNUMBER(R31),R31+1,0+1) -> 15
P33: 2016-17 | Q33: 264 | R33: =IF(ISNUMBER(R32),R32+1,0+1) -> 16
P34: 2017-18 | Q34: 272 | R34: =IF(ISNUMBER(R33),R33+1,0+1) -> 17
P35: 2018-19 | Q35: 280 | R35: =IF(ISNUMBER(R34),R34+1,0+1) -> 18
P36: 2019-20 | Q36: 289 | R36: =IF(ISNUMBER(R35),R35+1,0+1) -> 19
P37: 2020-21 | Q37: 301 | R37: =IF(ISNUMBER(R36),R36+1,0+1) -> 20
P38: 2021-22 | Q38: 317 | R38: =IF(ISNUMBER(R37),R37+1,0+1) -> 21
P39: 2022-23 | Q39: 331 | R39: =IF(ISNUMBER(R38),R38+1,0+1) -> 22
P40: 2023-24 | Q40: 348 | R40: =IF(ISNUMBER(R39),R39+1,0+1) -> 23
P41: 2024-25 | Q41: 363 | R41: =IF(ISNUMBER(R40),R40+1,0+1) -> 24

Sheet 5
A2: BACK | B2: SIP & SWP - YEAR ON YEAR CASHFLOW
B5: SIP amount (per month) | H5: 20000 | K5: SWP WILL START FROM THE AGE
B6: SIP top-up % (after every year), if any | H6: 0
B7: SIP tenure (no. of years) | H7: 20 | K7: =H9+H7+H8 -> 50
B8: After SIP tenure ends, SWP starts after no. of years | H8: 0
B9: Current age | H9: 30 | K9: SWP WILL CONTINUE TILL THE AGE OF
B10: Expected return from SIP (CAGR) | H10: 0.14
B11: Withdrawal amount per month (in today's value) | H11: 200000 | K11: =IF(ISNA(R19),"BEYOND "&C119,R19) -> 72
B12: Increase in withdrawal amount every year | H12: 0
B13: Expected portfolio return in withdrawal phase | H13: 0.1
B15: Prepared for: | D15: =" "&UPPER('Main Menu'!C29) -> CLIENT NAME
B16: Prepared by: | D16: =" "&UPPER('Main Menu'!L29) -> PARTNER NAME | I16: ="Dated: "& TEXT(TODAY(),"DD-MMM-YYYY") -> Dated: 28-Aug-2025
B18: YEARS | C18: AGE | D18: PORTFOLIO @ START OF YEAR | F18: SIP INVESTMENT PER MONTH | H18: SWP INCOME RECEIVED / MTH | J18: SWP INCOME RECEIVED / YEAR | L18: BALANCE @ START OF YEAR | N18: BALANCE @ END OF YEAR | Q18: SWP WILL LAST FOR
Q19: AGE | R19: =INDEX(C21:C119,MATCH(TRUE,Q21:Q119,0))-1 -> 72
B20: 1 | C20: =H9 -> 30 | D20: 0 | F20: =H5 -> 20000 | H20: 0 | J20: 0 | L20: 0 | N20: =FV((1+$H$10)^(1/12)-1,12,-F20,,1) -> 257835.77
B21: 2 | C21: =C20+1 -> 31 | D21: =N20 -> 257835.77 | F21: =IF(B21>$H$7,0, F20*(1+$H$6)) -> 20000 | H21: =IF(OR(L20=0,B20<($H$7+$H$8)),0,IF(H20=0,FV($H$12,B21,,-$H$11),H20*(1+$H$12))) -> 0 | J21: =H21*12 -> 0 | L21: =IF((D21-(H21*12))<0,0,(D21-(H21*12))) -> 257835.77 | N21: =IF(B20>=MAX($H$7,$H$8), FV((1+$H$13)^(1/12)-1,12,-F21,-L21,1), FV((1+$H$10)^(1/12)-1,12,-F21,-L21,1)) -> 551768.56 | Q21: =L21=0 -> FALSE | S21: =FALSE -> FALSE | T21: =MOD(ROW(),2) -> 1
B22: 3 | C22: =C21+1 -> 32 | D22: =N21 -> 551768.56 | F22: =IF(B22>$H$7,0, F21*(1+$H$6)) -> 20000 | H22: =IF(OR(L21=0,B21<($H$7+$H$8)),0,IF(H21=0,FV($H$12,B22,,-$H$11),H21*(1+$H$12))) -> 0 | J22: =H22*12 -> 0 | L22: =IF((D22-(H22*12))<0,0,(D22-(H22*12))) -> 551768.56 | N22: =IF(B21>=MAX($H$7,$H$8), FV((1+$H$13)^(1/12)-1,12,-F22,-L22,1), FV((1+$H$10)^(1/12)-1,12,-F22,-L22,1)) -> 886851.93 | Q22: =L22=0 -> FALSE | S22: =L21=0 -> FALSE | T22: =MOD(ROW(),2) -> 0
B23: 4 | C23: =C22+1 -> 33 | D23: =N22 -> 886851.93 | F23: =IF(B23>$H$7,0, F22*(1+$H$6)) -> 20000 | H23: =IF(OR(L22=0,B22<($H$7+$H$8)),0,IF(H22=0,FV($H$12,B23,,-$H$11),H22*(1+$H$12))) -> 0 | J23: =H23*12 -> 0 | L23: =IF((D23-(H23*12))<0,0,(D23-(H23*12))) -> 886851.93 | N23: =IF(B22>=MAX($H$7,$H$8), FV((1+$H$13)^(1/12)-1,12,-F23,-L23,1), FV((1+$H$10)^(1/12)-1,12,-F23,-L23,1)) -> 1268847 | Q23: =L23=0 -> FALSE | S23: =L22=0 -> FALSE | T23: =MOD(ROW(),2) -> 1
B24: 5 | C24: =C23+1 -> 34 | D24: =N23 -> 1268847 | F24: =IF(B24>$H$7,0, F23*(1+$H$6)) -> 20000 | H24: =IF(OR(L23=0,B23<($H$7+$H$8)),0,IF(H23=0,FV($H$12,B24,,-$H$11),H23*(1+$H$12))) -> 0 | J24: =H24*12 -> 0 | L24: =IF((D24-(H24*12))<0,0,(D24-(H24*12))) -> 1268847 | N24: =IF(B23>=MAX($H$7,$H$8), FV((1+$H$13)^(1/12)-1,12,-F24,-L24,1), FV((1+$H$10)^(1/12)-1,12,-F24,-L24,1)) -> 1704321.3 | Q24: =L24=0 -> FALSE | S24: =L23=0 -> FALSE | T24: =MOD(ROW(),2) -> 0
B25: 6 | C25: =C24+1 -> 35 | D25: =N24 -> 1704321.3 | F25: =IF(B25>$H$7,0, F24*(1+$H$6)) -> 20000 | H25: =IF(OR(L24=0,B24<($H$7+$H$8)),0,IF(H24=0,FV($H$12,B25,,-$H$11),H24*(1+$H$12))) -> 0 | J25: =H25*12 -> 0 | L25: =IF((D25-(H25*12))<0,0,(D25-(H25*12))) -> 1704321.3 | N25: =IF(B24>=MAX($H$7,$H$8), FV((1+$H$13)^(1/12)-1,12,-F25,-L25,1), FV((1+$H$10)^(1/12)-1,12,-F25,-L25,1)) -> 2200762.1 | Q25: =L25=0 -> FALSE | S25: =L24=0 -> FALSE | T25: =MOD(ROW(),2) -> 1
B26: 7 | C26: =C25+1 -> 36 | D26: =N25 -> 2200762.1 | F26: =IF(B26>$H$7,0, F25*(1+$H$6)) -> 20000 | H26: =IF(OR(L25=0,B25<($H$7+$H$8)),0,IF(H25=0,FV($H$12,B26,,-$H$11),H25*(1+$H$12))) -> 0 | J26: =H26*12 -> 0 | L26: =IF((D26-(H26*12))<0,0,(D26-(H26*12))) -> 2200762.1 | N26: =IF(B25>=MAX($H$7,$H$8), FV((1+$H$13)^(1/12)-1,12,-F26,-L26,1), FV((1+$H$10)^(1/12)-1,12,-F26,-L26,1)) -> 2766704.5 | Q26: =L26=0 -> FALSE | S26: =L25=0 -> FALSE | T26: =MOD(ROW(),2) -> 0
B27: 8 | C27: =C26+1 -> 37 | D27: =N26 -> 2766704.5 | F27: =IF(B27>$H$7,0, F26*(1+$H$6)) -> 20000 | H27: =IF(OR(L26=0,B26<($H$7+$H$8)),0,IF(H26=0,FV($H$12,B27,,-$H$11),H26*(1+$H$12))) -> 0 | J27: =H27*12 -> 0 | L27: =IF((D27-(H27*12))<0,0,(D27-(H27*12))) -> 2766704.5 | N27: =IF(B26>=MAX($H$7,$H$8), FV((1+$H$13)^(1/12)-1,12,-F27,-L27,1), FV((1+$H$10)^(1/12)-1,12,-F27,-L27,1)) -> 3411879 | Q27: =L27=0 -> FALSE | S27: =L26=0 -> FALSE | T27: =MOD(ROW(),2) -> 1
B28: 9 | C28: =C27+1 -> 38 | D28: =N27 -> 3411879 | F28: =IF(B28>$H$7,0, F27*(1+$H$6)) -> 20000 | H28: =IF(OR(L27=0,B27<($H$7+$H$8)),0,IF(H27=0,FV($H$12,B28,,-$H$11),H27*(1+$H$12))) -> 0 | J28: =H28*12 -> 0 | L28: =IF((D28-(H28*12))<0,0,(D28-(H28*12))) -> 3411879 | N28: =IF(B27>=MAX($H$7,$H$8), FV((1+$H$13)^(1/12)-1,12,-F28,-L28,1), FV((1+$H$10)^(1/12)-1,12,-F28,-L28,1)) -> 4147377.8 | Q28: =L28=0 -> FALSE | S28: =L27=0 -> FALSE | T28: =MOD(ROW(),2) -> 0
B29: 10 | C29: =C28+1 -> 39 | D29: =N28 -> 4147377.8 | F29: =IF(B29>$H$7,0, F28*(1+$H$6)) -> 20000 | H29: =IF(OR(L28=0,B28<($H$7+$H$8)),0,IF(H28=0,FV($H$12,B29,,-$H$11),H28*(1+$H$12))) -> 0 | J29: =H29*12 -> 0 | L29: =IF((D29-(H29*12))<0,0,(D29-(H29*12))) -> 4147377.8 | N29: =IF(B28>=MAX($H$7,$H$8), FV((1+$H$13)^(1/12)-1,12,-F29,-L29,1), FV((1+$H$10)^(1/12)-1,12,-F29,-L29,1)) -> 4985846.4 | Q29: =L29=0 -> FALSE | S29: =L28=0 -> FALSE | T29: =MOD(ROW(),2) -> 1
B30: 11 | C30: =C29+1 -> 40 | D30: =N29 -> 4985846.4 | F30: =IF(B30>$H$7,0, F29*(1+$H$6)) -> 20000 | H30: =IF(OR(L29=0,B29<($H$7+$H$8)),0,IF(H29=0,FV($H$12,B30,,-$H$11),H29*(1+$H$12))) -> 0 | J30: =H30*12 -> 0 | L30: =IF((D30-(H30*12))<0,0,(D30-(H30*12))) -> 4985846.4 | N30: =IF(B29>=MAX($H$7,$H$8), FV((1+$H$13)^(1/12)-1,12,-F30,-L30,1), FV((1+$H$10)^(1/12)-1,12,-F30,-L30,1)) -> 5941700.7 | Q30: =L30=0 -> FALSE | S30: =L29=0 -> FALSE | T30: =MOD(ROW(),2) -> 0
B31: 12 | C31: =C30+1 -> 41 | D31: =N30 -> 5941700.7 | F31: =IF(B31>$H$7,0, F30*(1+$H$6)) -> 20000 | H31: =IF(OR(L30=0,B30<($H$7+$H$8)),0,IF(H30=0,FV($H$12,B31,,-$H$11),H30*(1+$H$12))) -> 0 | J31: =H31*12 -> 0 | L31: =IF((D31-(H31*12))<0,0,(D31-(H31*12))) -> 5941700.7 | N31: =IF(B30>=MAX($H$7,$H$8), FV((1+$H$13)^(1/12)-1,12,-F31,-L31,1), FV((1+$H$10)^(1/12)-1,12,-F31,-L31,1)) -> 7031374.6 | Q31: =L31=0 -> FALSE | S31: =L30=0 -> FALSE | T31: =MOD(ROW(),2) -> 1
B32: 13 | C32: =C31+1 -> 42 | D32: =N31 -> 7031374.6 | F32: =IF(B32>$H$7,0, F31*(1+$H$6)) -> 20000 | H32: =IF(OR(L31=0,B31<($H$7+$H$8)),0,IF(H31=0,FV($H$12,B32,,-$H$11),H31*(1+$H$12))) -> 0 | J32: =H32*12 -> 0 | L32: =IF((D32-(H32*12))<0,0,(D32-(H32*12))) -> 7031374.6 | N32: =IF(B31>=MAX($H$7,$H$8), FV((1+$H$13)^(1/12)-1,12,-F32,-L32,1), FV((1+$H$10)^(1/12)-1,12,-F32,-L32,1)) -> 8273602.8 | Q32: =L32=0 -> FALSE | S32: =L31=0 -> FALSE | T32: =MOD(ROW(),2) -> 0
B33: 14 | C33: =C32+1 -> 43 | D33: =N32 -> 8273602.8 | F33: =IF(B33>$H$7,0, F32*(1+$H$6)) -> 20000 | H33: =IF(OR(L32=0,B32<($H$7+$H$8)),0,IF(H32=0,FV($H$12,B33,,-$H$11),H32*(1+$H$12))) -> 0 | J33: =H33*12 -> 0 | L33: =IF((D33-(H33*12))<0,0,(D33-(H33*12))) -> 8273602.8 | N33: =IF(B32>=MAX($H$7,$H$8), FV((1+$H$13)^(1/12)-1,12,-F33,-L33,1), FV((1+$H$10)^(1/12)-1,12,-F33,-L33,1)) -> 9689743 | Q33: =L33=0 -> FALSE | S33: =L32=0 -> FALSE | T33: =MOD(ROW(),2) -> 1
... B119: 100 | C119: =C118+1 -> 129 | D119: =N118 -> 0 | F119: =IF(B119>$H$7,0, F118*(1+$H$6)) -> 0 | H119: =IF(OR(L118=0,B118<($H$7+$H$8)),0,IF(H118=0,FV($H$12,B119,,-$H$11),H118*(1+$H$12))) -> 0 | J119: =H119*12 -> 0 | L119: =IF((D119-(H119*12))<0,0,(D119-(H119*12))) -> 0 | N119: =IF(B118>=MAX($H$7,$H$8), FV((1+$H$13)^(1/12)-1,12,-F119,-L119,1), FV((1+$H$10)^(1/12)-1,12,-F119,-L119,1)) -> 0 | Q119: =L119=0 -> TRUE | S119: =L118=0 -> TRUE | T119: =MOD(ROW(),2) -> 1

Sheet 6
A2: BACK | B2: TERM INSURANCE COVER REQUIREMENT
Q4: Annual Expenses | S4: =IF(OR(ISBLANK(K13),K13=0),12*K12,12*K13) -> 600000
E6: PERSONAL DETAILS
E7: Your age | K7: 45
E8: Your spouse's age | K8: 40 | Q8: Real rate of return | S8: =((1+K18)/(1+K14))-1 -> 0.028037383
E9: Spouse's life expectancy | K9: 85 | Q9: Required corpus | S9: =-PV(S8,K9-K8,S4,,1) -> 15660984
E11: EXPENSE DETAILS
E12: Current monthly household and lifestyle expenses | K12: 50000 | Q12: Plus Loan O/S | S12: =S9+K17 -> 18660984
E13: Monthly expenses in absence of breadwinner | Q13: Minus LI Cover | S13: =K20 -> 2500000
E14: Assumed inflation | K14: 0.07 | Q14: Minus Assets | S14: =K21 -> 1000000
E16: ASSETS & LIABILITIES DETAILS
E17: Your total loan outstanding (i.e. o/s principal amount) | K17: 3000000 | Q17: Addl Ins. Cover | S17: =S12-S13-S14 -> 15160984
E18: Assumed return on insurance proceeds in case of a claim | K18: 0.1
E19: Total required life insurance cover | K19: =K22+SUM(K20:L21) -> 18660984
E20: Existing life insurance cover amount | K20: 2500000
E21: Existing financial assets (not linked to any critical goal) | K21: 1000000
E22: Additional life insurance cover required | K22: =S17 -> 15160984
E24: Prepared for: | G24: =" "&UPPER('Main Menu'!C29) -> CLIENT NAME
E25: Prepared by: | G25: =" "&UPPER('Main Menu'!L29) -> PARTNER NAME
K26: ="Dated: "& TEXT(TODAY(),"DD-MMM-YYYY") -> Dated: 28-Aug-2025

Sheet 7
A2: BACK | B2: RETIREMENT ROADMAP
B5: Current age | F5: 40 | I5: ="Monthly expenses* @ retirement" -> Monthly expenses* @ retirement | M5: =FV(F9,F6-F5,,-F8) -> 193484.22 | P5: Real Rate of Return | R5: =((1+F11)/(1+F9))-1 -> 0.028037383
B6: Retirement age | F6: 60 | I6: Required retirement corpus | M6: =-PV(R5,F7-F6,M5*12,,1) -> 42487329 | P6: FV of Linked Asset | R6: =FV(M8,F6-F5,,-M7) -> 0
B7: Life expectancy age | F7: 85 | H7: =IF(F7<F6,"Total investment tenure cannot be less than SIP tenure","") | I7: Current value of linked investment | M7: 0
B8: Current monthly expenses* | F8: 50000 | I8: Assumed return from above investment | M8: 0.1
B9: Assumed inflation | F9: 0.07 | I9: Required lump-sum investment | M9: =-PV(F10,F6-F5,,M6-R6) -> 4404523.9
B10: Assumed return before retirement | F10: 0.12 | I10: Required fixed SIP investment | M10: =-PMT((1+F10)^(1/12)-1,(F6-F5)*12,,M6-R6,1) -> 46189.041 | R10: YEAR | S10: SIP | T10: WEALTH
B11: Assumed return after retirement | F11: 0.1 | I11: Required annual 10% SIP top-up | M11: =(100/VLOOKUP(F6-F5,$R$11:$T$60,3,0))*(M6-R6) -> 22804.173 | R11: 1 | S11: 100 | T11: =FV((1+$F$10)^(1/12)-1,12,-S11,,1) -> 1276.6498
B12: Prepared for: | I12: Prepared by: | R12: 2 | S12: =S11*(1+10%) -> 110 | T12: =FV((1+$F$10)^(1/12)-1,12,-S12,-T11,1) -> 2834.1625
B13: =" "&UPPER('Main Menu'!C29) -> CLIENT NAME | I13: =" "&UPPER('Main Menu'!L29) -> PARTNER NAME | R13: 3 | S13: =S12*(1+10%) -> 121 | T13: =FV((1+$F$10)^(1/12)-1,12,-S13,-T12,1) -> 4719.0083
B14: *Include only household and lifestyle expenses | M14: ="Dated: "& TEXT(TODAY(),"DD-MMM-YYYY") -> Dated: 28-Aug-2025 | R14: 4 | S14: =S13*(1+10%) -> 133.1 | T14: =FV((1+$F$10)^(1/12)-1,12,-S14,-T13,1) -> 6984.5102
B15: YEARS | C15: AGE | D15: START OF YEAR BALANCE | F15: ANNUAL WITHDRAWAL | H15: MONTHLY WITHDRAWAL | J15: REMAINING BALANCE | L15: END OF YEAR BALANCE | R15: 5 | S15: =S14*(1+10%) -> 146.41 | T15: =FV((1+$F$10)^(1/12)-1,12,-S15,-T14,1) -> 9691.7943
R16: 6 | S16: =S15*(1+10%) -> 161.051 | T16: =FV((1+$F$10)^(1/12)-1,12,-S16,-T15,1) -> 12910.867
B17: 1 | C17: =F6+1 -> 61 | D17: =M6 -> 42487329 | F17: =M5*12 -> 2321810.7 | H17: =M5 -> 193484.22 | J17: =D17-F17 -> 40165518 | L17: =J17*(1+$F$11) -> 44182070 | R17: 7 | S17: =S16*(1+10%) -> 177.1561 | T17: =FV((1+$F$10)^(1/12)-1,12,-S17,-T16,1) -> 16721.834 | V17: =C17="" -> FALSE
B18: =IF(C18="","",B17+1) -> 2 | C18: =IF(OR(C17=$F$7,C17=""),"",C17+1) -> 62 | D18: =IF(C18="","",L17) -> 44182070 | F18: =IF(C18="","",F17*(1+$F$9)) -> 2484337.4 | H18: =IF(C18="","",F18/12) -> 207028.12 | J18: =IF(C18="","",ABS(D18-F18)) -> 41697732 | L18: =IF(C18="","",J18*(1+$F$11)) -> 45867506 | R18: 8 | S18: =S17*(1+10%) -> 194.87171 | T18: =FV((1+$F$10)^(1/12)-1,12,-S18,-T17,1) -> 21216.283 | V18: =C18="" -> FALSE
B19: =IF(C19="","",B18+1) -> 3 | C19: =IF(OR(C18=$F$7,C18=""),"",C18+1) -> 63 | D19: =IF(C19="","",L18) -> 45867506 | F19: =IF(C19="","",F18*(1+$F$9)) -> 2658241 | H19: =IF(C19="","",F19/12) -> 221520.09 | J19: =IF(C19="","",ABS(D19-F19)) -> 43209265 | L19: =IF(C19="","",J19*(1+$F$11)) -> 47530191 | R19: 9 | S19: =S18*(1+10%) -> 214.35888 | T19: =FV((1+$F$10)^(1/12)-1,12,-S19,-T18,1) -> 26498.849 | V19: =C19="" -> FALSE
B20: =IF(C20="","",B19+1) -> 4 | C20: =IF(OR(C19=$F$7,C19=""),"",C19+1) -> 64 | D20: =IF(C20="","",L19) -> 47530191 | F20: =IF(C20="","",F19*(1+$F$9)) -> 2844317.9 | H20: =IF(C20="","",F20/12) -> 237026.49 | J20: =IF(C20="","",ABS(D20-F20)) -> 44685873 | L20: =IF(C20="","",J20*(1+$F$11)) -> 49154460 | R20: 10 | S20: =S19*(1+10%) -> 235.79477 | T20: =FV((1+$F$10)^(1/12)-1,12,-S20,-T19,1) -> 32688.985 | V20: =C20="" -> FALSE
B21: =IF(C21="","",B20+1) -> 5 | C21: =IF(OR(C20=$F$7,C20=""),"",C20+1) -> 65 | D21: =IF(C21="","",L20) -> 49154460 | F21: =IF(C21="","",F20*(1+$F$9)) -> 3043420.2 | H21: =IF(C21="","",F21/12) -> 253618.35 | J21: =IF(C21="","",ABS(D21-F21)) -> 46111040 | L21: =IF(C21="","",J21*(1+$F$11)) -> 50722144 | R21: 11 | S21: =S20*(1+10%) -> 259.37425 | T21: =FV((1+$F$10)^(1/12)-1,12,-S21,-T20,1) -> 39922.964 | V21: =C21="" -> FALSE
B22: =IF(C22="","",B21+1) -> 6 | C22: =IF(OR(C21=$F$7,C21=""),"",C21+1) -> 66 | D22: =IF(C22="","",L21) -> 50722144 | F22: =IF(C22="","",F21*(1+$F$9)) -> 3256459.6 | H22: =IF(C22="","",F22/12) -> 271371.63 | J22: =IF(C22="","",ABS(D22-F22)) -> 47465685 | L22: =IF(C22="","",J22*(1+$F$11)) -> 52212253 | R22: 12 | S22: =S21*(1+10%) -> 285.31167 | T22: =FV((1+$F$10)^(1/12)-1,12,-S22,-T21,1) -> 48356.15 | V22: =C22="" -> FALSE
B23: =IF(C23="","",B22+1) -> 7 | C23: =IF(OR(C22=$F$7,C22=""),"",C22+1) -> 67 | D23: =IF(C23="","",L22) -> 52212253 | F23: =IF(C23="","",F22*(1+$F$9)) -> 3484411.8 | H23: =IF(C23="","",F23/12) -> 290367.65 | J23: =IF(C23="","",ABS(D23-F23)) -> 48727841 | L23: =IF(C23="","",J23*(1+$F$11)) -> 53600626 | R23: 13 | S23: =S22*(1+10%) -> 313.84284 | T23: =FV((1+$F$10)^(1/12)-1,12,-S23,-T22,1) -> 58165.562 | V23: =C23="" -> FALSE
B24: =IF(C24="","",B23+1) -> 8 | C24: =IF(OR(C23=$F$7,C23=""),"",C23+1) -> 68 | D24: =IF(C24="","",L23) -> 53600626 | F24: =IF(C24="","",F23*(1+$F$9)) -> 3728320.6 | H24: =IF(C24="","",F24/12) -> 310693.38 | J24: =IF(C24="","",ABS(D24-F24)) -> 49872305 | L24: =IF(C24="","",J24*(1+$F$11)) -> 54859535 | R24: 14 | S24: =S23*(1+10%) -> 345.22712 | T24: =FV((1+$F$10)^(1/12)-1,12,-S24,-T23,1) -> 69552.771 | V24: =C24="" -> FALSE
B25: =IF(C25="","",B24+1) -> 9 | C25: =IF(OR(C24=$F$7,C24=""),"",C24+1) -> 69 | D25: =IF(C25="","",L24) -> 54859535 | F25: =IF(C25="","",F24*(1+$F$9)) -> 3989303 | H25: =IF(C25="","",F25/12) -> 332441.92 | J25: =IF(C25="","",ABS(D25-F25)) -> 50870232 | L25: =IF(C25="","",J25*(1+$F$11)) -> 55957256 | R25: 15 | S25: =S24*(1+10%) -> 379.74983 | T25: =FV((1+$F$10)^(1/12)-1,12,-S25,-T24,1) -> 82747.179 | V25: =C25="" -> FALSE
B26: =IF(C26="","",B25+1) -> 10 | C26: =IF(OR(C25=$F$7,C25=""),"",C25+1) -> 70 | D26: =IF(C26="","",L25) -> 55957256 | F26: =IF(C26="","",F25*(1+$F$9)) -> 4268554.2 | H26: =IF(C26="","",F26/12) -> 355712.85 | J26: =IF(C26="","",ABS(D26-F26)) -> 51688701 | L26: =IF(C26="","",J26*(1+$F$11)) -> 56857572 | R26: 16 | S26: =S25*(1+10%) -> 417.72482 | T26: =FV((1+$F$10)^(1/12)-1,12,-S26,-T25,1) -> 98009.723 | V26: =C26="" -> FALSE
B27: =IF(C27="","",B26+1) -> 11 | C27: =IF(OR(C26=$F$7,C26=""),"",C26+1) -> 71 | D27: =IF(C27="","",L26) -> 56857572 | F27: =IF(C27="","",F26*(1+$F$9)) -> 4567353 | H27: =IF(C27="","",F27/12) -> 380612.75 | J27: =IF(C27="","",ABS(D27-F27)) -> 52290219 | L27: =IF(C27="","",J27*(1+$F$11)) -> 57519240 | R27: 17 | S27: =S26*(1+10%) -> 459.4973 | T27: =FV((1+$F$10)^(1/12)-1,12,-S27,-T26,1) -> 115637.06 | V27: =C27="" -> FALSE
B28: =IF(C28="","",B27+1) -> 12 | C28: =IF(OR(C27=$F$7,C27=""),"",C27+1) -> 72 | D28: =IF(C28="","",L27) -> 57519240 | F28: =IF(C28="","",F27*(1+$F$9)) -> 4887067.7 | H28: =IF(C28="","",F28/12) -> 407255.64 | J28: =IF(C28="","",ABS(D28-F28)) -> 52632173 | L28: =IF(C28="","",J28*(1+$F$11)) -> 57895390 | R28: 18 | S28: =S27*(1+10%) -> 505.44703 | T28: =FV((1+$F$10)^(1/12)-1,12,-S28,-T27,1) -> 135966.3 | V28: =C28="" -> FALSE
B29: =IF(C29="","",B28+1) -> 13 | C29: =IF(OR(C28=$F$7,C28=""),"",C28+1) -> 73 | D29: =IF(C29="","",L28) -> 57895390 | F29: =IF(C29="","",F28*(1+$F$9)) -> 5229162.5 | H29: =IF(C29="","",F29/12) -> 435763.54 | J29: =IF(C29="","",ABS(D29-F29)) -> 52666228 | L29: =IF(C29="","",J29*(1+$F$11)) -> 57932850 | R29: 19 | S29: =S28*(1+10%) -> 555.99173 | T29: =FV((1+$F$10)^(1/12)-1,12,-S29,-T28,1) -> 159380.32 | V29: =C29="" -> FALSE
... B60: =IF(C60="","",B59+1) | C60: =IF(OR(C59=$F$7,C59=""),"",C59+1) | D60: =IF(C60="","",L59) | F60: =IF(C60="","",F59*(1+$F$9)) | H60: =IF(C60="","",F60/12) | J60: =IF(C60="","",ABS(D60-F60)) | L60: =IF(C60="","",J60*(1+$F$11)) | R60: 50 | S60: =S59*(1+10%) -> 10671.896 | T60: =FV((1+$F$10)^(1/12)-1,12,-S60,-T59,1) -> 10954379 | V60: =C60="" -> TRUE
B61: =IF(C61="","",B60+1) | C61: =IF(OR(C60=$F$7,C60=""),"",C60+1) | D61: =IF(C61="","",L60) | F61: =IF(C61="","",F60*(1+$F$9)) | H61: =IF(C61="","",F61/12) | J61: =IF(C61="","",ABS(D61-F61)) | L61: =IF(C61="","",J61*(1+$F$11)) | V61: =C61="" -> TRUE
B62: =IF(C62="","",B61+1) | C62: =IF(OR(C61=$F$7,C61=""),"",C61+1) | D62: =IF(C62="","",L61) | F62: =IF(C62="","",F61*(1+$F$9)) | H62: =IF(C62="","",F62/12) | J62: =IF(C62="","",ABS(D62-F62)) | L62: =IF(C62="","",J62*(1+$F$11)) | V62: =C62="" -> TRUE
B63: =IF(C63="","",B62+1) | C63: =IF(OR(C62=$F$7,C62=""),"",C62+1) | D63: =IF(C63="","",L62) | F63: =IF(C63="","",F62*(1+$F$9)) | H63: =IF(C63="","",F63/12) | J63: =IF(C63="","",ABS(D63-F63)) | L63: =IF(C63="","",J63*(1+$F$11)) | V63: =C63="" -> TRUE
B64: =IF(C64="","",B63+1) | C64: =IF(OR(C63=$F$7,C63=""),"",C63+1) | D64: =IF(C64="","",L63) | F64: =IF(C64="","",F63*(1+$F$9)) | H64: =IF(C64="","",F64/12) | J64: =IF(C64="","",ABS(D64-F64)) | L64: =IF(C64="","",J64*(1+$F$11)) | V64: =C64="" -> TRUE
B65: =IF(C65="","",B64+1) | C65: =IF(OR(C64=$F$7,C64=""),"",C64+1) | D65: =IF(C65="","",L64) | F65: =IF(C65="","",F64*(1+$F$9)) | H65: =IF(C65="","",F65/12) | J65: =IF(C65="","",ABS(D65-F65)) | L65: =IF(C65="","",J65*(1+$F$11)) | V65: =C65="" -> TRUE
B66: =IF(C66="","",B65+1) | C66: =IF(OR(C65=$F$7,C65=""),"",C65+1) | D66: =IF(C66="","",L65) | F66: =IF(C66="","",F65*(1+$F$9)) | H66: =IF(C66="","",F66/12) | J66: =IF(C66="","",ABS(D66-F66)) | L66: =IF(C66="","",J66*(1+$F$11)) | V66: =C66="" -> TRUE
B67: =IF(C67="","",B66+1) | C67: =IF(OR(C66=$F$7,C66=""),"",C66+1) | D67: =IF(C67="","",L66) | F67: =IF(C67="","",F66*(1+$F$9)) | H67: =IF(C67="","",F67/12) | J67: =IF(C67="","",D67-F67) | L67: =IF(C67="","",J67*(1+$F$11)) | V67: =C67="" -> TRUE

Sheet 8
A2: BACK | B2: WEALTH & LOAN TENURE
B4: Wealth creation through increase in HOME LOAN tenure
B6: =UPPER("Original home loan details") -> ORIGINAL HOME LOAN DETAILS | J6: ="After "&G10&" Months (Or "&QUOTIENT(G10,12)&" Y) "&IF(MOD(G10,12)=0,"",MOD(G10,12)&" M)") -> After 240 Months (Or 20 Y)
B7: Outstanding principal as of now | G7: 6000000 | J7: If home loan tenure was not increased
B8: Current rate of interest on home loan | G8: 0.09 | J8: and no SIP investment was made
B9: Current loan EMI (A) | G9: 58000 | J9: Total outgo from now onwards | N9: =(G10)*G9 -> 13920000
B10: Balance loan tenure as of now (no. of months) | G10: 240 | J10: Outstanding principal amount | N10: 0
B11: Balance loan tenure in years and months | G11: =QUOTIENT(G10,12)&" Y "&IF(MOD(G10,12)=0,"",MOD(G10,12)&" M") -> 20 Y | J11: Wealth created | N11: 0
B13: =UPPER("Revised home loan details") -> REVISED HOME LOAN DETAILS | J13: ="After "&G10&" Months (Or "&QUOTIENT(G10,12)&" Y) "&IF(MOD(G10,12)=0,"",MOD(G10,12)&" M)") -> After 240 Months (Or 20 Y)
B14: Revised home loan tenure (no. of years) | G14: 30 | J14: If home loan tenure was increased
B15: Rate of interest after balance transfer | G15: 0.09 | J15: ="and SIP investment was made for "&G10&" months" -> and SIP investment was made for 240 months
B16: Revised loan EMI (B) | G16: =PMT((1+G15/12)^(1)-1,G14*12,-G7,,0) -> 48277.357 | J16: Total outgo from now onwards | N16: =(G10)*(G16+G19) -> 13920000
J17: Outstanding principal amount (a) | N17: =VLOOKUP(G10,$B$27:$L$386,8,0) -> 3811096.3
B18: =UPPER("SIP details") -> SIP DETAILS | J18: Wealth created through SIP (b) | N18: =VLOOKUP(G10,$B$27:$L$386,10,0) -> 8943444.7
B19: Saving in EMI or SIP investment amount (A-B) | G19: =G9-G16 -> 9722.643 | J19: Net wealth created (b-a) | N19: =N18-N17 -> 5132348.4
B20: Expected return from SIP investment | G20: 0.12 | J20: Loan can be foreclosed on or after | N20: =QUOTIENT(O21,12)&" Y "&IF(MOD(O21,12)=0,"",MOD(O21,12)&" M") -> 15 Y 2 M
O21: =INDEX($B$27:$B$386,MATCH("YES",$M$27:$M$386,0)) -> 182
B22: Prepared for: | D22: =" "&UPPER('Main Menu'!C29) -> CLIENT NAME | I22: Prepared by: | K22: =" "&UPPER('Main Menu'!L29) -> PARTNER NAME
N23: ="Dated: "& TEXT(TODAY(),"DD-MMM-YYYY") -> Dated: 28-Aug-2025
B24: Revised loan repayment schedule along with wealth creation through SIP:
B25: MONTHS | C25: EMI AMOUNT | E25: INTEREST PAID | G25: PRINCIPAL PAID | I25: O/S PRINCIPAL | K25: WEALTH CREATED | M25: FORECLOSE POSSIBLE?
B26: 0 | I26: =G7 -> 6000000
A27: ORANGE | B27: =IF(B26="","",IF(B26+1>$G$14*12,"",B26+1)) -> 1 | C27: =IF(B27="","",$G$16) -> 48277.357 | E27: =IF(B27="","",I26*$G$15/12) -> 45000 | G27: =IF(B27="","",$G$16-E27) -> 3277.357 | I27: =IF(B27="","",I26-G27) -> 5996722.6 | K27: =IF(B27="","",FV((1+$G$20)^(1/12)-1,1,-$G$19,-K26,1)) -> 9814.8991 | M27: =IF(B27="","",IF(K27>=I27,"YES","NO")) -> NO
A28: WHITE | B28: =IF(B27="","",IF(B27+1>$G$14*12,"",B27+1)) -> 2 | C28: =IF(B28="","",$G$16) -> 48277.357 | E28: =IF(B28="","",I27*$G$15/12) -> 44975.42 | G28: =IF(B28="","",$G$16-E28) -> 3301.9372 | I28: =IF(B28="","",I27-G28) -> 5993420.7 | K28: =IF(B28="","",FV((1+$G$20)^(1/12)-1,1,-$G$19,-K27,1)) -> 19722.93 | M28: =IF(B28="","",IF(K28>=I28,"YES","NO")) -> NO
A29: ORANGE | B29: =IF(B28="","",IF(B28+1>$G$14*12,"",B28+1)) -> 3 | C29: =IF(B29="","",$G$16) -> 48277.357 | E29: =IF(B29="","",I28*$G$15/12) -> 44950.655 | G29: =IF(B29="","",$G$16-E29) -> 3326.7017 | I29: =IF(B29="","",I28-G29) -> 5990094 | K29: =IF(B29="","",FV((1+$G$20)^(1/12)-1,1,-$G$19,-K28,1)) -> 29724.976 | M29: =IF(B29="","",IF(K29>=I29,"YES","NO")) -> NO
A30: WHITE | B30: =IF(B29="","",IF(B29+1>$G$14*12,"",B29+1)) -> 4 | C30: =IF(B30="","",$G$16) -> 48277.357 | E30: =IF(B30="","",I29*$G$15/12) -> 44925.705 | G30: =IF(B30="","",$G$16-E30) -> 3351.652 | I30: =IF(B30="","",I29-G30) -> 5986742.4 | K30: =IF(B30="","",FV((1+$G$20)^(1/12)-1,1,-$G$19,-K29,1)) -> 39821.929 | M30: =IF(B30="","",IF(K30>=I30,"YES","NO")) -> NO
A31: ORANGE | B31: =IF(B30="","",IF(B30+1>$G$14*12,"",B30+1)) -> 5 | C31: =IF(B31="","",$G$16) -> 48277.357 | E31: =IF(B31="","",I30*$G$15/12) -> 44900.568 | G31: =IF(B31="","",$G$16-E31) -> 3376.7894 | I31: =IF(B31="","",I30-G31) -> 5983365.6 | K31: =IF(B31="","",FV((1+$G$20)^(1/12)-1,1,-$G$19,-K30,1)) -> 50014.69 | M31: =IF(B31="","",IF(K31>=I31,"YES","NO")) -> NO
A32: WHITE | B32: =IF(B31="","",IF(B31+1>$G$14*12,"",B31+1)) -> 6 | C32: =IF(B32="","",$G$16) -> 48277.357 | E32: =IF(B32="","",I31*$G$15/12) -> 44875.242 | G32: =IF(B32="","",$G$16-E32) -> 3402.1153 | I32: =IF(B32="","",I31-G32) -> 5979963.4 | K32: =IF(B32="","",FV((1+$G$20)^(1/12)-1,1,-$G$19,-K31,1)) -> 60304.168 | M32: =IF(B32="","",IF(K32>=I32,"YES","NO")) -> NO
A33: ORANGE | B33: =IF(B32="","",IF(B32+1>$G$14*12,"",B32+1)) -> 7 | C33: =IF(B33="","",$G$16) -> 48277.357 | E33: =IF(B33="","",I32*$G$15/12) -> 44849.726 | G33: =IF(B33="","",$G$16-E33) -> 3427.6312 | I33: =IF(B33="","",I32-G33) -> 5976535.8 | K33: =IF(B33="","",FV((1+$G$20)^(1/12)-1,1,-$G$19,-K32,1)) -> 70691.281 | M33: =IF(B33="","",IF(K33>=I33,"YES","NO")) -> NO
A34: WHITE | B34: =IF(B33="","",IF(B33+1>$G$14*12,"",B33+1)) -> 8 | C34: =IF(B34="","",$G$16) -> 48277.357 | E34: =IF(B34="","",I33*$G$15/12) -> 44824.019 | G34: =IF(B34="","",$G$16-E34) -> 3453.3384 | I34: =IF(B34="","",I33-G34) -> 5973082.5 | K34: =IF(B34="","",FV((1+$G$20)^(1/12)-1,1,-$G$19,-K33,1)) -> 81176.955 | M34: =IF(B34="","",IF(K34>=I34,"YES","NO")) -> NO
A35: ORANGE | B35: =IF(B34="","",IF(B34+1>$G$14*12,"",B34+1)) -> 9 | C35: =IF(B35="","",$G$16) -> 48277.357 | E35: =IF(B35="","",I34*$G$15/12) -> 44798.119 | G35: =IF(B35="","",$G$16-E35) -> 3479.2384 | I35: =IF(B35="","",I34-G35) -> 5969603.2 | K35: =IF(B35="","",FV((1+$G$20)^(1/12)-1,1,-$G$19,-K34,1)) -> 91762.126 | M35: =IF(B35="","",IF(K35>=I35,"YES","NO")) -> NO
A36: WHITE | B36: =IF(B35="","",IF(B35+1>$G$14*12,"",B35+1)) -> 10 | C36: =IF(B36="","",$G$16) -> 48277.357 | E36: =IF(B36="","",I35*$G$15/12) -> 44772.024 | G36: =IF(B36="","",$G$16-E36) -> 3505.3327 | I36: =IF(B36="","",I35-G36) -> 5966097.9 | K36: =IF(B36="","",FV((1+$G$20)^(1/12)-1,1,-$G$19,-K35,1)) -> 102447.74 | M36: =IF(B36="","",IF(K36>=I36,"YES","NO")) -> NO
A37: ORANGE | B37: =IF(B36="","",IF(B36+1>$G$14*12,"",B36+1)) -> 11 | C37: =IF(B37="","",$G$16) -> 48277.357 | E37: =IF(B37="","",I36*$G$15/12) -> 44745.734 | G37: =IF(B37="","",$G$16-E37) -> 3531.6227 | I37: =IF(B37="","",I36-G37) -> 5962566.3 | K37: =IF(B37="","",FV((1+$G$20)^(1/12)-1,1,-$G$19,-K36,1)) -> 113234.74 | M37: =IF(B37="","",IF(K37>=I37,"YES","NO")) -> NO
A38: WHITE | B38: =IF(B37="","",IF(B37+1>$G$14*12,"",B37+1)) -> 12 | C38: =IF(B38="","",$G$16) -> 48277.357 | E38: =IF(B38="","",I37*$G$15/12) -> 44719.247 | G38: =IF(B38="","",$G$16-E38) -> 3558.1099 | I38: =IF(B38="","",I37-G38) -> 5959008.2 | K38: =IF(B38="","",FV((1+$G$20)^(1/12)-1,1,-$G$19,-K37,1)) -> 124124.1 | M38: =IF(B38="","",IF(K38>=I38,"YES","NO")) -> NO
... A386: WHITE | B386: =IF(B385="","",IF(B385+1>$G$14*12,"",B385+1)) -> 360 | C386: =IF(B386="","",$G$16) -> 48277.357 | E386: =IF(B386="","",I385*$G$15/12) -> 359.38479 | G386: =IF(B386="","",$G$16-E386) -> 47917.972 | I386: =IF(B386="","",I385-G386) -> -5.444308e-07 | K386: =IF(B386="","",FV((1+$G$20)^(1/12)-1,1,-$G$19,-K385,1)) -> 29955203 | M386: =IF(B386="","",IF(K386>=I386,"YES","NO")) -> YES

Sheet 9(Old)
A2: BACK | B2: FINANCIAL ROADMAP
B5: Prepared for: | D5: =" "&UPPER('Main Menu'!C29) -> CLIENT NAME | I5: Prepared by: | J5: =" "&UPPER('Main Menu'!L29) -> PARTNER NAME
N6: ="Dated: "& TEXT(TODAY(),"DD-MMM-YYYY") -> Dated: 28-Aug-2025
B7: =UPPER("Personal details") -> PERSONAL DETAILS | G7: =UPPER("Retirement details") -> RETIREMENT DETAILS | Q7: Retirement
B8: Your age | E8: 40 | G8: Return expected upto retirement | K8: 0.12 | L8: Reqd. corpus | N8: =-PV(S8,E11-E10,S10,,1) -> 42487329 | Q8: Real rate of return | S8: =((1+K9)/(1+E16))-1 -> 0.028037383
B9: Spouse's age | E9: 35 | G9: Return expected post retirement | K9: 0.1 | L9: Reqd. SIP amount | N9: =-PMT((1+K8)^(1/12)-1,(E10-E8)*12,,N8,1) -> 46189.041 | Q9: FV of mthly expenses | S9: =FV(E16,E10-E8,,-E13,) -> 193484.22
B10: Retirement age (self) | E10: 60 | G10: =UPPER("Life insurance requirement") -> LIFE INSURANCE REQUIREMENT | Q10: FV of yearly expenses | S10: =S9*12 -> 2321810.7
B11: Life expectancy (self) | E11: 85 | G11: Expected return on claim proceeds | K11: 0.1 | L11: Reqd. life cover | N11: =-PV(S12,E12-E9,S14,,1) -> 16479514 | Q11: Insurance
B12: Life expectancy (spouse) | E12: 85 | G12: Existing financial assets | J12: 5000000 | L12: Reqd. addl. cover | N12: =N11-J12 -> 11479514 | Q12: Real rate of return | S12: =((1+K11)/(1+E16))-1 -> 0.028037383
B13: Monthly expenses* | E13: 50000 | G13: =UPPER("Health insurance details") -> HEALTH INSURANCE DETAILS | Q13: FV of mthly expenses | S13: =E13 -> 50000
B14: *Includes household + lifestyle expensesonly | G14: Recommended health cover | J14: 1000000 | L14: Current cover | N14: 500000 | Q14: FV of yearly expenses | S14: =S13*12 -> 600000
B15: Other expenses (monthly) | E15: 25000 | G15: =UPPER("Emergency fund details") -> EMERGENCY FUND DETAILS
B16: Assumed inflation | E16: 0.07 | G16: Keep aside equal amount of | J16: 6 | K16: months' of total expenses | N16: =J16*(E13+E15) -> 450000
B17: Assumed return: | D17: For short term goals (<3 Yrs) | G17: 0.08 | H17: For mid term goals (>3 Yrs and <5 Yrs) | L17: 0.1 | M17: For long term goals | O17: 0.12
B18: =UPPER("Goal name") -> GOAL NAME | F18: =UPPER("Current Cost") -> CURRENT COST | H18: =UPPER("Years") -> YEARS | I18: INFLATION | J18: FUTURE VALUE | L18: REQD. LUMPSUM | N18: REQD. SIP
B19: Trishagni's Higher Education | F19: 1000000 | H19: 4 | I19: 0.07 | J19: =FV(I19,H19,,-F19) -> 1310796 | L19: =-PV(Q19,H19,,J19,) -> 895291.31 | N19: =IFERROR(-PMT((1+Q19)^(1/12)-1,H19*12,,J19,1),0) -> 22343.851 | Q19: =IF(H19<3,$G$17, IF(H19>5,$O$17,$L$17)) -> 0.1
J20: =FV(I20,H20,,-F20) -> 0 | L20: =-PV(Q20,H20,,J20,) -> 0 | N20: =IFERROR(-PMT((1+Q20)^(1/12)-1,H20*12,,J20,1),0) -> 0 | Q20: =IF(H20<3,$G$17, IF(H20>5,$O$17,$L$17)) -> 0.08
J21: =FV(I21,H21,,-F21) -> 0 | L21: =-PV(Q21,H21,,J21,) -> 0 | N21: =IFERROR(-PMT((1+Q21)^(1/12)-1,H21*12,,J21,1),0) -> 0 | Q21: =IF(H21<3,$G$17, IF(H21>5,$O$17,$L$17)) -> 0.08
J22: =FV(I22,H22,,-F22) -> 0 | L22: =-PV(Q22,H22,,J22,) -> 0 | N22: =IFERROR(-PMT((1+Q22)^(1/12)-1,H22*12,,J22,1),0) -> 0 | Q22: =IF(H22<3,$G$17, IF(H22>5,$O$17,$L$17)) -> 0.08
J23: =FV(I23,H23,,-F23) -> 0 | L23: =-PV(Q23,H23,,J23,) -> 0 | N23: =IFERROR(-PMT((1+Q23)^(1/12)-1,H23*12,,J23,1),0) -> 0 | Q23: =IF(H23<3,$G$17, IF(H23>5,$O$17,$L$17)) -> 0.08
J24: =FV(I24,H24,,-F24) -> 0 | L24: =-PV(Q24,H24,,J24,) -> 0 | N24: =IFERROR(-PMT((1+Q24)^(1/12)-1,H24*12,,J24,1),0) -> 0 | Q24: =IF(H24<3,$G$17, IF(H24>5,$O$17,$L$17)) -> 0.08
J25: =FV(I25,H25,,-F25) -> 0 | L25: =-PV(Q25,H25,,J25,) -> 0 | N25: =IFERROR(-PMT((1+Q25)^(1/12)-1,H25*12,,J25,1),0) -> 0 | Q25: =IF(H25<3,$G$17, IF(H25>5,$O$17,$L$17)) -> 0.08
J26: =FV(I26,H26,,-F26) -> 0 | L26: =-PV(Q26,H26,,J26,) -> 0 | N26: =IFERROR(-PMT((1+Q26)^(1/12)-1,H26*12,,J26,1),0) -> 0 | Q26: =IF(H26<3,$G$17, IF(H26>5,$O$17,$L$17)) -> 0.08
J27: =FV(I27,H27,,-F27) -> 0 | L27: =-PV(Q27,H27,,J27,) -> 0 | N27: =IFERROR(-PMT((1+Q27)^(1/12)-1,H27*12,,J27,1),0) -> 0 | Q27: =IF(H27<3,$G$17, IF(H27>5,$O$17,$L$17)) -> 0.08
J28: =FV(I28,H28,,-F28) -> 0 | L28: =-PV(Q28,H28,,J28,) -> 0 | N28: =IFERROR(-PMT((1+Q28)^(1/12)-1,H28*12,,J28,1),0) -> 0 | Q28: =IF(H28<3,$G$17, IF(H28>5,$O$17,$L$17)) -> 0.08
J29: =FV(I29,H29,,-F29) -> 0 | L29: =-PV(Q29,H29,,J29,) -> 0 | N29: =IFERROR(-PMT((1+Q29)^(1/12)-1,H29*12,,J29,1),0) -> 0 | Q29: =IF(H29<3,$G$17, IF(H29>5,$O$17,$L$17)) -> 0.08
J30: =FV(I30,H30,,-F30) -> 0 | L30: =-PV(Q30,H30,,J30,) -> 0 | N30: =IFERROR(-PMT((1+Q30)^(1/12)-1,H30*12,,J30,1),0) -> 0 | Q30: =IF(H30<3,$G$17, IF(H30>5,$O$17,$L$17)) -> 0.08

Sheet 9
A2: BACK | B2: Quick Financial Plan
B5: MANDATORY INPUTS
B6: Your name | D6: ='Main Menu'!C29 -> Client Name | G6: Age | H6: 40 | I6: Spouse's name | K6: Purvi Shah | N6: Spouse's Age | P6: 35
B7: First child's name | D7: Sahil | G7: Age | H7: 7 | I7: 2nd child's name | K7: Sneha | N7: 2nd Child's Age | P7: 5
B8: 3rd child's name | G8: Age | I8: Expenses* | K8: 35000 | N8: * Household & Lifestyle
B9: ="Basic Financial Plan for " & D6 & " & Family" -> Basic Financial Plan for Client Name & Family
T14: Life cover calculation
J15: Prepared by: | L15: ='Main Menu'!L29 -> Partner Name | T15: Inflation | U15: =K42 -> 0.07
J16: Dated: | L16: =TODAY() -> 45897 | T16: Return on claim proceeds | W16: =Q41 -> 0.1
T17: Life expectancy | V17: =E42 -> 85
T18: Real rate of return | V18: =((1+W16)/(1+U15))-1 -> 0.028037383
B19: CONTINGENCY PLAN | T19: Reqd. Insurance Cover | W19: =-PV(V18,V17-P6,K8*12,,1) -> 11535660
B20: It is strongly recommended that you to keep sufficient amount (generally equivalent to 3 to 6 months' of all your regular expenses) in investment instruments where your money remains safe and liquid (i.e. any time you can withdraw).
B23: HEALTH INSURANCE
B24: Safeguard your financial assets and future goals, against any medical emergency by taking adequate amount of health cover.
B25: Required Health Cover | E25: 1000000 | G25: Existing Health Cover | J25: 0 | L25: Reqd. Addl. Health Cover | O25: =E25-J25 -> 1000000
B27: LIFE INSURANCE (Inflation, spouse's life expectancy and return on claim proceeds are assumed as per data given for retirement goal)
B28: To be able to continue with current lifestyle & household expenses till life expectancy, your spouse will need the following amt of life cover:
B29: Required Life Cover | E29: =W19 -> 11535660 | G29: Existing life cover | J29: 0 | L29: Reqd. Addl. Life Cover | O29: =E29-J29 -> 11535660
B31: INVESTMENT SUMMARY | E31: Total SIP investment amount needs to start with now: | L31: =SUM(H33:I37,P33:Q37) -> 129582.02
B32: FINANCIAL GOAL | F32: FUTURE VALUE | H32: REQD. SIP INV. | J32: FINANCIAL GOAL | N32: FUTURE VALUE | P32: REQD. SIP INV.
B33: Your own retirement goal | F33: =O57 -> 46076364 | H33: =O61 -> 50090.771 | J33: =K7&"'s Post-Graduation Expenses" -> Sneha's Post-Graduation Expenses | N33: =SUMIFS(L132:L147,W132:W147,"Post Graduation") -> 3700018.1 | P33: =SUMIFS(P132:P147,W132:W147,"Post Graduation") -> 5985.0768
B34: =D7&"'s Upto Graduation Expenses" -> Sahil's Upto Graduation Expenses | F34: =SUMIFS(L103:L118,W103:W118,"Upto Graduation") -> 3701327.4 | H34: =SUMIFS(P103:P118,W103:W118,"Upto Graduation") -> 16655.174 | J34: =K7&"'s Marriage Expenses" -> Sneha's Marriage Expenses | N34: =SUMIFS(L132:L147,W132:W147,"Marriage") -> 7550750.6 | P34: =SUMIFS(P132:P147,W132:W147,"Marriage") -> 7308.1005
B35: =D7&"'s Post-Graduation Expenses" -> Sahil's Post-Graduation Expenses | F35: =SUMIFS(L103:L118,W103:W118,"Post Graduation") -> 3172169.1 | H35: =SUMIFS(P103:P118,W103:W118,"Post Graduation") -> 6728.4259 | J35: =D8&"'s Upto Graduation Expenses" -> 's Upto Graduation Expenses | N35: =SUMIFS(L161:L176,W161:W176,"Upto Graduation") -> 6343424.6 | P35: =SUMIFS(P161:P176,W161:W176,"Upto Graduation") -> 10181.671
B36: =D7&"'s Marriage Expenses" -> Sahil's Marriage Expenses | F36: =SUMIFS(L103:L118,W103:W118,"Marriage") -> 6473551.6 | H36: =SUMIFS(P103:P118,W103:W118,"Marriage") -> 8068.8445 | J36: =D8&"'s Post-Graduation Expenses" -> 's Post-Graduation Expenses | N36: =SUMIFS(L161:L176,W161:W176,"Post Graduation") -> 5436540.4 | P36: =SUMIFS(P161:P176,W161:W176,"Post Graduation") -> 4647.2762
B37: =K7&"'s Upto Graduation Expenses" -> Sneha's Upto Graduation Expenses | F37: =SUMIFS(L132:L147,W132:W147,"Upto Graduation") -> 4317228.2 | H37: =SUMIFS(P132:P147,W132:W147,"Upto Graduation") -> 14081.138 | J37: =D8&"'s Marriage Expenses" -> 's Marriage Expenses | N37: =SUMIFS(L161:L176,W161:W176,"Marriage") -> 11094530 | P37: =SUMIFS(P161:P176,W161:W176,"Marriage") -> 5835.5474
B38: RETIREMENT GOAL - DATA INPUT & ASSUMPTIONS
B40: Current Age | E40: 40 | F40: Current Household+Lifestyle Expenses | K40: =K8 -> 35000 | M40: Expected Return Pre-Retirement | Q40: 0.12
B41: Retirement Age | E41: 60 | F41: Likely tax slab post retirement | K41: 0.312 | M41: Expected Return Post-Retirement | Q41: 0.1
B42: Life Expectancy | E42: 85 | F42: Assumed Inflation Rate Per Annum | K42: 0.07
J44: RETIREMENT GOAL - OUTPUT / ACTIONABLES
J45: No. of years left for retirement | O45: =E41-E40 -> 20
J46: No. of years after retirement | O46: =E42-E41 -> 25
J47: 1st month's expense post retirement | O47: =FV(K42,O45,,-K40*12)/12 -> 135438.96
J48: 1st year's expense post retirement | O48: =FV(K42,O45,,-K40*12) -> 1625267.5
J49: 1st year's expense post retirement | O49: =O48/(1-K41) -> 2362307.4
J50: (Pre-tax value)
J52: =UPPER("Retirement corpus required") -> RETIREMENT CORPUS REQUIRED | O52: =-PV(V52,O46,O49,,1) -> 43228387 | T52: Real rate of return | V52: =((1+Q41)/(1+K42))-1 -> 0.028037383
T53: YEAR | U53: SIP | V53: YEAR END VALUE
J54: =UPPER("Fund you must set aside at retirement age to get your capital back") -> FUND YOU MUST SET ASIDE AT RETIREMENT AGE TO GET YOUR CAPITAL BACK | O54: =-PV(Q40,O46-1,,O52) -> 2847977 | T54: 1 | U54: 100 | V54: =FV((1+$Q$40)^(1/12)-1,12,-U54,,1) -> 1276.6498
T55: 2 | U55: =U54*(1+10%) -> 110 | V55: =FV((1+$Q$40)^(1/12)-1,12,-U55,-V54,1) -> 2834.1625
T56: 3 | U56: =U55*(1+10%) -> 121 | V56: =FV((1+$Q$40)^(1/12)-1,12,-U56,-V55,1) -> 4719.0083
J57: =UPPER("Total retirement corpus required") -> TOTAL RETIREMENT CORPUS REQUIRED | O57: =O52+O54 -> 46076364 | T57: 4 | U57: =U56*(1+10%) -> 133.1 | V57: =FV((1+$Q$40)^(1/12)-1,12,-U57,-V56,1) -> 6984.5102
T58: 5 | U58: =U57*(1+10%) -> 146.41 | V58: =FV((1+$Q$40)^(1/12)-1,12,-U58,-V57,1) -> 9691.7943
J59: =UPPER("Lump sum investment required") -> LUMP SUM INVESTMENT REQUIRED | O59: =-PV(Q40,O45,,O57) -> 4776587.6 | T59: 6 | U59: =U58*(1+10%) -> 161.051 | V59: =FV((1+$Q$40)^(1/12)-1,12,-U59,-V58,1) -> 12910.867
T60: 7 | U60: =U59*(1+10%) -> 177.1561 | V60: =FV((1+$Q$40)^(1/12)-1,12,-U60,-V59,1) -> 16721.834
J61: =UPPER("Fixed SIP required") -> FIXED SIP REQUIRED | O61: =-PMT((1+Q40)^(1/12)-1,O45*12,,O57,1) -> 50090.771 | T61: 8 | U61: =U60*(1+10%) -> 194.87171 | V61: =FV((1+$Q$40)^(1/12)-1,12,-U61,-V60,1) -> 21216.283
T62: 9 | U62: =U61*(1+10%) -> 214.35888 | V62: =FV((1+$Q$40)^(1/12)-1,12,-U62,-V61,1) -> 26498.849
J63: =UPPER("Top-up (annualy 10%) SIP required") -> TOP-UP (ANNUALY 10%) SIP REQUIRED | O63: =(100/VLOOKUP(O45,T54:V103,3,0))*O57 -> 24730.511 | T63: 10 | U63: =U62*(1+10%) -> 235.79477 | V63: =FV((1+$Q$40)^(1/12)-1,12,-U63,-V62,1) -> 32688.985
T64: 11 | U64: =U63*(1+10%) -> 259.37425 | V64: =FV((1+$Q$40)^(1/12)-1,12,-U64,-V63,1) -> 39922.964
T65: 12 | U65: =U64*(1+10%) -> 285.31167 | V65: =FV((1+$Q$40)^(1/12)-1,12,-U65,-V64,1) -> 48356.15
T66: 13 | U66: =U65*(1+10%) -> 313.84284 | V66: =FV((1+$Q$40)^(1/12)-1,12,-U66,-V65,1) -> 58165.562
B67: Age | C67: Opening Balance | F67: Pre-Tax Withdrawal | I67: Post-Tax Withdrawal | L67: Year End Balance | O67: Capital Protection Amt | T67: 14 | U67: =U66*(1+10%) -> 345.22712 | V67: =FV((1+$Q$40)^(1/12)-1,12,-U67,-V66,1) -> 69552.771
B68: =E41+1 -> 61 | C68: =O52 -> 43228387 | F68: =O49 -> 2362307.4 | I68: =O48 -> 1625267.5 | L68: =ABS((C68-F68)*(1+$Q$41)) -> 44952687 | O68: =O54 -> 2847977 | T68: 15 | U68: =U67*(1+10%) -> 379.74983 | V68: =FV((1+$Q$40)^(1/12)-1,12,-U68,-V67,1) -> 82747.179
B69: =IF(B68="","",IF(B68+1>$E$42,"",B68+1)) -> 62 | C69: =L68 -> 44952687 | F69: =F68*(1+$K$42) -> 2527668.9 | I69: =I68*(1+$K$42) -> 1739036.2 | L69: =ABS((C69-F69)*(1+$Q$41)) -> 46667520 | O69: =O68*(1+$Q$40) -> 3189734.3 | S69: Blue | T69: 16 | U69: =U68*(1+10%) -> 417.72482 | V69: =FV((1+$Q$40)^(1/12)-1,12,-U69,-V68,1) -> 98009.723
B70: =IF(B69="","",IF(B69+1>$E$42,"",B69+1)) -> 63 | C70: =L69 -> 46667520 | F70: =F69*(1+$K$42) -> 2704605.7 | I70: =I69*(1+$K$42) -> 1860768.7 | L70: =ABS((C70-F70)*(1+$Q$41)) -> 48359206 | O70: =O69*(1+$Q$40) -> 3572502.4 | T70: 17 | U70: =U69*(1+10%) -> 459.4973 | V70: =FV((1+$Q$40)^(1/12)-1,12,-U70,-V69,1) -> 115637.06
B71: =IF(B70="","",IF(B70+1>$E$42,"",B70+1)) -> 64 | C71: =L70 -> 48359206 | F71: =F70*(1+$K$42) -> 2893928.1 | I71: =I70*(1+$K$42) -> 1991022.5 | L71: =ABS((C71-F71)*(1+$Q$41)) -> 50011806 | O71: =O70*(1+$Q$40) -> 4001202.7 | S71: Blue | T71: 18 | U71: =U70*(1+10%) -> 505.44703 | V71: =FV((1+$Q$40)^(1/12)-1,12,-U71,-V70,1) -> 135966.3
B72: =IF(B71="","",IF(B71+1>$E$42,"",B71+1)) -> 65 | C72: =L71 -> 50011806 | F72: =F71*(1+$K$42) -> 3096503.1 | I72: =I71*(1+$K$42) -> 2130394.1 | L72: =ABS((C72-F72)*(1+$Q$41)) -> 51606833 | O72: =O71*(1+$Q$40) -> 4481347 | T72: 19 | U72: =U71*(1+10%) -> 555.99173 | V72: =FV((1+$Q$40)^(1/12)-1,12,-U72,-V71,1) -> 159380.32
B73: =IF(B72="","",IF(B72+1>$E$42,"",B72+1)) -> 66 | C73: =L72 -> 51606833 | F73: =F72*(1+$K$42) -> 3313258.3 | I73: =I72*(1+$K$42) -> 2279521.7 | L73: =ABS((C73-F73)*(1+$Q$41)) -> 53122932 | O73: =O72*(1+$Q$40) -> 5019108.7 | S73: Blue | T73: 20 | U73: =U72*(1+10%) -> 611.5909 | V73: =FV((1+$Q$40)^(1/12)-1,12,-U73,-V72,1) -> 186313.83
B74: =IF(B73="","",IF(B73+1>$E$42,"",B73+1)) -> 67 | C74: =L73 -> 53122932 | F74: =F73*(1+$K$42) -> 3545186.4 | I74: =I73*(1+$K$42) -> 2439088.2 | L74: =ABS((C74-F74)*(1+$Q$41)) -> 54535520 | O74: =O73*(1+$Q$40) -> 5621401.7 | T74: 21 | U74: =U73*(1+10%) -> 672.74999 | V74: =FV((1+$Q$40)^(1/12)-1,12,-U74,-V73,1) -> 217260.15
B75: =IF(B74="","",IF(B74+1>$E$42,"",B74+1)) -> 68 | C75: =L74 -> 54535520 | F75: =F74*(1+$K$42) -> 3793349.4 | I75: =I74*(1+$K$42) -> 2609824.4 | L75: =ABS((C75-F75)*(1+$Q$41)) -> 55816388 | O75: =O74*(1+$Q$40) -> 6295969.9 | S75: Blue | T75: 22 | U75: =U74*(1+10%) -> 740.02499 | V75: =FV((1+$Q$40)^(1/12)-1,12,-U75,-V74,1) -> 252778.9
B76: =IF(B75="","",IF(B75+1>$E$42,"",B75+1)) -> 69 | C76: =L75 -> 55816388 | F76: =F75*(1+$K$42) -> 4058883.9 | I76: =I75*(1+$K$42) -> 2792512.1 | L76: =ABS((C76-F76)*(1+$Q$41)) -> 56933254 | O76: =O75*(1+$Q$40) -> 7051486.3 | T76: 23 | U76: =U75*(1+10%) -> 814.02749 | V76: =FV((1+$Q$40)^(1/12)-1,12,-U76,-V75,1) -> 293504.65
B77: =IF(B76="","",IF(B76+1>$E$42,"",B76+1)) -> 70 | C77: =L76 -> 56933254 | F77: =F76*(1+$K$42) -> 4343005.8 | I77: =I76*(1+$K$42) -> 2987988 | L77: =ABS((C77-F77)*(1+$Q$41)) -> 57849273 | O77: =O76*(1+$Q$40) -> 7897664.6 | S77: Blue | T77: 24 | U77: =U76*(1+10%) -> 895.43024 | V77: =FV((1+$Q$40)^(1/12)-1,12,-U77,-V76,1) -> 340156.71
B78: =IF(B77="","",IF(B77+1>$E$42,"",B77+1)) -> 71 | C78: =L77 -> 57849273 | F78: =F77*(1+$K$42) -> 4647016.2 | I78: =I77*(1+$K$42) -> 3197147.1 | L78: =ABS((C78-F78)*(1+$Q$41)) -> 58522483 | O78: =O77*(1+$Q$40) -> 8845384.4 | T78: 25 | U78: =U77*(1+10%) -> 984.97327 | V78: =FV((1+$Q$40)^(1/12)-1,12,-U78,-V77,1) -> 393550.18
B79: =IF(B78="","",IF(B78+1>$E$42,"",B78+1)) -> 72 | C79: =L78 -> 58522483 | F79: =F78*(1+$K$42) -> 4972307.3 | I79: =I78*(1+$K$42) -> 3420947.4 | L79: =ABS((C79-F79)*(1+$Q$41)) -> 58905193 | O79: =O78*(1+$Q$40) -> 9906830.5 | S79: Blue | T79: 26 | U79: =U78*(1+10%) -> 1083.4706 | V79: =FV((1+$Q$40)^(1/12)-1,12,-U79,-V78,1) -> 454608.33
B80: =IF(B79="","",IF(B79+1>$E$42,"",B79+1)) -> 73 | C80: =L79 -> 58905193 | F80: =F79*(1+$K$42) -> 5320368.8 | I80: =I79*(1+$K$42) -> 3660413.7 | L80: =ABS((C80-F80)*(1+$Q$41)) -> 58943307 | O80: =O79*(1+$Q$40) -> 11095650 | T80: 27 | U80: =U79*(1+10%) -> 1191.8177 | V80: =FV((1+$Q$40)^(1/12)-1,12,-U80,-V79,1) -> 524376.66
B81: =IF(B80="","",IF(B80+1>$E$42,"",B80+1)) -> 74 | C81: =L80 -> 58943307 | F81: =F80*(1+$K$42) -> 5692794.6 | I81: =I80*(1+$K$42) -> 3916642.7 | L81: =ABS((C81-F81)*(1+$Q$41)) -> 58575564 | O81: =O80*(1+$Q$40) -> 12427128 | S81: Blue | T81: 28 | U81: =U80*(1+10%) -> 1310.9994 | V81: =FV((1+$Q$40)^(1/12)-1,12,-U81,-V80,1) -> 604038.73
B82: =IF(B81="","",IF(B81+1>$E$42,"",B81+1)) -> 75 | C82: =L81 -> 58575564 | F82: =F81*(1+$K$42) -> 6091290.2 | I82: =I81*(1+$K$42) -> 4190807.7 | L82: =ABS((C82-F82)*(1+$Q$41)) -> 57732701 | O82: =O81*(1+$Q$40) -> 13918384 | T82: 29 | U82: =U81*(1+10%) -> 1442.0994 | V82: =FV((1+$Q$40)^(1/12)-1,12,-U82,-V81,1) -> 694933.94
B83: =IF(B82="","",IF(B82+1>$E$42,"",B82+1)) -> 76 | C83: =L82 -> 57732701 | F83: =F82*(1+$K$42) -> 6517680.6 | I83: =I82*(1+$K$42) -> 4484164.2 | L83: =ABS((C83-F83)*(1+$Q$41)) -> 56336522 | O83: =O82*(1+$Q$40) -> 15588590 | S83: Blue | T83: 30 | U83: =U82*(1+10%) -> 1586.3093 | V83: =FV((1+$Q$40)^(1/12)-1,12,-U83,-V82,1) -> 798577.63
B84: =IF(B83="","",IF(B83+1>$E$42,"",B83+1)) -> 77 | C84: =L83 -> 56336522 | F84: =F83*(1+$K$42) -> 6973918.2 | I84: =I83*(1+$K$42) -> 4798055.7 | L84: =ABS((C84-F84)*(1+$Q$41)) -> 54298864 | O84: =O83*(1+$Q$40) -> 17459220 | T84: 31 | U84: =U83*(1+10%) -> 1744.9402 | V84: =FV((1+$Q$40)^(1/12)-1,12,-U84,-V83,1) -> 916683.72
B85: =IF(B84="","",IF(B84+1>$E$42,"",B84+1)) -> 78 | C85: =L84 -> 54298864 | F85: =F84*(1+$K$42) -> 7462092.5 | I85: =I84*(1+$K$42) -> 5133919.6 | L85: =ABS((C85-F85)*(1+$Q$41)) -> 51520449 | O85: =O84*(1+$Q$40) -> 19554327 | S85: Blue | T85: 32 | U85: =U84*(1+10%) -> 1919.4342 | V85: =FV((1+$Q$40)^(1/12)-1,12,-U85,-V84,1) -> 1051190.2
B86: =IF(B85="","",IF(B85+1>$E$42,"",B85+1)) -> 79 | C86: =L85 -> 51520449 | F86: =F85*(1+$K$42) -> 7984438.9 | I86: =I85*(1+$K$42) -> 5493294 | L86: =ABS((C86-F86)*(1+$Q$41)) -> 47889611 | O86: =O85*(1+$Q$40) -> 21900846 | T86: 33 | U86: =U85*(1+10%) -> 2111.3777 | V86: =FV((1+$Q$40)^(1/12)-1,12,-U86,-V85,1) -> 1204287.9
B87: =IF(B86="","",IF(B86+1>$E$42,"",B86+1)) -> 80 | C87: =L86 -> 47889611 | F87: =F86*(1+$K$42) -> 8543349.7 | I87: =I86*(1+$K$42) -> 5877824.6 | L87: =ABS((C87-F87)*(1+$Q$41)) -> 43280888 | O87: =O86*(1+$Q$40) -> 24528948 | S87: Blue | T87: 34 | U87: =U86*(1+10%) -> 2322.5154 | V87: =FV((1+$Q$40)^(1/12)-1,12,-U87,-V86,1) -> 1378452.9
B88: =IF(B87="","",IF(B87+1>$E$42,"",B87+1)) -> 81 | C88: =L87 -> 43280888 | F88: =F87*(1+$K$42) -> 9141384.1 | I88: =I87*(1+$K$42) -> 6289272.3 | L88: =ABS((C88-F88)*(1+$Q$41)) -> 37553454 | O88: =O87*(1+$Q$40) -> 27472421 | T88: 35 | U88: =U87*(1+10%) -> 2554.767 | V88: =FV((1+$Q$40)^(1/12)-1,12,-U88,-V87,1) -> 1576482.7
B89: =IF(B88="","",IF(B88+1>$E$42,"",B88+1)) -> 82 | C89: =L88 -> 37553454 | F89: =F88*(1+$K$42) -> 9781281 | I89: =I88*(1+$K$42) -> 6729521.4 | L89: =ABS((C89-F89)*(1+$Q$41)) -> 30549390 | O89: =O88*(1+$Q$40) -> 30769112 | S89: Blue | T89: 36 | U89: =U88*(1+10%) -> 2810.2437 | V89: =FV((1+$Q$40)^(1/12)-1,12,-U89,-V88,1) -> 1801537.5
B90: =IF(B89="","",IF(B89+1>$E$42,"",B89+1)) -> 83 | C90: =L89 -> 30549390 | F90: =F89*(1+$K$42) -> 10465971 | I90: =I89*(1+$K$42) -> 7200587.8 | L90: =ABS((C90-F90)*(1+$Q$41)) -> 22091761 | O90: =O89*(1+$Q$40) -> 34461405 | T90: 37 | U90: =U89*(1+10%) -> 3091.2681 | V90: =FV((1+$Q$40)^(1/12)-1,12,-U90,-V89,1) -> 2057186.7
B91: =IF(B90="","",IF(B90+1>$E$42,"",B90+1)) -> 84 | C91: =L90 -> 22091761 | F91: =F90*(1+$K$42) -> 11198589 | I91: =I90*(1+$K$42) -> 7704629 | L91: =ABS((C91-F91)*(1+$Q$41)) -> 11982490 | O91: =O90*(1+$Q$40) -> 38596774 | S91: Blue | T91: 38 | U91: =U90*(1+10%) -> 3400.3949 | V91: =FV((1+$Q$40)^(1/12)-1,12,-U91,-V90,1) -> 2347460.3
B92: =IF(B91="","",IF(B91+1>$E$42,"",B91+1)) -> 85 | C92: =L91 -> 11982490 | F92: =F91*(1+$K$42) -> 11982490 | I92: =I91*(1+$K$42) -> 8243953 | L92: =ABS((C92-F92)*(1+$Q$41)) -> 1.8645078e-07 | O92: =O91*(1+$Q$40) -> 43228387 | T92: 39 | U92: =U91*(1+10%) -> 3740.4343 | V92: =FV((1+$Q$40)^(1/12)-1,12,-U92,-V91,1) -> 2676907.7
B93: =IF(B92="","",IF(B92+1>$E$42,"",B92+1)) | C93: =L92 -> 1.8645078e-07 | F93: =F92*(1+$K$42) -> 12821264 | I93: =I92*(1+K66) -> 8243953 | L93: =ABS((C93-F93)*(1+$Q$41)) -> 14103391 | O93: =O92*(1+$Q$40) -> 48415793 | S93: Blue | T93: 40 | U93: =U92*(1+10%) -> 4114.4778 | V93: =FV((1+$Q$40)^(1/12)-1,12,-U93,-V92,1) -> 3050664.1
B94: =IF(B93="","",IF(B93+1>$E$42,"",B93+1)) | C94: =L93 -> 14103391 | F94: =F93*(1+$K$42) -> 13718753 | I94: =I93*(1+K67) -> 8243953 | L94: =ABS((C94-F94)*(1+$Q$41)) -> 423101.72 | O94: =O93*(1+$Q$40) -> 54225688 | T94: 41 | U94: =U93*(1+10%) -> 4525.9256 | V94: =FV((1+$Q$40)^(1/12)-1,12,-U94,-V93,1) -> 3474524.1
B95: =IF(B94="","",IF(B94+1>$E$42,"",B94+1)) | C95: =L94 -> 423101.72 | F95: =F94*(1+$K$42) -> 14679065 | I95: =I94*(1+K68) -> 8243953 | L95: =ABS((C95-F95)*(1+$Q$41)) -> 15681560 | O95: =O94*(1+$Q$40) -> 60732771 | S95: Blue | T95: 42 | U95: =U94*(1+10%) -> 4978.5181 | V95: =FV((1+$Q$40)^(1/12)-1,12,-U95,-V94,1) -> 3955025.2
B96: =IF(B95="","",IF(B95+1>$E$42,"",B95+1)) | C96: =L95 -> 15681560 | F96: =F95*(1+$K$42) -> 15706600 | I96: =I95*(1+K69) -> 8243953 | L96: =ABS((C96-F96)*(1+$Q$41)) -> 27543.922 | O96: =O95*(1+$Q$40) -> 68020703 | T96: 43 | U96: =U95*(1+10%) -> 5476.3699 | V96: =FV((1+$Q$40)^(1/12)-1,12,-U96,-V95,1) -> 4499542.3
B97: =IF(B96="","",IF(B96+1>$E$42,"",B96+1)) | C97: =L96 -> 27543.922 | F97: =F96*(1+$K$42) -> 16806062 | I97: =I96*(1+K70) -> 8243953 | L97: =ABS((C97-F97)*(1+$Q$41)) -> 18456370 | O97: =O96*(1+$Q$40) -> 76183188 | S97: Blue | T97: 44 | U97: =U96*(1+10%) -> 6024.0069 | V97: =FV((1+$Q$40)^(1/12)-1,12,-U97,-V96,1) -> 5116392.8
B98: =UPPER(D7)&"'S HIGHER EDUCATION & MARRIAGE GOAL" -> SAHIL'S HIGHER EDUCATION & MARRIAGE GOAL | T98: 45 | U98: =U97*(1+10%) -> 6626.4076 | V98: =FV((1+$Q$40)^(1/12)-1,12,-U98,-V97,1) -> 5814956
T99: 46 | U99: =U98*(1+10%) -> 7289.0484 | V99: =FV((1+$Q$40)^(1/12)-1,12,-U99,-V98,1) -> 6605806.3
B100: Assumed return for short term (<3 Yrs) | F100: 0.08 | G100: for mid term (>3 Yrs and <5 Yrs) | K100: 0.1 | L100: For long term | N100: 0.12 | O100: Assumed inflation | Q100: 0.08 | S100: Age | T100: 47 | U100: =U99*(1+10%) -> 8017.9532 | V100: =FV((1+$Q$40)^(1/12)-1,12,-U100,-V99,1) -> 7500864.2
S101: =H7 -> 7 | T101: 48 | U101: =U100*(1+10%) -> 8819.7485 | V101: =FV((1+$Q$40)^(1/12)-1,12,-U101,-V100,1) -> 8513565.3
F102: AGE | G102: GOAL | J102: PRESENT VALUE | L102: FUTURE VALUE | N102: REQD. LUMPSUM | P102: REQD. SIP | T102: 49 | U102: =U101*(1+10%) -> 9701.7234 | V102: =FV((1+$Q$40)^(1/12)-1,12,-U102,-V101,1) -> 9659050.1
F103: 15 | G103: 10th Board Exam | J103: 200000 | L103: =FV($Q$100,S103,,-J103) -> 370186.04 | N103: =IF(S103<3,-PV($F$100,S103,,L103),IF(S103<5,-PV($K$100,S103,,L103),-PV($N$100,S103,,L103))) -> 149511.93 | P103: =IFERROR(IF(S103<3,-PMT((1+$F$100)^(1/12)-1,S103*12,,L103),IF(S103<5,-PMT((1+$K$100)^(1/12)-1,S103*12,,L103),-PMT((1+$N$100)^(1/12)-1,S103*12,,L103))),0) -> 2379.8823 | S103: =F103-$S$101 -> 8 | T103: 50 | U103: =U102*(1+10%) -> 10671.896 | V103: =FV((1+$Q$40)^(1/12)-1,12,-U103,-V102,1) -> 10954379 | W103: =IFERROR(VLOOKUP(G103,$T$104:$V$109,3,0),"") -> Upto Graduation
F104: =F103+1 -> 16 | G104: Entrance Exam Training | J104: 500000 | L104: =FV($Q$100,S104,,-J104) -> 999502.31 | N104: =IF(S104<3,-PV($F$100,S104,,L104),IF(S104<5,-PV($K$100,S104,,L104),-PV($N$100,S104,,L104))) -> 360430.55 | P104: =IFERROR(IF(S104<3,-PMT((1+$F$100)^(1/12)-1,S104*12,,L104),IF(S104<5,-PMT((1+$K$100)^(1/12)-1,S104*12,,L104),-PMT((1+$N$100)^(1/12)-1,S104*12,,L104))),0) -> 5348.9279 | S104: =F104-$S$101 -> 9 | T104: 10th Board Exam | V104: Upto Graduation | W104: =IFERROR(VLOOKUP(G104,$T$104:$V$109,3,0),"") -> Upto Graduation
F105: =F104+1 -> 17 | L105: =FV($Q$100,S105,,-J105) -> 0 | N105: =IF(S105<3,-PV($F$100,S105,,L105),IF(S105<5,-PV($K$100,S105,,L105),-PV($N$100,S105,,L105))) -> 0 | P105: =IFERROR(IF(S105<3,-PMT((1+$F$100)^(1/12)-1,S105*12,,L105),IF(S105<5,-PMT((1+$K$100)^(1/12)-1,S105*12,,L105),-PMT((1+$N$100)^(1/12)-1,S105*12,,L105))),0) -> 0 | S105: =F105-$S$101 -> 10 | T105: 10+2 Studies | V105: Upto Graduation | W105: =IFERROR(VLOOKUP(G105,$T$104:$V$109,3,0),"")
F106: =F105+1 -> 18 | G106: Graduation | J106: 1000000 | L106: =FV($Q$100,S106,,-J106) -> 2331639 | N106: =IF(S106<3,-PV($F$100,S106,,L106),IF(S106<5,-PV($K$100,S106,,L106),-PV($N$100,S106,,L106))) -> 670290.5 | P106: =IFERROR(IF(S106<3,-PMT((1+$F$100)^(1/12)-1,S106*12,,L106),IF(S106<5,-PMT((1+$K$100)^(1/12)-1,S106*12,,L106),-PMT((1+$N$100)^(1/12)-1,S106*12,,L106))),0) -> 8926.3641 | S106: =F106-$S$101 -> 11 | T106: Entrance Exam Training | V106: Upto Graduation | W106: =IFERROR(VLOOKUP(G106,$T$104:$V$109,3,0),"") -> Upto Graduation
F107: =F106+1 -> 19 | L107: =FV($Q$100,S107,,-J107) -> 0 | N107: =IF(S107<3,-PV($F$100,S107,,L107),IF(S107<5,-PV($K$100,S107,,L107),-PV($N$100,S107,,L107))) -> 0 | P107: =IFERROR(IF(S107<3,-PMT((1+$F$100)^(1/12)-1,S107*12,,L107),IF(S107<5,-PMT((1+$K$100)^(1/12)-1,S107*12,,L107),-PMT((1+$N$100)^(1/12)-1,S107*12,,L107))),0) -> 0 | S107: =F107-$S$101 -> 12 | T107: Graduation | V107: Upto Graduation | W107: =IFERROR(VLOOKUP(G107,$T$104:$V$109,3,0),"")
F108: =F107+1 -> 20 | L108: =FV($Q$100,S108,,-J108) -> 0 | N108: =IF(S108<3,-PV($F$100,S108,,L108),IF(S108<5,-PV($K$100,S108,,L108),-PV($N$100,S108,,L108))) -> 0 | P108: =IFERROR(IF(S108<3,-PMT((1+$F$100)^(1/12)-1,S108*12,,L108),IF(S108<5,-PMT((1+$K$100)^(1/12)-1,S108*12,,L108),-PMT((1+$N$100)^(1/12)-1,S108*12,,L108))),0) -> 0 | S108: =F108-$S$101 -> 13 | T108: Post Graduation | V108: Post Graduation | W108: =IFERROR(VLOOKUP(G108,$T$104:$V$109,3,0),"")
F109: =F108+1 -> 21 | L109: =FV($Q$100,S109,,-J109) -> 0 | N109: =IF(S109<3,-PV($F$100,S109,,L109),IF(S109<5,-PV($K$100,S109,,L109),-PV($N$100,S109,,L109))) -> 0 | P109: =IFERROR(IF(S109<3,-PMT((1+$F$100)^(1/12)-1,S109*12,,L109),IF(S109<5,-PMT((1+$K$100)^(1/12)-1,S109*12,,L109),-PMT((1+$N$100)^(1/12)-1,S109*12,,L109))),0) -> 0 | S109: =F109-$S$101 -> 14 | T109: Marriage | V109: Marriage | W109: =IFERROR(VLOOKUP(G109,$T$104:$V$109,3,0),"")
F110: =F109+1 -> 22 | G110: Post Graduation | J110: 1000000 | L110: =FV($Q$100,S110,,-J110) -> 3172169.1 | N110: =IF(S110<3,-PV($F$100,S110,,L110),IF(S110<5,-PV($K$100,S110,,L110),-PV($N$100,S110,,L110))) -> 579543.44 | P110: =IFERROR(IF(S110<3,-PMT((1+$F$100)^(1/12)-1,S110*12,,L110),IF(S110<5,-PMT((1+$K$100)^(1/12)-1,S110*12,,L110),-PMT((1+$N$100)^(1/12)-1,S110*12,,L110))),0) -> 6728.4259 | S110: =F110-$S$101 -> 15 | W110: =IFERROR(VLOOKUP(G110,$T$104:$V$109,3,0),"") -> Post Graduation
F111: =F110+1 -> 23 | L111: =FV($Q$100,S111,,-J111) -> 0 | N111: =IF(S111<3,-PV($F$100,S111,,L111),IF(S111<5,-PV($K$100,S111,,L111),-PV($N$100,S111,,L111))) -> 0 | P111: =IFERROR(IF(S111<3,-PMT((1+$F$100)^(1/12)-1,S111*12,,L111),IF(S111<5,-PMT((1+$K$100)^(1/12)-1,S111*12,,L111),-PMT((1+$N$100)^(1/12)-1,S111*12,,L111))),0) -> 0 | S111: =F111-$S$101 -> 16 | W111: =IFERROR(VLOOKUP(G111,$T$104:$V$109,3,0),"")
F112: =F111+1 -> 24 | L112: =FV($Q$100,S112,,-J112) -> 0 | N112: =IF(S112<3,-PV($F$100,S112,,L112),IF(S112<5,-PV($K$100,S112,,L112),-PV($N$100,S112,,L112))) -> 0 | P112: =IFERROR(IF(S112<3,-PMT((1+$F$100)^(1/12)-1,S112*12,,L112),IF(S112<5,-PMT((1+$K$100)^(1/12)-1,S112*12,,L112),-PMT((1+$N$100)^(1/12)-1,S112*12,,L112))),0) -> 0 | S112: =F112-$S$101 -> 17 | W112: =IFERROR(VLOOKUP(G112,$T$104:$V$109,3,0),"")
F113: =F112+1 -> 25 | L113: =FV($Q$100,S113,,-J113) -> 0 | N113: =IF(S113<3,-PV($F$100,S113,,L113),IF(S113<5,-PV($K$100,S113,,L113),-PV($N$100,S113,,L113))) -> 0 | P113: =IFERROR(IF(S113<3,-PMT((1+$F$100)^(1/12)-1,S113*12,,L113),IF(S113<5,-PMT((1+$K$100)^(1/12)-1,S113*12,,L113),-PMT((1+$N$100)^(1/12)-1,S113*12,,L113))),0) -> 0 | S113: =F113-$S$101 -> 18 | W113: =IFERROR(VLOOKUP(G113,$T$104:$V$109,3,0),"")
F114: =F113+1 -> 26 | G114: Marriage | J114: 1500000 | L114: =FV($Q$100,S114,,-J114) -> 6473551.6 | N114: =IF(S114<3,-PV($F$100,S114,,L114),IF(S114<5,-PV($K$100,S114,,L114),-PV($N$100,S114,,L114))) -> 751623.21 | P114: =IFERROR(IF(S114<3,-PMT((1+$F$100)^(1/12)-1,S114*12,,L114),IF(S114<5,-PMT((1+$K$100)^(1/12)-1,S114*12,,L114),-PMT((1+$N$100)^(1/12)-1,S114*12,,L114))),0) -> 8068.8445 | S114: =F114-$S$101 -> 19 | W114: =IFERROR(VLOOKUP(G114,$T$104:$V$109,3,0),"") -> Marriage
...

Sheet 10
A2: BACK | B2: FINANCIAL HEALTH CHECKUP
B5: Prepared for: | E5: =" "&UPPER('Main Menu'!C29) -> CLIENT NAME
B6: Prepared by: | E6: =" "&UPPER('Main Menu'!L29) -> PARTNER NAME | J6: ="Dated: "& TEXT(TODAY(),"DD-MMM-YYYY") -> Dated: 28-Aug-2025
B8: Your age | D8: 49 | F8: Your monthly income | I8: 200000
B9: Current EMI amount you're paying monthly | G9: 75000 | I9: Your current monthly investment amount | N9: 50000
B10: Your assets & liabilities details:
B11: INVESTMENT ASSETS | E11: CURRENT VALUE | G11: LIABILITIES | I11: OUTSTANDING | K11: PHYSICAL ASSETS | N11: CURRENT VALUE
B12: Liquid | E12: 1000000 | G12: Home Loan | I12: 2500000 | K12: Property (excl. non-primary) | N12: 5000000
B13: Debt | E13: 2000000 | G13: Vehicle Loan | I13: 0 | K13: Gold, Silver (inv. purpose) | N13: 0
B14: Equity | E14: 3000000 | G14: Personal Loan | I14: 0 | K14: PERSONAL ASSETS | N14: CURRENT VALUE
B15: Commodity | E15: 0 | G15: Education Loan | I15: 0 | K15: Primary Residence | N15: 17500000
B16: REIT / Structured Products | E16: 0 | G16: Consumer Loan | I16: 0 | K16: Personal Vehicles | N16: 1500000
B17: Alternative Investsment | E17: 0 | G17: Credit Card | I17: 0 | K17: Jewellery | N17: 1000000
B19: NET WORTH: | J19: DEBT TO INCOME RATIO:
B20: Net worth including personal assets (A) | G20: =SUM(E12:E17,N12:N13,N15:N17)-SUM(I12:I17) -> 28500000 | J20: Your current EMI amount | N20: =G9 -> 75000 | Q20: =G21<G22 -> TRUE
B21: Net worth excluding personal assets (B) | G21: =SUM(E12:E17,N12:N13)-SUM(I12:I17) -> 8500000 | J21: Your debt to income ratio | N21: =N20/I8 -> 0.375 | Q21: =N21>N22 -> TRUE
B22: Above net worth (B) shouldn't be less than | G22: =D8*(I8*12)/10 -> 11760000 | J22: This shouldn't be more than | N22: 0.3 | Q22: =G26<G27 -> TRUE
Q23: =N26<N27 -> TRUE
B24: INVESTMENT RATIO: | J24: FINANCIAL ASSETS RATIO:
B25: Your current monthly investment | G25: =N9 -> 50000 | J25: Your total financial assets | N25: =SUM(E12:E17) -> 6000000
B26: Your current investment ratio | G26: =G25/I8 -> 0.25 | J26: Financial assets / Total assets | N26: =N25/SUM(E12:E17,N12:N13,N15:N17) -> 0.19354839
B27: This shouldn't be less than | G27: =IF(D8<=25,10%, IF(D8<=35,20%,35%)) -> 0.35 | J27: This shouldn't be less than | N27: 0.2

Sheet 11
A2: BACK | B2: 3-in-1 : Life, Health and Wealth
S3: =VLOOKUP(G12,S6:AA55,9,0) -> 53681539
B5: Prepared for: | D5: =" "&UPPER('Main Menu'!C29) -> CLIENT NAME | S5: Year | T5: Age | U5: Contribution | V5: LI | W5: LI Mthly | X5: HI | Y5: HI Monthly | Z5: SIP | AA5: Wealth
B6: Prepared by: | D6: =" "&UPPER('Main Menu'!L29) -> PARTNER NAME | I6: ="Dated: "& TEXT(TODAY(),"DD-MMM-YYYY") -> Dated: 28-Aug-2025 | S6: 1 | T6: =G11+1 -> 36 | U6: =G9 -> 15000 | V6: =N10 -> 10915 | W6: =V6/12 -> 909.58333 | X6: =N12 -> 18379 | Y6: =IF(S6="","",X6/12) -> 1531.5833 | Z6: =IF(S6="","",U6-(W6+Y6)) -> 12558.833 | AA6: =IF(S6="","",FV((1+$G$13)^(1/12)-1,12,-Z6,IF(ISNUMBER(AA5),-AA5,0),1)) -> 160332.32
S7: =IF(S6="","",IF(S6+1<=$G$12,S6+1,"")) -> 2 | T7: =IF(S7="","",T6+1) -> 37 | U7: =IF(S7="","",U6*(1+$G$10)) -> 16500 | V7: =IF(S7="","",V6) -> 10915 | W7: =IF(S7="","",V7/12) -> 909.58333 | X7: =IF(S7="","",X6*(1+$N$13)) -> 19297.95 | Y7: =IF(S7="","",X7/12) -> 1608.1625 | Z7: =IF(S7="","",U7-(W7+Y7)) -> 13982.254 | AA7: =IF(S7="","",FV((1+$G$13)^(1/12)-1,12,-Z7,IF(ISNUMBER(AA6),-AA6,0),1)) -> 358076.62
B8: =UPPER("Personal and investment details") -> PERSONAL AND INVESTMENT DETAILS | J8: =UPPER("Insurance details") -> INSURANCE DETAILS | S8: =IF(S7="","",IF(S7+1<=$G$12,S7+1,"")) -> 3 | T8: =IF(S8="","",T7+1) -> 38 | U8: =IF(S8="","",U7*(1+$G$10)) -> 18150 | V8: =IF(S8="","",V7) -> 10915 | W8: =IF(S8="","",V8/12) -> 909.58333 | X8: =IF(S8="","",X7*(1+$N$13)) -> 20262.847 | Y8: =IF(S8="","",X8/12) -> 1688.5706 | Z8: =IF(S8="","",U8-(W8+Y8)) -> 15551.846 | AA8: =IF(S8="","",FV((1+$G$13)^(1/12)-1,12,-Z8,IF(ISNUMBER(AA7),-AA7,0),1)) -> 599588.42
B9: Monthly amount, you want to start with | G9: 15000 | J9: Life insurance cover amt | N9: 5000000 | S9: =IF(S8="","",IF(S8+1<=$G$12,S8+1,"")) -> 4 | T9: =IF(S9="","",T8+1) -> 39 | U9: =IF(S9="","",U8*(1+$G$10)) -> 19965 | V9: =IF(S9="","",V8) -> 10915 | W9: =IF(S9="","",V9/12) -> 909.58333 | X9: =IF(S9="","",X8*(1+$N$13)) -> 21275.99 | Y9: =IF(S9="","",X9/12) -> 1772.9992 | Z9: =IF(S9="","",U9-(W9+Y9)) -> 17282.418 | AA9: =IF(S9="","",FV((1+$G$13)^(1/12)-1,12,-Z9,IF(ISNUMBER(AA8),-AA8,0),1)) -> 892174.98
B10: Annual step-up% on monthly contribution amt | G10: 0.1 | J10: Annual life insurance premium | N10: 10915 | S10: =IF(S9="","",IF(S9+1<=$G$12,S9+1,"")) -> 5 | T10: =IF(S10="","",T9+1) -> 40 | U10: =IF(S10="","",U9*(1+$G$10)) -> 21961.5 | V10: =IF(S10="","",V9) -> 10915 | W10: =IF(S10="","",V10/12) -> 909.58333 | X10: =IF(S10="","",X9*(1+$N$13)) -> 22339.789 | Y10: =IF(S10="","",X10/12) -> 1861.6491 | Z10: =IF(S10="","",U10-(W10+Y10)) -> 19190.268 | AA10: =IF(S10="","",FV((1+$G$13)^(1/12)-1,12,-Z10,IF(ISNUMBER(AA9),-AA9,0),1)) -> 1244228.5
B11: Your age now | G11: 35 | J11: Health insurance cover amt | N11: 1000000 | S11: =IF(S10="","",IF(S10+1<=$G$12,S10+1,"")) -> 6 | T11: =IF(S11="","",T10+1) -> 41 | U11: =IF(S11="","",U10*(1+$G$10)) -> 24157.65 | V11: =IF(S11="","",V10) -> 10915 | W11: =IF(S11="","",V11/12) -> 909.58333 | X11: =IF(S11="","",X10*(1+$N$13)) -> 23456.779 | Y11: =IF(S11="","",X11/12) -> 1954.7316 | Z11: =IF(S11="","",U11-(W11+Y11)) -> 21293.335 | AA11: =IF(S11="","",FV((1+$G$13)^(1/12)-1,12,-Z11,IF(ISNUMBER(AA10),-AA10,0),1)) -> 1665377.2
B12: No. of years, you want to contribute | G12: 25 | J12: Annual health insurance (HI) premium | N12: 18379 | S12: =IF(S11="","",IF(S11+1<=$G$12,S11+1,"")) -> 7 | T12: =IF(S12="","",T11+1) -> 42 | U12: =IF(S12="","",U11*(1+$G$10)) -> 26573.415 | V12: =IF(S12="","",V11) -> 10915 | W12: =IF(S12="","",V12/12) -> 909.58333 | X12: =IF(S12="","",X11*(1+$N$13)) -> 24629.618 | Y12: =IF(S12="","",X12/12) -> 2052.4681 | Z12: =IF(S12="","",U12-(W12+Y12)) -> 23611.364 | AA12: =IF(S12="","",FV((1+$G$13)^(1/12)-1,12,-Z12,IF(ISNUMBER(AA11),-AA11,0),1)) -> 2166656.9
B13: Assumed return from investment amt | G13: 0.12 | J13: Premium increase % on HI renewal | N13: 0.05 | S13: =IF(S12="","",IF(S12+1<=$G$12,S12+1,"")) -> 8 | T13: =IF(S13="","",T12+1) -> 43 | U13: =IF(S13="","",U12*(1+$G$10)) -> 29230.757 | V13: =IF(S13="","",V12) -> 10915 | W13: =IF(S13="","",V13/12) -> 909.58333 | X13: =IF(S13="","",X12*(1+$N$13)) -> 25861.099 | Y13: =IF(S13="","",X13/12) -> 2155.0916 | Z13: =IF(S13="","",U13-(W13+Y13)) -> 26166.082 | AA13: =IF(S13="","",FV((1+$G$13)^(1/12)-1,12,-Z13,IF(ISNUMBER(AA12),-AA12,0),1)) -> 2760705
S14: =IF(S13="","",IF(S13+1<=$G$12,S13+1,"")) -> 9 | T14: =IF(S14="","",T13+1) -> 44 | U14: =IF(S14="","",U13*(1+$G$10)) -> 32153.832 | V14: =IF(S14="","",V13) -> 10915 | W14: =IF(S14="","",V14/12) -> 909.58333 | X14: =IF(S14="","",X13*(1+$N$13)) -> 27154.154 | Y14: =IF(S14="","",X14/12) -> 2262.8461 | Z14: =IF(S14="","",U14-(W14+Y14)) -> 28981.403 | AA14: =IF(S14="","",FV((1+$G$13)^(1/12)-1,12,-Z14,IF(ISNUMBER(AA13),-AA13,0),1)) -> 3461980.6
B15: By starting with mthly contribution of Rs. | G15: =G9 -> 15000 | K15: =" by your age of "&G11+G12&", you'll get all of the below:" -> by your age of 60, you'll get all of the below: | S15: =IF(S14="","",IF(S14+1<=$G$12,S14+1,"")) -> 10 | T15: =IF(S15="","",T14+1) -> 45 | U15: =IF(S15="","",U14*(1+$G$10)) -> 35369.215 | V15: =IF(S15="","",V14) -> 10915 | W15: =IF(S15="","",V15/12) -> 909.58333 | X15: =IF(S15="","",X14*(1+$N$13)) -> 28511.861 | Y15: =IF(S15="","",X15/12) -> 2375.9884 | Z15: =IF(S15="","",U15-(W15+Y15)) -> 32083.644 | AA15: =IF(S15="","",FV((1+$G$13)^(1/12)-1,12,-Z15,IF(ISNUMBER(AA14),-AA14,0),1)) -> 4287014
S16: =IF(S15="","",IF(S15+1<=$G$12,S15+1,"")) -> 11 | T16: =IF(S16="","",T15+1) -> 46 | U16: =IF(S16="","",U15*(1+$G$10)) -> 38906.137 | V16: =IF(S16="","",V15) -> 10915 | W16: =IF(S16="","",V16/12) -> 909.58333 | X16: =IF(S16="","",X15*(1+$N$13)) -> 29937.454 | Y16: =IF(S16="","",X16/12) -> 2494.7879 | Z16: =IF(S16="","",U16-(W16+Y16)) -> 35501.766 | AA16: =IF(S16="","",FV((1+$G$13)^(1/12)-1,12,-Z16,IF(ISNUMBER(AA15),-AA15,0),1)) -> 5254688.9
B17: LIFE INSURANCE COVER | G17: HEALTH INSURANCE COVER | L17: WEALTH CREATED | S17: =IF(S16="","",IF(S16+1<=$G$12,S16+1,"")) -> 12 | T17: =IF(S17="","",T16+1) -> 47 | U17: =IF(S17="","",U16*(1+$G$10)) -> 42796.751 | V17: =IF(S17="","",V16) -> 10915 | W17: =IF(S17="","",V17/12) -> 909.58333 | X17: =IF(S17="","",X16*(1+$N$13)) -> 31434.327 | Y17: =IF(S17="","",X17/12) -> 2619.5273 | Z17: =IF(S17="","",U17-(W17+Y17)) -> 39267.64 | AA17: =IF(S17="","",FV((1+$G$13)^(1/12)-1,12,-Z17,IF(ISNUMBER(AA16),-AA16,0),1)) -> 6386561.8
B18: =IF(N9<10000000,IF(MOD(N9,100000)=0, TEXT(N9/100000, "#"), TEXT(N9/100000, "#.00"))&" Lakhs",IF(MOD(N9,10000000)=0, TEXT(N9/10000000, "#"), TEXT(N9/10000000, "#.00"))&" Cr") -> 50 Lakhs | G18: =IF(N11<10000000,IF(MOD(N11,100000)=0, TEXT(N11/100000, "#"), TEXT(N11/100000, "#.00"))&" Lakhs",IF(MOD(N11,10000000)=0, TEXT(N11/10000000, "#"), TEXT(N11/10000000, "#.00"))&" Cr") -> 10 Lakhs | L18: =IF(S3<10000000,IF(MOD(S3,100000)=0, TEXT(S3/100000, "#"), TEXT(S3/100000, "#.00"))&" Lakhs",IF(MOD(S3,10000000)=0, TEXT(S3/10000000, "#"), TEXT(S3/10000000, "#.00"))&" Cr") -> 5.37 Cr | S18: =IF(S17="","",IF(S17+1<=$G$12,S17+1,"")) -> 13 | T18: =IF(S18="","",T17+1) -> 48 | U18: =IF(S18="","",U17*(1+$G$10)) -> 47076.426 | V18: =IF(S18="","",V17) -> 10915 | W18: =IF(S18="","",V18/12) -> 909.58333 | X18: =IF(S18="","",X17*(1+$N$13)) -> 33006.043 | Y18: =IF(S18="","",X18/12) -> 2750.5036 | Z18: =IF(S18="","",U18-(W18+Y18)) -> 43416.339 | AA18: =IF(S18="","",FV((1+$G$13)^(1/12)-1,12,-Z18,IF(ISNUMBER(AA17),-AA17,0),1)) -> 7707223.8
S19: =IF(S18="","",IF(S18+1<=$G$12,S18+1,"")) -> 14 | T19: =IF(S19="","",T18+1) -> 49 | U19: =IF(S19="","",U18*(1+$G$10)) -> 51784.068 | V19: =IF(S19="","",V18) -> 10915 | W19: =IF(S19="","",V19/12) -> 909.58333 | X19: =IF(S19="","",X18*(1+$N$13)) -> 34656.346 | Y19: =IF(S19="","",X19/12) -> 2888.0288 | Z19: =IF(S19="","",U19-(W19+Y19)) -> 47986.456 | AA19: =IF(S19="","",FV((1+$G$13)^(1/12)-1,12,-Z19,IF(ISNUMBER(AA18),-AA18,0),1)) -> 9244709.7
B20: ="Monthly contribution amount breakup @ age "&G11 -> Monthly contribution amount breakup @ age 35 | J20: ="Monthly contribution amt breakup @ age "&G11+G12 -> Monthly contribution amt breakup @ age 60 | S20: =IF(S19="","",IF(S19+1<=$G$12,S19+1,"")) -> 15 | T20: =IF(S20="","",T19+1) -> 50 | U20: =IF(S20="","",U19*(1+$G$10)) -> 56962.475 | V20: =IF(S20="","",V19) -> 10915 | W20: =IF(S20="","",V20/12) -> 909.58333 | X20: =IF(S20="","",X19*(1+$N$13)) -> 36389.163 | Y20: =IF(S20="","",X20/12) -> 3032.4302 | Z20: =IF(S20="","",U20-(W20+Y20)) -> 53020.461 | AA20: =IF(S20="","",FV((1+$G$13)^(1/12)-1,12,-Z20,IF(ISNUMBER(AA19),-AA19,0),1)) -> 11030960
B21: Total monthly outgo | G21: =G9 -> 15000 | J21: Total monthly outgo | N21: =VLOOKUP(G12,S6:U55,3,0) -> 147745.99 | S21: =IF(S20="","",IF(S20+1<=$G$12,S20+1,"")) -> 16 | T21: =IF(S21="","",T20+1) -> 51 | U21: =IF(S21="","",U20*(1+$G$10)) -> 62658.723 | V21: =IF(S21="","",V20) -> 10915 | W21: =IF(S21="","",V21/12) -> 909.58333 | X21: =IF(S21="","",X20*(1+$N$13)) -> 38208.621 | Y21: =IF(S21="","",X21/12) -> 3184.0518 | Z21: =IF(S21="","",U21-(W21+Y21)) -> 58565.087 | AA21: =IF(S21="","",FV((1+$G$13)^(1/12)-1,12,-Z21,IF(ISNUMBER(AA20),-AA20,0),1)) -> 13102347
B22: Annual life insurance premium | G22: =N10 -> 10915 | J22: Annual life insurance premium | N22: =VLOOKUP(G12,S6:V55,4,0) -> 10915 | S22: =IF(S21="","",IF(S21+1<=$G$12,S21+1,"")) -> 17 | T22: =IF(S22="","",T21+1) -> 52 | U22: =IF(S22="","",U21*(1+$G$10)) -> 68924.595 | V22: =IF(S22="","",V21) -> 10915 | W22: =IF(S22="","",V22/12) -> 909.58333 | X22: =IF(S22="","",X21*(1+$N$13)) -> 40119.052 | Y22: =IF(S22="","",X22/12) -> 3343.2543 | Z22: =IF(S22="","",U22-(W22+Y22)) -> 64671.757 | AA22: =IF(S22="","",FV((1+$G$13)^(1/12)-1,12,-Z22,IF(ISNUMBER(AA21),-AA21,0),1)) -> 15500260
B23: Monthly life insurance premium | G23: =G22/12 -> 909.58333 | J23: Monthly life insurance premium | N23: =N22/12 -> 909.58333 | S23: =IF(S22="","",IF(S22+1<=$G$12,S22+1,"")) -> 18 | T23: =IF(S23="","",T22+1) -> 53 | U23: =IF(S23="","",U22*(1+$G$10)) -> 75817.054 | V23: =IF(S23="","",V22) -> 10915 | W23: =IF(S23="","",V23/12) -> 909.58333 | X23: =IF(S23="","",X22*(1+$N$13)) -> 42125.005 | Y23: =IF(S23="","",X23/12) -> 3510.4171 | Z23: =IF(S23="","",U23-(W23+Y23)) -> 71397.054 | AA23: =IF(S23="","",FV((1+$G$13)^(1/12)-1,12,-Z23,IF(ISNUMBER(AA22),-AA22,0),1)) -> 18271782
B24: Annual health insurance premium | G24: =N12 -> 18379 | J24: Annual health insurance premium | N24: =VLOOKUP(G12,S6:X55,6,0) -> 59274.112 | S24: =IF(S23="","",IF(S23+1<=$G$12,S23+1,"")) -> 19 | T24: =IF(S24="","",T23+1) -> 54 | U24: =IF(S24="","",U23*(1+$G$10)) -> 83398.76 | V24: =IF(S24="","",V23) -> 10915 | W24: =IF(S24="","",V24/12) -> 909.58333 | X24: =IF(S24="","",X23*(1+$N$13)) -> 44231.255 | Y24: =IF(S24="","",X24/12) -> 3685.9379 | Z24: =IF(S24="","",U24-(W24+Y24)) -> 78803.238 | AA24: =IF(S24="","",FV((1+$G$13)^(1/12)-1,12,-Z24,IF(ISNUMBER(AA23),-AA23,0),1)) -> 21470437
B25: Monthly health insurance premium | G25: =G24/12 -> 1531.5833 | J25: Monthly health insurance premium | N25: =N24/12 -> 4939.5093 | S25: =IF(S24="","",IF(S24+1<=$G$12,S24+1,"")) -> 20 | T25: =IF(S25="","",T24+1) -> 55 | U25: =IF(S25="","",U24*(1+$G$10)) -> 91738.636 | V25: =IF(S25="","",V24) -> 10915 | W25: =IF(S25="","",V25/12) -> 909.58333 | X25: =IF(S25="","",X24*(1+$N$13)) -> 46442.818 | Y25: =IF(S25="","",X25/12) -> 3870.2348 | Z25: =IF(S25="","",U25-(W25+Y25)) -> 86958.818 | AA25: =IF(S25="","",FV((1+$G$13)^(1/12)-1,12,-Z25,IF(ISNUMBER(AA24),-AA24,0),1)) -> 25157049
B26: Monthly SIP investment amt | G26: =G21-(G23+G25) -> 12558.833 | J26: Monthly SIP investment amt | N26: =N21-(N23+N25) -> 141896.9 | S26: =IF(S25="","",IF(S25+1<=$G$12,S25+1,"")) -> 21 | T26: =IF(S26="","",T25+1) -> 56 | U26: =IF(S26="","",U25*(1+$G$10)) -> 100912.5 | V26: =IF(S26="","",V25) -> 10915 | W26: =IF(S26="","",V26/12) -> 909.58333 | X26: =IF(S26="","",X25*(1+$N$13)) -> 48764.959 | Y26: =IF(S26="","",X26/12) -> 4063.7465 | Z26: =IF(S26="","",U26-(W26+Y26)) -> 95939.169 | AA26: =IF(S26="","",FV((1+$G$13)^(1/12)-1,12,-Z26,IF(ISNUMBER(AA25),-AA25,0),1)) -> 29400702
S27: =IF(S26="","",IF(S26+1<=$G$12,S26+1,"")) -> 22 | T27: =IF(S27="","",T26+1) -> 57 | U27: =IF(S27="","",U26*(1+$G$10)) -> 111003.75 | V27: =IF(S27="","",V26) -> 10915 | W27: =IF(S27="","",V27/12) -> 909.58333 | X27: =IF(S27="","",X26*(1+$N$13)) -> 51203.206 | Y27: =IF(S27="","",X27/12) -> 4266.9339 | Z27: =IF(S27="","",U27-(W27+Y27)) -> 105827.23 | AA27: =IF(S27="","",FV((1+$G$13)^(1/12)-1,12,-Z27,IF(ISNUMBER(AA26),-AA26,0),1)) -> 34279830
S28: =IF(S27="","",IF(S27+1<=$G$12,S27+1,"")) -> 23 | T28: =IF(S28="","",T27+1) -> 58 | U28: =IF(S28="","",U27*(1+$G$10)) -> 122104.12 | V28: =IF(S28="","",V27) -> 10915 | W28: =IF(S28="","",V28/12) -> 909.58333 | X28: =IF(S28="","",X27*(1+$N$13)) -> 53763.367 | Y28: =IF(S28="","",X28/12) -> 4480.2806 | Z28: =IF(S28="","",U28-(W28+Y28)) -> 116714.26 | AA28: =IF(S28="","",FV((1+$G$13)^(1/12)-1,12,-Z28,IF(ISNUMBER(AA27),-AA27,0),1)) -> 39883441
S29: =IF(S28="","",IF(S28+1<=$G$12,S28+1,"")) -> 24 | T29: =IF(S29="","",T28+1) -> 59 | U29: =IF(S29="","",U28*(1+$G$10)) -> 134314.54 | V29: =IF(S29="","",V28) -> 10915 | W29: =IF(S29="","",V29/12) -> 909.58333 | X29: =IF(S29="","",X28*(1+$N$13)) -> 56451.535 | Y29: =IF(S29="","",X29/12) -> 4704.2946 | Z29: =IF(S29="","",U29-(W29+Y29)) -> 128700.66 | AA29: =IF(S29="","",FV((1+$G$13)^(1/12)-1,12,-Z29,IF(ISNUMBER(AA28),-AA28,0),1)) -> 46312511
S30: =IF(S29="","",IF(S29+1<=$G$12,S29+1,"")) -> 25 | T30: =IF(S30="","",T29+1) -> 60 | U30: =IF(S30="","",U29*(1+$G$10)) -> 147745.99 | V30: =IF(S30="","",V29) -> 10915 | W30: =IF(S30="","",V30/12) -> 909.58333 | X30: =IF(S30="","",X29*(1+$N$13)) -> 59274.112 | Y30: =IF(S30="","",X30/12) -> 4939.5093 | Z30: =IF(S30="","",U30-(W30+Y30)) -> 141896.9 | AA30: =IF(S30="","",FV((1+$G$13)^(1/12)-1,12,-Z30,IF(ISNUMBER(AA29),-AA29,0),1)) -> 53681539
S31: =IF(S30="","",IF(S30+1<=$G$12,S30+1,"")) | T31: =IF(S31="","",T30+1) | U31: =IF(S31="","",U30*(1+$G$10)) | V31: =IF(S31="","",V30) | W31: =IF(S31="","",V31/12) | X31: =IF(S31="","",X30*(1+$N$13)) | Y31: =IF(S31="","",X31/12) | Z31: =IF(S31="","",U31-(W31+Y31)) | AA31: =IF(S31="","",FV((1+$G$13)^(1/12)-1,12,-Z31,IF(ISNUMBER(AA30),-AA30,0),1))
S32: =IF(S31="","",IF(S31+1<=$G$12,S31+1,"")) | T32: =IF(S32="","",T31+1) | U32: =IF(S32="","",U31*(1+$G$10)) | V32: =IF(S32="","",V31) | W32: =IF(S32="","",V32/12) | X32: =IF(S32="","",X31*(1+$N$13)) | Y32: =IF(S32="","",X32/12) | Z32: =IF(S32="","",U32-(W32+Y32)) | AA32: =IF(S32="","",FV((1+$G$13)^(1/12)-1,12,-Z32,IF(ISNUMBER(AA31),-AA31,0),1))
S33: =IF(S32="","",IF(S32+1<=$G$12,S32+1,"")) | T33: =IF(S33="","",T32+1) | U33: =IF(S33="","",U32*(1+$G$10)) | V33: =IF(S33="","",V32) | W33: =IF(S33="","",V33/12) | X33: =IF(S33="","",X32*(1+$N$13)) | Y33: =IF(S33="","",X33/12) | Z33: =IF(S33="","",U33-(W33+Y33)) | AA33: =IF(S33="","",FV((1+$G$13)^(1/12)-1,12,-Z33,IF(ISNUMBER(AA32),-AA32,0),1))
S34: =IF(S33="","",IF(S33+1<=$G$12,S33+1,"")) | T34: =IF(S34="","",T33+1) | U34: =IF(S34="","",U33*(1+$G$10)) | V34: =IF(S34="","",V33) | W34: =IF(S34="","",V34/12) | X34: =IF(S34="","",X33*(1+$N$13)) | Y34: =IF(S34="","",X34/12) | Z34: =IF(S34="","",U34-(W34+Y34)) | AA34: =IF(S34="","",FV((1+$G$13)^(1/12)-1,12,-Z34,IF(ISNUMBER(AA33),-AA33,0),1))
S35: =IF(S34="","",IF(S34+1<=$G$12,S34+1,"")) | T35: =IF(S35="","",T34+1) | U35: =IF(S35="","",U34*(1+$G$10)) | V35: =IF(S35="","",V34) | W35: =IF(S35="","",V35/12) | X35: =IF(S35="","",X34*(1+$N$13)) | Y35: =IF(S35="","",X35/12) | Z35: =IF(S35="","",U35-(W35+Y35)) | AA35: =IF(S35="","",FV((1+$G$13)^(1/12)-1,12,-Z35,IF(ISNUMBER(AA34),-AA34,0),1))
S36: =IF(S35="","",IF(S35+1<=$G$12,S35+1,"")) | T36: =IF(S36="","",T35+1) | U36: =IF(S36="","",U35*(1+$G$10)) | V36: =IF(S36="","",V35) | W36: =IF(S36="","",V36/12) | X36: =IF(S36="","",X35*(1+$N$13)) | Y36: =IF(S36="","",X36/12) | Z36: =IF(S36="","",U36-(W36+Y36)) | AA36: =IF(S36="","",FV((1+$G$13)^(1/12)-1,12,-Z36,IF(ISNUMBER(AA35),-AA35,0),1))
S37: =IF(S36="","",IF(S36+1<=$G$12,S36+1,"")) | T37: =IF(S37="","",T36+1) | U37: =IF(S37="","",U36*(1+$G$10)) | V37: =IF(S37="","",V36) | W37: =IF(S37="","",V37/12) | X37: =IF(S37="","",X36*(1+$N$13)) | Y37: =IF(S37="","",X37/12) | Z37: =IF(S37="","",U37-(W37+Y37)) | AA37: =IF(S37="","",FV((1+$G$13)^(1/12)-1,12,-Z37,IF(ISNUMBER(AA36),-AA36,0),1))
S38: =IF(S37="","",IF(S37+1<=$G$12,S37+1,"")) | T38: =IF(S38="","",T37+1) | U38: =IF(S38="","",U37*(1+$G$10)) | V38: =IF(S38="","",V37) | W38: =IF(S38="","",V38/12) | X38: =IF(S38="","",X37*(1+$N$13)) | Y38: =IF(S38="","",X38/12) | Z38: =IF(S38="","",U38-(W38+Y38)) | AA38: =IF(S38="","",FV((1+$G$13)^(1/12)-1,12,-Z38,IF(ISNUMBER(AA37),-AA37,0),1))
... S55: =IF(S54="","",IF(S54+1<=$G$12,S54+1,"")) | T55: =IF(S55="","",T54+1) | U55: =IF(S55="","",U54*(1+$G$10)) | V55: =IF(S55="","",V54) | W55: =IF(S55="","",V55/12) | X55: =IF(S55="","",X54*(1+$N$13)) | Y55: =IF(S55="","",X55/12) | Z55: =IF(S55="","",U55-(W55+Y55)) | AA55: =IF(S55="","",FV((1+$G$13)^(1/12)-1,12,-Z55,IF(ISNUMBER(AA54),-AA54,0),1))

Sheet 12
A2: BACK | B2: QUICK CALCYS
B5: SIP FUTURE VALUE | J5: LUMP SUM FUTURE VALUE
B6: SIP investment amount (per month) | F6: 20000 | J6: Lump sum investment amount | N6: 1000000
B7: SIP tenure (no. of years) | F7: 10 | J7: Investment tenure (no. of years) | N7: 10
B8: Expected return from SIP investment | F8: 0.12 | J8: Expected return from SIP investment | N8: 0.12
B9: EXPECTED FUTURE VALUE | F9: =FV((1+F8)^(1/12)-1,F7*12,-F6,,1) -> 4480717.8 | J9: EXPECTED FUTURE VALUE | N9: =FV(N8,N7,,-N6,1) -> 3105848.2
B11: NO. OF YEARS REQD. IN SIP INVESTMENT | J11: NO. OF YEARS REQD. IN LUMP SUM INVESTMENT
B12: SIP investment amount (per month) | F12: 20000 | J12: Lump sum investment amount | N12: 1000000
B13: Target amount of future value | F13: 5000000 | J13: Target amount of future value | N13: 3000000
B14: Expected return from SIP investment | F14: 0.12 | J14: Expected return from lump sum inv. | N14: 0.12
B15: NO. OF YEARS REQUIRED | F15: =NPER((1+F14)^(1/12)-1,-F12,,F13,1)/12 -> 10.667473 | J15: NO. OF YEARS REQUIRED | N15: =NPER(N14,,-N12,N13) -> 9.6940354
B17: REQD. SIP INVESTMENT AMOUNT | J17: REQD. LUMP SUM INVESTMENT AMOUNT
B18: Target amount of future value | F18: 5000000 | J18: Target amount of future value | N18: 3000000
B19: SIP tenure (no. of years) | F19: 10 | J19: Investment tenure (no. of years) | N19: 10
B20: Expected return from SIP investment | F20: 0.12 | J20: Expected return from lump sum inv. | N20: 0.12
B21: REQUIRED SIP INVESTMENT | F21: =-PMT((1+F20)^(1/12)-1,F19*12,,F18,1) -> 22317.853 | J21: REQUIRED LUMP SUM INVESTMENT | N21: =-PV(N20,N19,,N18) -> 965919.71
B23: REQD. RATE OF RETURN IN SIP INVESTMENT | J23: REQD. RATE OF RETURN IN LUMP SUM INVESTMENT
B24: SIP investment amount (per month) | F24: 20000 | J24: Lump sum investment amount | N24: 1000000
B25: Target amount of future value | F25: 5000000 | J25: Target amount of future value | N25: 3000000
B26: SIP tenure (no. of years) | F26: 10 | J26: Investment tenure (no. of years) | N26: 10
B27: REQUIRED RATE OF RETURN | F27: =(1+RATE(F26*12,-F24,,F25,1))^12-1 -> 0.14052944 | J27: REQUIRED RATE OF RETURN | N27: =RATE(N26,,-N24,N25) -> 0.11612317
B28: Prepared for: | J28: Prepared by:
B29: =" "&UPPER('Main Menu'!C29) -> CLIENT NAME | H29: ="Dated: "& TEXT(TODAY(),"DD-MMM-YYYY") -> Dated: 28-Aug-2025 | J29: =" "&UPPER('Main Menu'!L29) -> PARTNER NAME

Sheet DISCLAIMER
A2: BACK | B2: DISCLAIMER
B5: These calculators are designed using mathematical formulas and functions available in Microsoft Excel. Though utmost care has been taken in creating these calculators, but the accuracy of these are not guranteed. It is highly recommended that you cross-check the accuracy of the same by yourself. Certain assumptions are made while designing the calculators. Such assumptions are may or may not be appropriate considering your needs, priorities and risk profile. Result or output are displayed for representational purpose only and investment or insurance decisions should never be taken based on these results or output. Consult your Mutual fund Distributor, Insurance Consultant, Tax Advisor, Registered Investment Advisor etc. before taking any such decisions. Returns from any investment instrument displayed here are not guaranteed and are often subject to market risk and macro economic decisions. Tax laws, regulations etc. may change in the meantime from the date of designing these calculators - so also cross-check the same from authentic and official sources.
